Workbook

Sheet G_Entregas
A1: Etiquetas | B1: UF Destino | C1: Cód. Winthor | D1: [Item] Descrição | E1: [Item] Quantidade | F1: [Item] Data de validade | G1: Nome PJ Emitente | H1: Número | I1: Data Emissão | J1: Mês | K1: Valor Total da Nota | L1: NFs Entrada - Winthor | M1: Previsão De Entrega
A2: PRIVADO | B2: PB | C2: 2187 | D2: IV FIX- FIXADOR ESTERIL IV FIX- FIXADOR ESTERIL | E2: 8 | F2: 46579 | G2: 3M DO BRASIL LTDA | H2: 522375 | I2: 45925 | J2: set | K2: 755.76 | L2: Pendente | M2: =_xlfn.XLOOKUP(relatorio_NF[[#This Row],[Número]],'relatorio_NF'!D:D,'relatorio_NF'!U:U) -> 45936
A3: PRIVADO | B3: PB | C3: 2187 | D3: IV FIX- FIXADOR ESTERIL IV FIX- FIXADOR ESTERIL | E3: 32 | F3: 46579 | G3: 3M DO BRASIL LTDA | H3: 522376 | I3: 45925 | J3: set | K3: 3000.96 | L3: Pendente | M3: =_xlfn.XLOOKUP(relatorio_NF[[#This Row],[Número]],'relatorio_NF'!D:D,'relatorio_NF'!U:U) -> 45936
A4: PUBLICO | B4: PE | C4: 869 | D4: DIPRIVAN 1% PFS 1X50ML BR (C1) ASP | E4: 200 | F4: 46386 | G4: Aspen Pharma Industria Farmaceutica Ltda | H4: 267737 | I4: 45924 | J4: set | K4: 34704 | L4: Pendente | M4: =_xlfn.XLOOKUP(relatorio_NF[[#This Row],[Número]],'relatorio_NF'!D:D,'relatorio_NF'!U:U) -> 45930
A5: PRIVADO | B5: PE | C5: 2382 | D5: NUBEQA 300MG TAFI BT 1X120 BR | E5: 15 | F5: 46721 | G5: Bayer S/A | H5: 288919 | I5: 45924 | J5: set | K5: 176334.37 | L5: Pendente | M5: =_xlfn.XLOOKUP(relatorio_NF[[#This Row],[Número]],'relatorio_NF'!D:D,'relatorio_NF'!U:U) -> 45936
A6: PUBLICO, VALOR DIVERGENTE (PÚBLICO ) | B6: PE | C6: 1514 | D6: URBANIL CPR 10MG X 20 M8 | E6: 45 | F6: 46568 | G6: MOKSHA8 BRASIL INDUSTRIA E COM | H6: 57029 | I6: 45924 | J6: set | K6: 384.62 | L6: Pendente | M6: =_xlfn.XLOOKUP(relatorio_NF[[#This Row],[Número]],'relatorio_NF'!D:D,'relatorio_NF'!U:U) -> 45943
A7: PUBLICO | B7: PB | C7: 3092 | D7: XTANDI TAB 40 4X28 BR | E7: 6 | F7: 46752 | G7: Astellas Farma Brasil Imp e Distrib de Medicamentos Ltda. | H7: 56041 | I7: 45924 | J7: set | K7: 52202.32 | L7: Pendente | M7: =_xlfn.XLOOKUP(relatorio_NF[[#This Row],[Número]],'relatorio_NF'!D:D,'relatorio_NF'!U:U) -> 45932
A8: PUBLICO | B8: PB | C8: 1430 | D8: VOTRIENT 400MG 60 CE | E8: 6 | F8: 46568 | G8: NOVARTIS BIOCIENCIAS SA | H8: 502164 | I8: 45924 | J8: set | K8: 47248.51 | L8: Pendente | M8: =_xlfn.XLOOKUP(relatorio_NF[[#This Row],[Número]],'relatorio_NF'!D:D,'relatorio_NF'!U:U) -> 45936
A9: PUBLICO | B9: PB | C9: 3759 | D9: KISQALI 200 MG 63 CE | E9: 44 | F9: 46326 | G9: NOVARTIS BIOCIENCIAS SA | H9: 502165 | I9: 45924 | J9: set | K9: 517591.34 | L9: Pendente | M9: =_xlfn.XLOOKUP(relatorio_NF[[#This Row],[Número]],'relatorio_NF'!D:D,'relatorio_NF'!U:U) -> 45936
A10: PUBLICO | B10: PB | C10: 2438 | D10: XOLAIR 150MG/1ML (1) SERINGA | E10: 408 | F10: 46265 | G10: NOVARTIS BIOCIENCIAS SA | H10: 50115 | I10: 45924 | J10: set | K10: 160113.55 | L10: Pendente | M10: =_xlfn.XLOOKUP(relatorio_NF[[#This Row],[Número]],'relatorio_NF'!D:D,'relatorio_NF'!U:U) -> 45929
A11: PUBLICO | B11: CE | C11: 2382 | D11: NUBEQA 300MG TAFI BT 1X120 BR | E11: 6 | F11: 46721 | G11: Bayer S/A | H11: 288743 | I11: 45924 | J11: set | K11: 70914.62 | L11: Pendente | M11: =_xlfn.XLOOKUP(relatorio_NF[[#This Row],[Número]],'relatorio_NF'!D:D,'relatorio_NF'!U:U) -> 45936
A12: PRIVADO | B12: CE | C12: 2382 | D12: NUBEQA 300MG TAFI BT 1X120 BR | E12: 15 | F12: 46721 | G12: Bayer S/A | H12: 288920 | I12: 45924 | J12: set | K12: 176332.6 | L12: Pendente | M12: =_xlfn.XLOOKUP(relatorio_NF[[#This Row],[Número]],'relatorio_NF'!D:D,'relatorio_NF'!U:U) -> 45936
A13: PRIVADO | B13: CE | C13: 2575 | D13: ONTAX 300 MG OR | E13: 1 | F13: 46568 | G13: LIBBS FARMACEUTICA Ltda | H13: 343366 | I13: 45924 | J13: set | K13: 318.86 | L13: Pendente | M13: =_xlfn.XLOOKUP(relatorio_NF[[#This Row],[Número]],'relatorio_NF'!D:D,'relatorio_NF'!U:U) -> 45931
... A82: PRIVADO | B82: PE | C82: 2421 | D82: HERZUMA 440 MG/20ML LOTE 5A6C222 Fab.:5/7/2025 Val.:2/28/2031 | E82: 48 | F82: 47907 | G82: CELLTRION HEALTHCARE DIST PROD FARMACEUTICOS DO BRASIL LTDA | H82: 8207 | I82: 45919 | J82: set | K82: 66240 | L82: Pendente | M82: =_xlfn.XLOOKUP(relatorio_NF[[#This Row],[Número]],'relatorio_NF'!D:D,'relatorio_NF'!U:U) -> 45929
A83: PUBLICO | B83: PE | C83: 3143 | D83: CANULA NASAL PARA OXIGENOTERAPIA GMI FR:06 - 2,10 M (NEONATAL) | E83: 300 | G83: GABISA MEDICAL INTERNATIONAL S.A. | H83: 36372 | I83: 45919 | J83: set | K83: 4904.17 | L83: Pendente | M83: =_xlfn.XLOOKUP(relatorio_NF[[#This Row],[Número]],'relatorio_NF'!D:D,'relatorio_NF'!U:U) -> 45943
A84: PUBLICO | B84: PE | C84: 3329 | D84: 1657R TEGADERM CHG CX C/25 3M TEGADERM CHG | E84: 40 | F84: 46471 | G84: 3M DO BRASIL LTDA | H84: 511798 | I84: 45919 | J84: set | K84: 50686.4 | L84: Pendente | M84: =_xlfn.XLOOKUP(relatorio_NF[[#This Row],[Número]],'relatorio_NF'!D:D,'relatorio_NF'!U:U) -> 45933
A85: PRIVADO | B85: PE | C85: 1344 | D85: REVOLADE 50MG 14 CE | E85: 5 | F85: 46446 | G85: NOVARTIS BIOCIENCIAS SA | H85: 501817 | I85: 45919 | J85: set | K85: 20125.53 | L85: Pendente | M85: =_xlfn.XLOOKUP(relatorio_NF[[#This Row],[Número]],'relatorio_NF'!D:D,'relatorio_NF'!U:U) -> 45929
A86: PRIVADO | B86: PB | C86: 3280 | D86: YUFLYMA SC 40MG/0,4ML LOTE 3LAT06T1D Fab.:9/19/2023 Val.:8/31/2026 | E86: 60 | F86: 46265 | G86: CELLTRION HEALTHCARE DIST PROD FARMACEUTICOS DO BRASIL LTDA | H86: 8204 | I86: 45919 | J86: set | K86: 52231.2 | L86: Pendente | M86: =_xlfn.XLOOKUP(relatorio_NF[[#This Row],[Número]],'relatorio_NF'!D:D,'relatorio_NF'!U:U) -> 45926
A87: PRIVADO | B87: PB | C87: 3143 | D87: CANULA NASAL PARA OXIGENOTERAPIA GMI FR:06 - 2,10 M (NEONATAL) | E87: 144 | G87: GABISA MEDICAL INTERNATIONAL S.A. | H87: 36370 | I87: 45919 | J87: set | K87: 2827.7 | L87: Pendente | M87: =_xlfn.XLOOKUP(relatorio_NF[[#This Row],[Número]],'relatorio_NF'!D:D,'relatorio_NF'!U:U) -> 45943
A88: PRIVADO | B88: PB | C88: 3149 | D88: CATETER UMBILICAL GMI FR:2,5 | E88: 10 | G88: GABISA MEDICAL INTERNATIONAL S.A. | H88: 36370 | I88: 45919 | J88: set | K88: 2827.7 | L88: Pendente | M88: =_xlfn.XLOOKUP(relatorio_NF[[#This Row],[Número]],'relatorio_NF'!D:D,'relatorio_NF'!U:U) -> 45943
A89: PRIVADO | B89: PB | C89: 3155 | D89: GABILINK - EXTENSOR VALVULADO SAFETY GMI NEONATAL 2 VIAS | E89: 50 | G89: GABISA MEDICAL INTERNATIONAL S.A. | H89: 36370 | I89: 45919 | J89: set | K89: 2827.7 | L89: Pendente | M89: =_xlfn.XLOOKUP(relatorio_NF[[#This Row],[Número]],'relatorio_NF'!D:D,'relatorio_NF'!U:U) -> 45943
A90: PRIVADO | B90: PB | C90: 3762 | D90: 54500 MANTA AQ UNDBD AD C/10 3M BAIR HUGGER MANTA 54500 | E90: 2 | F90: 46877 | G90: 3M DO BRASIL LTDA | H90: 511799 | I90: 45919 | J90: set | K90: 3259.43 | L90: Pendente | M90: =_xlfn.XLOOKUP(relatorio_NF[[#This Row],[Número]],'relatorio_NF'!D:D,'relatorio_NF'!U:U)
A91: PRIVADO | B91: PB | C91: 2335 | D91: 52500 MANTA AQ MEMBRO INF C/10 3M BAIR HUGGER MANTA 52500 | E91: 2 | F91: 46936 | G91: 3M DO BRASIL LTDA | H91: 511799 | I91: 45919 | J91: set | K91: 3259.43 | L91: Pendente | M91: =_xlfn.XLOOKUP(relatorio_NF[[#This Row],[Número]],'relatorio_NF'!D:D,'relatorio_NF'!U:U)
A92: PUBLICO | B92: PB | C92: 1296 | D92: MEKINIST 2MG 30 CE | E92: 6 | F92: 46326 | G92: NOVARTIS BIOCIENCIAS SA | H92: 501806 | I92: 45919 | J92: set | K92: 83577.69 | L92: Pendente | M92: =_xlfn.XLOOKUP(relatorio_NF[[#This Row],[Número]],'relatorio_NF'!D:D,'relatorio_NF'!U:U) -> 45929
A93: PUBLICO | B93: PB | C93: 1296 | D93: MEKINIST 2MG 30 CE | E93: 2 | F93: 46295 | G93: NOVARTIS BIOCIENCIAS SA | H93: 501807 | I93: 45919 | J93: set | K93: 27859.23 | L93: Pendente | M93: =_xlfn.XLOOKUP(relatorio_NF[[#This Row],[Número]],'relatorio_NF'!D:D,'relatorio_NF'!U:U) -> 45929
A94: PRIVADO | B94: CE | C94: 3199 | D94: ZEJULA 100MG 56CAPS | E94: 2 | F94: 46326 | G94: GLAXOSMITHKLINE BRASIL LTDA | H94: 251539 | I94: 45919 | J94: set | K94: 62349.98 | L94: Pendente | M94: =_xlfn.XLOOKUP(relatorio_NF[[#This Row],[Número]],'relatorio_NF'!D:D,'relatorio_NF'!U:U) -> 45925
A95: PRIVADO | B95: CE | C95: 3335 | D95: ZEJULA 100MG 28CAPS | E95: 2 | F95: 46326 | G95: GLAXOSMITHKLINE BRASIL LTDA | H95: 251539 | I95: 45919 | J95: set | K95: 62349.98 | L95: Pendente | M95: =_xlfn.XLOOKUP(relatorio_NF[[#This Row],[Número]],'relatorio_NF'!D:D,'relatorio_NF'!U:U) -> 45925
A96: PRIVADO | B96: CE | C96: 3335 | D96: ZEJULA 100MG 28CAPS | E96: 1 | F96: 46326 | G96: GLAXOSMITHKLINE BRASIL LTDA | H96: 251540 | I96: 45919 | J96: set | K96: 9407.19 | L96: Pendente | M96: =_xlfn.XLOOKUP(relatorio_NF[[#This Row],[Número]],'relatorio_NF'!D:D,'relatorio_NF'!U:U) -> 45926
A97: PRIVADO | B97: CE | C97: 3199 | D97: ZEJULA 100MG 56CAPS | E97: 1 | F97: 46326 | G97: GLAXOSMITHKLINE BRASIL LTDA | H97: 251541 | I97: 45919 | J97: set | K97: 19689.47 | L97: Pendente | M97: =_xlfn.XLOOKUP(relatorio_NF[[#This Row],[Número]],'relatorio_NF'!D:D,'relatorio_NF'!U:U) -> 45925
A98: PRIVADO | B98: CE | C98: 2889 | D98: VERZENIOS 150MG X30 COMP BL | E98: 20 | F98: 46507 | G98: Eli Lilly do Brasil Ltda. | H98: 447284 | I98: 45919 | J98: set | K98: 142850.65 | L98: Pendente | M98: =_xlfn.XLOOKUP(relatorio_NF[[#This Row],[Número]],'relatorio_NF'!D:D,'relatorio_NF'!U:U) -> 45936
A99: PRIVADO | B99: CE | C99: 3330 | D99: TALTZ AUTOINJECTOR 80MG X 1PEND BL | E99: 50 | F99: 46387 | G99: Eli Lilly do Brasil Ltda. | H99: 447293 | I99: 45919 | J99: set | K99: 222262.18 | L99: Pendente | M99: =_xlfn.XLOOKUP(relatorio_NF[[#This Row],[Número]],'relatorio_NF'!D:D,'relatorio_NF'!U:U) -> 45929
A100: PRIVADO | B100: CE | C100: 3322 | D100: OLUMIANT 4MG X 30 COMP BL | E100: 4 | F100: 46660 | G100: Eli Lilly do Brasil Ltda. | H100: 447294 | I100: 45919 | J100: set | K100: 15615.56 | L100: Pendente | M100: =_xlfn.XLOOKUP(relatorio_NF[[#This Row],[Número]],'relatorio_NF'!D:D,'relatorio_NF'!U:U) -> 45930
A101: PRIVADO | B101: CE | C101: 768 | D101: SANDOSTATIN LAR MPVI 30 MG | E101: 30 | F101: 46812 | G101: NOVARTIS BIOCIENCIAS SA | H101: 501823 | I101: 45919 | J101: set | K101: 237342.09 | L101: Pendente | M101: =_xlfn.XLOOKUP(relatorio_NF[[#This Row],[Número]],'relatorio_NF'!D:D,'relatorio_NF'!U:U) -> 45929
... A166: PRIVADO | B166: CE | C166: 2175 | D166: 1530 50MMX10M CARRETEL FITA CIRURGICA HIPO. MICROPORE | E166: 3960 | F166: 46579 | G166: 3M DO BRASIL LTDA | H166: 509463 | I166: 45917 | J166: set | K166: 106791.55 | L166: Pendente | M166: =_xlfn.XLOOKUP(relatorio_NF[[#This Row],[Número]],'relatorio_NF'!D:D,'relatorio_NF'!U:U) -> 45936
A167: PRIVADO | B167: CE | C167: 2367 | D167: 2269T NEO 10 SC C/ 3 UNID CADA ELETRODO RED DOT | E167: 2 | G167: 3M DO BRASIL LTDA | H167: 509463 | I167: 45917 | J167: set | K167: 106791.55 | L167: Pendente | M167: =_xlfn.XLOOKUP(relatorio_NF[[#This Row],[Número]],'relatorio_NF'!D:D,'relatorio_NF'!U:U) -> 45936
A168: PRIVADO | B168: CE | C168: 2380 | D168: 9160F UNIVERSAL REM CX C/ 200 PLACA ELETROCIRURGICA | E168: 5400 | F168: 46775 | G168: 3M DO BRASIL LTDA | H168: 509463 | I168: 45917 | J168: set | K168: 106791.55 | L168: Pendente | M168: =_xlfn.XLOOKUP(relatorio_NF[[#This Row],[Número]],'relatorio_NF'!D:D,'relatorio_NF'!U:U) -> 45936
A169: PRIVADO | B169: CE | C169: 2332 | D169: 55501 MANTA AQ PED UNDERB C/10 3M BAIR HUGGER MANTA 55501 | E169: 15 | F169: 46862 | G169: 3M DO BRASIL LTDA | H169: 509463 | I169: 45917 | J169: set | K169: 106791.55 | L169: Pendente | M169: =_xlfn.XLOOKUP(relatorio_NF[[#This Row],[Número]],'relatorio_NF'!D:D,'relatorio_NF'!U:U) -> 45936
A170: PRIVADO | B170: CE | C170: 2335 | D170: 52500 MANTA AQ MEMBRO INF C/10 3M BAIR HUGGER MANTA 52500 | E170: 10 | F170: 46936 | G170: 3M DO BRASIL LTDA | H170: 509463 | I170: 45917 | J170: set | K170: 106791.55 | L170: Pendente | M170: =_xlfn.XLOOKUP(relatorio_NF[[#This Row],[Número]],'relatorio_NF'!D:D,'relatorio_NF'!U:U) -> 45936
A171: PRIVADO | B171: CE | C171: 2337 | D171: 63500 MANTA AQ UNDER COMPL C/5 3M BAIR HUGGER MANTA 63500 | E171: 92 | F171: 46945 | G171: 3M DO BRASIL LTDA | H171: 509463 | I171: 45917 | J171: set | K171: 106791.55 | L171: Pendente | M171: =_xlfn.XLOOKUP(relatorio_NF[[#This Row],[Número]],'relatorio_NF'!D:D,'relatorio_NF'!U:U) -> 45936
A172: PRIVADO | B172: CE | C172: 2248 | D172: COBAN NL 2082 50MMX4.5M 3M COBAN NL 2082 50MMX4.5M | E172: 540 | F172: 46910 | G172: 3M DO BRASIL LTDA | H172: 509464 | I172: 45917 | J172: set | K172: 6285.6 | L172: Pendente | M172: =_xlfn.XLOOKUP(relatorio_NF[[#This Row],[Número]],'relatorio_NF'!D:D,'relatorio_NF'!U:U) -> 45933
A173: PRIVADO | B173: CE | C173: 2213 | D173: 3591 9CMX25CM CX C/25 CURATIVO TRANSPARENTE TEGADERM | E173: 68 | F173: 46879 | G173: 3M DO BRASIL LTDA | H173: 509465 | I173: 45917 | J173: set | K173: 356707.4 | L173: Pendente | M173: =_xlfn.XLOOKUP(relatorio_NF[[#This Row],[Número]],'relatorio_NF'!D:D,'relatorio_NF'!U:U) -> 45933
A174: PRIVADO | B174: CE | C174: 2373 | D174: 2223 BRQ ELETRODO P/ MONITORIZ ELETRODO P/ MONITORIZ 2223 BRQ | E174: 23040 | F174: 46570 | G174: 3M DO BRASIL LTDA | H174: 509465 | I174: 45917 | J174: set | K174: 356707.4 | L174: Pendente | M174: =_xlfn.XLOOKUP(relatorio_NF[[#This Row],[Número]],'relatorio_NF'!D:D,'relatorio_NF'!U:U) -> 45933
A175: PRIVADO | B175: CE | C175: 2371 | D175: 2258 BR-N NEONAT SC C/ 50 UN 2258 BR-N NEONAT SC C/ 50 UN | E175: 20 | F175: 46593 | G175: 3M DO BRASIL LTDA | H175: 509465 | I175: 45917 | J175: set | K175: 356707.4 | L175: Pendente | M175: =_xlfn.XLOOKUP(relatorio_NF[[#This Row],[Número]],'relatorio_NF'!D:D,'relatorio_NF'!U:U) -> 45933
A176: PRIVADO | B176: CE | C176: 2240 | D176: CAVILON CREME BARREIRA GBR 92G CAVILON CREME BARREIRA 3392GBR | E176: 1128 | F176: 46431 | G176: 3M DO BRASIL LTDA | H176: 509465 | I176: 45917 | J176: set | K176: 356707.4 | L176: Pendente | M176: =_xlfn.XLOOKUP(relatorio_NF[[#This Row],[Número]],'relatorio_NF'!D:D,'relatorio_NF'!U:U) -> 45933
A177: PRIVADO | B177: CE | C177: 2209 | D177: 3M FIXADOR TUBOS SONDAS NASAL 3M FIXADOR TUBOS SONDAS NASAL | E177: 16 | F177: 46584 | G177: 3M DO BRASIL LTDA | H177: 509465 | I177: 45917 | J177: set | K177: 356707.4 | L177: Pendente | M177: =_xlfn.XLOOKUP(relatorio_NF[[#This Row],[Número]],'relatorio_NF'!D:D,'relatorio_NF'!U:U) -> 45933
A178: PRIVADO | B178: CE | C178: 2173 | D178: 1530 12.5MMX10M CARRETEL 1530 12.5MMX10M CARRETEL | E178: 120 | F178: 46551 | G178: 3M DO BRASIL LTDA | H178: 509465 | I178: 45917 | J178: set | K178: 356707.4 | L178: Pendente | M178: =_xlfn.XLOOKUP(relatorio_NF[[#This Row],[Número]],'relatorio_NF'!D:D,'relatorio_NF'!U:U) -> 45933
A179: PRIVADO | B179: CE | C179: 2177 | D179: 1533 12.5MMX10M CARRETEL (RL) 1533 12.5MMX10M CARRETEL (RL) | E179: 120 | F179: 46557 | G179: 3M DO BRASIL LTDA | H179: 509465 | I179: 45917 | J179: set | K179: 356707.4 | L179: Pendente | M179: =_xlfn.XLOOKUP(relatorio_NF[[#This Row],[Número]],'relatorio_NF'!D:D,'relatorio_NF'!U:U) -> 45933
... A211: PRIVADO | B211: CE | C211: 2213 | D211: 3591 9CMX25CM CX C/25 CURATIVO TRANSPARENTE TEGADERM | E211: 4 | F211: 46879 | G211: 3M DO BRASIL LTDA | H211: 509471 | I211: 45917 | J211: set | K211: 11656.73 | L211: Pendente | M211: =_xlfn.XLOOKUP(relatorio_NF[[#This Row],[Número]],'relatorio_NF'!D:D,'relatorio_NF'!U:U) -> 45933
A212: PRIVADO | B212: CE | C212: 2373 | D212: 2223 BRQ ELETRODO P/ MONITORIZ ELETRODO P/ MONITORIZ 2223 BRQ | E212: 20 | G212: 3M DO BRASIL LTDA | H212: 509471 | I212: 45917 | J212: set | K212: 11656.73 | L212: Pendente | M212: =_xlfn.XLOOKUP(relatorio_NF[[#This Row],[Número]],'relatorio_NF'!D:D,'relatorio_NF'!U:U) -> 45933
A213: PRIVADO | B213: CE | C213: 2240 | D213: CAVILON CREME BARREIRA GBR 92G CAVILON CREME BARREIRA 3392GBR | E213: 12 | F213: 46431 | G213: 3M DO BRASIL LTDA | H213: 509471 | I213: 45917 | J213: set | K213: 11656.73 | L213: Pendente | M213: =_xlfn.XLOOKUP(relatorio_NF[[#This Row],[Número]],'relatorio_NF'!D:D,'relatorio_NF'!U:U) -> 45933
A214: PRIVADO | B214: CE | C214: 3561 | D214: 1685 IV ADV 8.5CMX11.5CM CX 50 3M TEGADERM IV ADVANCED | E214: 4 | F214: 46897 | G214: 3M DO BRASIL LTDA | H214: 509471 | I214: 45917 | J214: set | K214: 11656.73 | L214: Pendente | M214: =_xlfn.XLOOKUP(relatorio_NF[[#This Row],[Número]],'relatorio_NF'!D:D,'relatorio_NF'!U:U) -> 45933
A215: PRIVADO | B215: CE | C215: 3547 | D215: 1683BR IV ADV 6.5CMX7CM CX 100 3M TEGADERM IV ADV FIX AVANC | E215: 4 | F215: 46920 | G215: 3M DO BRASIL LTDA | H215: 509471 | I215: 45917 | J215: set | K215: 11656.73 | L215: Pendente | M215: =_xlfn.XLOOKUP(relatorio_NF[[#This Row],[Número]],'relatorio_NF'!D:D,'relatorio_NF'!U:U) -> 45933
A216: PRIVADO | B216: CE | C216: 3479 | D216: 1610 CX C/100 5CMX5.7CM 3M TEGADERM IV CURATIVO | E216: 4 | F216: 46853 | G216: 3M DO BRASIL LTDA | H216: 509471 | I216: 45917 | J216: set | K216: 11656.73 | L216: Pendente | M216: =_xlfn.XLOOKUP(relatorio_NF[[#This Row],[Número]],'relatorio_NF'!D:D,'relatorio_NF'!U:U) -> 45933
A217: PRIVADO | B217: CE | C217: 2213 | D217: 3591 9CMX25CM CX C/25 CURATIVO TRANSPARENTE TEGADERM | E217: 4 | F217: 46879 | G217: 3M DO BRASIL LTDA | H217: 509472 | I217: 45917 | J217: set | K217: 18308.64 | L217: Pendente | M217: =_xlfn.XLOOKUP(relatorio_NF[[#This Row],[Número]],'relatorio_NF'!D:D,'relatorio_NF'!U:U) -> 45933
A218: PRIVADO | B218: CE | C218: 3547 | D218: 1683BR IV ADV 6.5CMX7CM CX 100 3M TEGADERM IV ADV FIX AVANC | E218: 32 | F218: 46920 | G218: 3M DO BRASIL LTDA | H218: 509472 | I218: 45917 | J218: set | K218: 18308.64 | L218: Pendente | M218: =_xlfn.XLOOKUP(relatorio_NF[[#This Row],[Número]],'relatorio_NF'!D:D,'relatorio_NF'!U:U) -> 45933
A219: PRIVADO | B219: CE | C219: 2199 | D219: 1680 IV ADV 3.8X4.5CM CX C/100 3M TEGAD IV ADV CURAT FIX AVAN | E219: 4 | F219: 46891 | G219: 3M DO BRASIL LTDA | H219: 509473 | I219: 45917 | J219: set | K219: 7108 | L219: Pendente | M219: =_xlfn.XLOOKUP(relatorio_NF[[#This Row],[Número]],'relatorio_NF'!D:D,'relatorio_NF'!U:U) -> 45933
A220: PRIVADO | B220: CE | C220: 3479 | D220: 1610 CX C/100 5CMX5.7CM 3M TEGADERM IV CURATIVO | E220: 4 | F220: 46853 | G220: 3M DO BRASIL LTDA | H220: 509473 | I220: 45917 | J220: set | K220: 7108 | L220: Pendente | M220: =_xlfn.XLOOKUP(relatorio_NF[[#This Row],[Número]],'relatorio_NF'!D:D,'relatorio_NF'!U:U) -> 45933
A221: PRIVADO | B221: CE | C221: 2180 | D221: 1527 100MMX4,5M CARRETEL FITA HIPOALERGENICA TRANSPORE | E221: 80 | F221: 46563 | G221: 3M DO BRASIL LTDA | H221: 509474 | I221: 45917 | J221: set | K221: 11167.19 | L221: Pendente | M221: =_xlfn.XLOOKUP(relatorio_NF[[#This Row],[Número]],'relatorio_NF'!D:D,'relatorio_NF'!U:U) -> 45936
A222: PRIVADO | B222: CE | C222: 2175 | D222: 1530 50MMX10M CARRETEL FITA CIRURGICA HIPO. MICROPORE | E222: 160 | F222: 46579 | G222: 3M DO BRASIL LTDA | H222: 509474 | I222: 45917 | J222: set | K222: 11167.19 | L222: Pendente | M222: =_xlfn.XLOOKUP(relatorio_NF[[#This Row],[Número]],'relatorio_NF'!D:D,'relatorio_NF'!U:U) -> 45936
A223: PRIVADO | B223: CE | C223: 2367 | D223: 2269T NEO 10 SC C/ 3 UNID CADA ELETRODO RED DOT | E223: 7 | F223: 46549 | G223: 3M DO BRASIL LTDA | H223: 509474 | I223: 45917 | J223: set | K223: 11167.19 | L223: Pendente | M223: =_xlfn.XLOOKUP(relatorio_NF[[#This Row],[Número]],'relatorio_NF'!D:D,'relatorio_NF'!U:U) -> 45936
A224: PRIVADO | B224: CE | C224: 2333 | D224: 30000 MANTA AQ CORPO INT C/10 3M BAIR HUGGER MANTA 30000 | E224: 1 | F224: 46902 | G224: 3M DO BRASIL LTDA | H224: 509474 | I224: 45917 | J224: set | K224: 11167.19 | L224: Pendente | M224: =_xlfn.XLOOKUP(relatorio_NF[[#This Row],[Número]],'relatorio_NF'!D:D,'relatorio_NF'!U:U) -> 45936
... A241: PRIVADO | B241: CE | C241: 2332 | D241: 55501 MANTA AQ PED UNDERB C/10 3M BAIR HUGGER MANTA 55501 | E241: 1 | F241: 46862 | G241: 3M DO BRASIL LTDA | H241: 509479 | I241: 45917 | J241: set | K241: 44867.08 | L241: Pendente | M241: =_xlfn.XLOOKUP(relatorio_NF[[#This Row],[Número]],'relatorio_NF'!D:D,'relatorio_NF'!U:U) -> 45936
A242: PRIVADO | B242: CE | C242: 2333 | D242: 30000 MANTA AQ CORPO INT C/10 3M BAIR HUGGER MANTA 30000 | E242: 9 | G242: 3M DO BRASIL LTDA | H242: 509479 | I242: 45917 | J242: set | K242: 44867.08 | L242: Pendente | M242: =_xlfn.XLOOKUP(relatorio_NF[[#This Row],[Número]],'relatorio_NF'!D:D,'relatorio_NF'!U:U) -> 45936
A243: PRIVADO | B243: CE | C243: 2337 | D243: 63500 MANTA AQ UNDER COMPL C/5 3M BAIR HUGGER MANTA 63500 | E243: 50 | F243: 46945 | G243: 3M DO BRASIL LTDA | H243: 509479 | I243: 45917 | J243: set | K243: 44867.08 | L243: Pendente | M243: =_xlfn.XLOOKUP(relatorio_NF[[#This Row],[Número]],'relatorio_NF'!D:D,'relatorio_NF'!U:U) -> 45936
A244: PRIVADO | B244: CE | C244: 2248 | D244: COBAN NL 2082 50MMX4.5M 3M COBAN NL 2082 50MMX4.5M | E244: 36 | F244: 46910 | G244: 3M DO BRASIL LTDA | H244: 509479 | I244: 45917 | J244: set | K244: 44867.08 | L244: Pendente | M244: =_xlfn.XLOOKUP(relatorio_NF[[#This Row],[Número]],'relatorio_NF'!D:D,'relatorio_NF'!U:U) -> 45936
A245: PRIVADO | B245: CE | C245: 2241 | D245: CAVILON LIMP. PELE S/ ENXAGUE CAVILON | E245: 60 | F245: 46630 | G245: 3M DO BRASIL LTDA | H245: 509480 | I245: 45917 | J245: set | K245: 19713.2 | L245: Pendente | M245: =_xlfn.XLOOKUP(relatorio_NF[[#This Row],[Número]],'relatorio_NF'!D:D,'relatorio_NF'!U:U) -> 45929
A246: PRIVADO | B246: CE | C246: 2240 | D246: CAVILON CREME BARREIRA GBR 92G CAVILON CREME BARREIRA 3392GBR | E246: 96 | F246: 46431 | G246: 3M DO BRASIL LTDA | H246: 509480 | I246: 45917 | J246: set | K246: 19713.2 | L246: Pendente | M246: =_xlfn.XLOOKUP(relatorio_NF[[#This Row],[Número]],'relatorio_NF'!D:D,'relatorio_NF'!U:U) -> 45929
A247: PRIVADO | B247: CE | C247: 2209 | D247: 3M FIXADOR TUBOS SONDAS NASAL 3M FIXADOR TUBOS SONDAS NASAL | E247: 4 | F247: 46584 | G247: 3M DO BRASIL LTDA | H247: 509480 | I247: 45917 | J247: set | K247: 19713.2 | L247: Pendente | M247: =_xlfn.XLOOKUP(relatorio_NF[[#This Row],[Número]],'relatorio_NF'!D:D,'relatorio_NF'!U:U) -> 45929
A248: PRIVADO | B248: CE | C248: 2956 | D248: 2861BR-4 2.5CMX4M CX C/ 48 3M MEDIPORE H BR FITA MEDICA | E248: 48 | F248: 46962 | G248: 3M DO BRASIL LTDA | H248: 509480 | I248: 45917 | J248: set | K248: 19713.2 | L248: Pendente | M248: =_xlfn.XLOOKUP(relatorio_NF[[#This Row],[Número]],'relatorio_NF'!D:D,'relatorio_NF'!U:U) -> 45929
A249: PRIVADO | B249: CE | C249: 2958 | D249: 2864BR-4 10CMX4M CX C/ 24 3M MEDIPORE H BR FITA MEDICA | E249: 96 | F249: 46914 | G249: 3M DO BRASIL LTDA | H249: 509480 | I249: 45917 | J249: set | K249: 19713.2 | L249: Pendente | M249: =_xlfn.XLOOKUP(relatorio_NF[[#This Row],[Número]],'relatorio_NF'!D:D,'relatorio_NF'!U:U) -> 45929
A250: PRIVADO | B250: CE | C250: 3551 | D250: 1660R TEGADERM CHG CX C/25 3M TEGADERM CHG | E250: 4 | F250: 46450 | G250: 3M DO BRASIL LTDA | H250: 509480 | I250: 45917 | J250: set | K250: 19713.2 | L250: Pendente | M250: =_xlfn.XLOOKUP(relatorio_NF[[#This Row],[Número]],'relatorio_NF'!D:D,'relatorio_NF'!U:U) -> 45929
A251: PRIVADO | B251: CE | C251: 3286 | D251: 1682 IV ADV 5X5.7CM CX C/100 3M TEGAD IV ADV CURAT FIX AVAN | E251: 4 | F251: 46824 | G251: 3M DO BRASIL LTDA | H251: 509480 | I251: 45917 | J251: set | K251: 19713.2 | L251: Pendente | M251: =_xlfn.XLOOKUP(relatorio_NF[[#This Row],[Número]],'relatorio_NF'!D:D,'relatorio_NF'!U:U) -> 45929
A252: PRIVADO | B252: CE | C252: 3345 | D252: 1626W 10.0CMX12.0CM CX C/50 CURATIVO TRANSPARENTE TEGADERM | E252: 4 | F252: 46839 | G252: 3M DO BRASIL LTDA | H252: 509480 | I252: 45917 | J252: set | K252: 19713.2 | L252: Pendente | M252: =_xlfn.XLOOKUP(relatorio_NF[[#This Row],[Número]],'relatorio_NF'!D:D,'relatorio_NF'!U:U) -> 45929
A253: PRIVADO | B253: CE | C253: 3547 | D253: 1683BR IV ADV 6.5CMX7CM CX 100 3M TEGADERM IV ADV FIX AVANC | E253: 12 | F253: 46920 | G253: 3M DO BRASIL LTDA | H253: 509481 | I253: 45917 | J253: set | K253: 3767.64 | L253: Pendente | M253: =_xlfn.XLOOKUP(relatorio_NF[[#This Row],[Número]],'relatorio_NF'!D:D,'relatorio_NF'!U:U) -> 45918
A254: PRIVADO | B254: CE | C254: 2180 | D254: 1527 100MMX4,5M CARRETEL FITA HIPOALERGENICA TRANSPORE | E254: 20 | F254: 46563 | G254: 3M DO BRASIL LTDA | H254: 509482 | I254: 45917 | J254: set | K254: 4009.97 | L254: Pendente | M254: =_xlfn.XLOOKUP(relatorio_NF[[#This Row],[Número]],'relatorio_NF'!D:D,'relatorio_NF'!U:U) -> 45936
A255: PRIVADO | B255: CE | C255: 2221 | D255: 16010-10 BR ROLO 10X10 3M TEGADERM EM ROLO | E255: 4 | F255: 46613 | G255: 3M DO BRASIL LTDA | H255: 509482 | I255: 45917 | J255: set | K255: 4009.97 | L255: Pendente | M255: =_xlfn.XLOOKUP(relatorio_NF[[#This Row],[Número]],'relatorio_NF'!D:D,'relatorio_NF'!U:U) -> 45936
A256: PRIVADO | B256: CE | C256: 2333 | D256: 30000 MANTA AQ CORPO INT C/10 3M BAIR HUGGER MANTA 30000 | E256: 1 | G256: 3M DO BRASIL LTDA | H256: 509482 | I256: 45917 | J256: set | K256: 4009.97 | L256: Pendente | M256: =_xlfn.XLOOKUP(relatorio_NF[[#This Row],[Número]],'relatorio_NF'!D:D,'relatorio_NF'!U:U) -> 45936
A257: PRIVADO | B257: CE | C257: 2335 | D257: 52500 MANTA AQ MEMBRO INF C/10 3M BAIR HUGGER MANTA 52500 | E257: 1 | F257: 46936 | G257: 3M DO BRASIL LTDA | H257: 509482 | I257: 45917 | J257: set | K257: 4009.97 | L257: Pendente | M257: =_xlfn.XLOOKUP(relatorio_NF[[#This Row],[Número]],'relatorio_NF'!D:D,'relatorio_NF'!U:U) -> 45936
A258: PRIVADO | B258: CE | C258: 2337 | D258: 63500 MANTA AQ UNDER COMPL C/5 3M BAIR HUGGER MANTA 63500 | E258: 1 | F258: 46946 | G258: 3M DO BRASIL LTDA | H258: 509482 | I258: 45917 | J258: set | K258: 4009.97 | L258: Pendente | M258: =_xlfn.XLOOKUP(relatorio_NF[[#This Row],[Número]],'relatorio_NF'!D:D,'relatorio_NF'!U:U) -> 45936
A259: PRIVADO | B259: CE | C259: 2248 | D259: COBAN NL 2082 50MMX4.5M 3M COBAN NL 2082 50MMX4.5M | E259: 36 | F259: 46910 | G259: 3M DO BRASIL LTDA | H259: 509482 | I259: 45917 | J259: set | K259: 4009.97 | L259: Pendente | M259: =_xlfn.XLOOKUP(relatorio_NF[[#This Row],[Número]],'relatorio_NF'!D:D,'relatorio_NF'!U:U) -> 45936
A260: PRIVADO | B260: CE | C260: 2241 | D260: CAVILON LIMP. PELE S/ ENXAGUE CAVILON | E260: 6 | F260: 46630 | G260: 3M DO BRASIL LTDA | H260: 509483 | I260: 45917 | J260: set | K260: 12749.88 | L260: Pendente | M260: =_xlfn.XLOOKUP(relatorio_NF[[#This Row],[Número]],'relatorio_NF'!D:D,'relatorio_NF'!U:U) -> 45929
A261: PRIVADO | B261: CE | C261: 2240 | D261: CAVILON CREME BARREIRA GBR 92G CAVILON CREME BARREIRA 3392GBR | E261: 12 | F261: 46431 | G261: 3M DO BRASIL LTDA | H261: 509483 | I261: 45917 | J261: set | K261: 12749.88 | L261: Pendente | M261: =_xlfn.XLOOKUP(relatorio_NF[[#This Row],[Número]],'relatorio_NF'!D:D,'relatorio_NF'!U:U) -> 45929
A262: PRIVADO | B262: CE | C262: 2958 | D262: 2864BR-4 10CMX4M CX C/ 24 3M MEDIPORE H BR FITA MEDICA | E262: 24 | F262: 46914 | G262: 3M DO BRASIL LTDA | H262: 509483 | I262: 45917 | J262: set | K262: 12749.88 | L262: Pendente | M262: =_xlfn.XLOOKUP(relatorio_NF[[#This Row],[Número]],'relatorio_NF'!D:D,'relatorio_NF'!U:U) -> 45929
A263: PRIVADO | B263: CE | C263: 3551 | D263: 1660R TEGADERM CHG CX C/25 3M TEGADERM CHG | E263: 4 | F263: 46450 | G263: 3M DO BRASIL LTDA | H263: 509483 | I263: 45917 | J263: set | K263: 12749.88 | L263: Pendente | M263: =_xlfn.XLOOKUP(relatorio_NF[[#This Row],[Número]],'relatorio_NF'!D:D,'relatorio_NF'!U:U) -> 45929
A264: PRIVADO | B264: CE | C264: 3561 | D264: 1685 IV ADV 8.5CMX11.5CM CX 50 3M TEGADERM IV ADVANCED | E264: 4 | F264: 46897 | G264: 3M DO BRASIL LTDA | H264: 509483 | I264: 45917 | J264: set | K264: 12749.88 | L264: Pendente | M264: =_xlfn.XLOOKUP(relatorio_NF[[#This Row],[Número]],'relatorio_NF'!D:D,'relatorio_NF'!U:U) -> 45929
A265: PRIVADO | B265: CE | C265: 3286 | D265: 1682 IV ADV 5X5.7CM CX C/100 3M TEGAD IV ADV CURAT FIX AVAN | E265: 4 | F265: 46824 | G265: 3M DO BRASIL LTDA | H265: 509483 | I265: 45917 | J265: set | K265: 12749.88 | L265: Pendente | M265: =_xlfn.XLOOKUP(relatorio_NF[[#This Row],[Número]],'relatorio_NF'!D:D,'relatorio_NF'!U:U) -> 45929
A266: PRIVADO | B266: CE | C266: 3345 | D266: 1626W 10.0CMX12.0CM CX C/50 CURATIVO TRANSPARENTE TEGADERM | E266: 4 | F266: 46839 | G266: 3M DO BRASIL LTDA | H266: 509483 | I266: 45917 | J266: set | K266: 12749.88 | L266: Pendente | M266: =_xlfn.XLOOKUP(relatorio_NF[[#This Row],[Número]],'relatorio_NF'!D:D,'relatorio_NF'!U:U) -> 45929
A267: PRIVADO | B267: CE | C267: 3547 | D267: 1683BR IV ADV 6.5CMX7CM CX 100 3M TEGADERM IV ADV FIX AVANC | E267: 4 | F267: 46920 | G267: 3M DO BRASIL LTDA | H267: 509483 | I267: 45917 | J267: set | K267: 12749.88 | L267: Pendente | M267: =_xlfn.XLOOKUP(relatorio_NF[[#This Row],[Número]],'relatorio_NF'!D:D,'relatorio_NF'!U:U) -> 45929
A268: PRIVADO | B268: CE | C268: 3399 | D268: FIX SONDA NASAL GDE 1501NG 3M FIXADOR DE SONDA NASAL | E268: 4 | F268: 46234 | G268: 3M DO BRASIL LTDA | H268: 509484 | I268: 45917 | J268: set | K268: 2218.24 | L268: Pendente | M268: =_xlfn.XLOOKUP(relatorio_NF[[#This Row],[Número]],'relatorio_NF'!D:D,'relatorio_NF'!U:U)
... A341: PRIVADO | B341: PB | C341: 2175 | D341: 1530 50MMX10M CARRETEL FITA CIRURGICA HIPO. MICROPORE | E341: 120 | F341: 46572 | G341: 3M DO BRASIL LTDA | H341: 508642 | I341: 45916 | J341: set | K341: 3703.78 | L341: Pendente | M341: =_xlfn.XLOOKUP(relatorio_NF[[#This Row],[Número]],'relatorio_NF'!D:D,'relatorio_NF'!U:U) -> 45933
A342: PRIVADO | B342: PB | C342: 2333 | D342: 30000 MANTA AQ CORPO INT C/10 3M BAIR HUGGER MANTA 30000 | E342: 2 | G342: 3M DO BRASIL LTDA | H342: 508642 | I342: 45916 | J342: set | K342: 3703.78 | L342: Pendente | M342: =_xlfn.XLOOKUP(relatorio_NF[[#This Row],[Número]],'relatorio_NF'!D:D,'relatorio_NF'!U:U) -> 45933
A343: PRIVADO | B343: PB | C343: 2192 | D343: 1633BR IV 7.0CMX7.0CM CX C/100 TEGADERM IV CURAT E FIX TRANSP | E343: 4 | F343: 46544 | G343: 3M DO BRASIL LTDA | H343: 508646 | I343: 45916 | J343: set | K343: 13568.96 | L343: Pendente | M343: =_xlfn.XLOOKUP(relatorio_NF[[#This Row],[Número]],'relatorio_NF'!D:D,'relatorio_NF'!U:U) -> 45932
A344: PRIVADO | B344: PB | C344: 2240 | D344: CAVILON CREME BARREIRA GBR 92G CAVILON CREME BARREIRA 3392GBR | E344: 12 | F344: 46431 | G344: 3M DO BRASIL LTDA | H344: 508646 | I344: 45916 | J344: set | K344: 13568.96 | L344: Pendente | M344: =_xlfn.XLOOKUP(relatorio_NF[[#This Row],[Número]],'relatorio_NF'!D:D,'relatorio_NF'!U:U) -> 45932
A345: PRIVADO | B345: PB | C345: 2209 | D345: 3M FIXADOR TUBOS SONDAS NASAL 3M FIXADOR TUBOS SONDAS NASAL | E345: 4 | F345: 46584 | G345: 3M DO BRASIL LTDA | H345: 508646 | I345: 45916 | J345: set | K345: 13568.96 | L345: Pendente | M345: =_xlfn.XLOOKUP(relatorio_NF[[#This Row],[Número]],'relatorio_NF'!D:D,'relatorio_NF'!U:U) -> 45932
A346: PRIVADO | B346: PB | C346: 2182 | D346: 2770-1 MICROP S 2.5CMX5M CX 12 3M MICROPORE S 2770-1 | E346: 120 | F346: 46787 | G346: 3M DO BRASIL LTDA | H346: 508646 | I346: 45916 | J346: set | K346: 13568.96 | L346: Pendente | M346: =_xlfn.XLOOKUP(relatorio_NF[[#This Row],[Número]],'relatorio_NF'!D:D,'relatorio_NF'!U:U) -> 45932
A347: PRIVADO | B347: PB | C347: 2957 | D347: 2862BR-4 5CMX4M CX C/ 24 3M MEDIPORE H BR FITA MEDICA | E347: 24 | F347: 46910 | G347: 3M DO BRASIL LTDA | H347: 508646 | I347: 45916 | J347: set | K347: 13568.96 | L347: Pendente | M347: =_xlfn.XLOOKUP(relatorio_NF[[#This Row],[Número]],'relatorio_NF'!D:D,'relatorio_NF'!U:U) -> 45932
A348: PRIVADO | B348: PB | C348: 3329 | D348: 1657R TEGADERM CHG CX C/25 3M TEGADERM CHG | E348: 4 | F348: 46476 | G348: 3M DO BRASIL LTDA | H348: 508646 | I348: 45916 | J348: set | K348: 13568.96 | L348: Pendente | M348: =_xlfn.XLOOKUP(relatorio_NF[[#This Row],[Número]],'relatorio_NF'!D:D,'relatorio_NF'!U:U) -> 45932
A349: PRIVADO | B349: PB | C349: 3345 | D349: 1626W 10.0CMX12.0CM CX C/50 CURATIVO TRANSPARENTE TEGADERM | E349: 4 | F349: 46839 | G349: 3M DO BRASIL LTDA | H349: 508646 | I349: 45916 | J349: set | K349: 13568.96 | L349: Pendente | M349: =_xlfn.XLOOKUP(relatorio_NF[[#This Row],[Número]],'relatorio_NF'!D:D,'relatorio_NF'!U:U) -> 45932
A350: PRIVADO | B350: PB | C350: 2219 | D350: 1627 10.0CMX25.0CM CX C/20 CURATIVO TRANSPARENTE TEGADERM | E350: 4 | F350: 46890 | G350: 3M DO BRASIL LTDA | H350: 508646 | I350: 45916 | J350: set | K350: 13568.96 | L350: Pendente | M350: =_xlfn.XLOOKUP(relatorio_NF[[#This Row],[Número]],'relatorio_NF'!D:D,'relatorio_NF'!U:U) -> 45932
A351: PRIVADO | B351: PB | C351: 2373 | D351: 2223 BRQ ELETRODO P/ MONITORIZ ELETRODO P/ MONITORIZ 2223 BRQ | E351: 20 | F351: 46134 | G351: 3M DO BRASIL LTDA | H351: 508648 | I351: 45916 | J351: set | K351: 7992.01 | L351: Pendente | M351: =_xlfn.XLOOKUP(relatorio_NF[[#This Row],[Número]],'relatorio_NF'!D:D,'relatorio_NF'!U:U) -> 45933
...

Sheet relatorio_NF
A1: Etiquetas | B1: UF Destino | C1: Nome PJ Emitente | D1: Número | E1: Data Emissão | F1: Valor Total da Nota | G1: [Item] EAN | H1: [Item] Código | I1: [Item] Descrição | J1: [Item] Data de validade | K1: [Item] Quantidade | L1: De_Para | M1: EAN | N1: Mês | O1: NFs Entrada - Winthor | P1: Natureza | Q1: Cód. Winthor | R1: CTE | S1: Dt. CTE | T1: Previsão de entrega - Bruto | U1: Previsão de entrega
A2: PRIVADO | B2: PB | C2: 3M DO BRASIL LTDA | D2: 522375 | E2: 45925 | F2: 755.76 | G2: 7891040118168 | H2: HB004244164 | I2: IV FIX- FIXADOR ESTERIL IV FIX- FIXADOR ESTERIL | J2: 46579 | K2: 8 | L2: =_xlfn.XLOOKUP(relatorio[[#This Row],[Nome PJ Emitente]],De_Para!A:A,De_Para!C:C) -> 3M | M2: {=IF(LEFT(G2&"",1)="0", IFERROR( VALUE(MID(G2&"",_xlfn.AGGREGATE(15,6,ROW(INDIRECT("1:"&LEN(G2&"")))/(MID(G2&"",ROW(INDIRECT("1:"&LEN(G2&""))),1)<>"0"),1),999)), MID(G2&"",_xlfn.AGGREGATE(15,6,ROW(INDIRECT("1:"&LEN(G2&"")))/(MID(G2&"",ROW(INDIRECT("1:"&LEN(G2&""))),1)<>"0"),1),999) ), IFERROR(VALUE(G2),G2))} -> 7891040118168 | N2: =TEXT(relatorio[[#This Row],[Data Emissão]],"mmm") -> set | O2: =_xlfn.XLOOKUP(relatorio[[#This Row],[Número]],relatorio_Entrada_NF!A:A,relatorio_Entrada_NF!A:A,"Pendente") -> Pendente | P2: =_xlfn.XLOOKUP(relatorio[[#This Row],[Nome PJ Emitente]],Material!A:A,Material!B:B,"Medicamento") -> Material | Q2: =IF(relatorio[[#This Row],[Natureza]]="Medicamento",_xlfn.XLOOKUP(relatorio[[#This Row],[EAN]],CadastroProd!U:U,CadastroProd!A:A," "),_xlfn.XLOOKUP(relatorio[[#This Row],['[Item'] Código]],CadastroProd!X:X,CadastroProd!A:A," ")) -> 2187 | R2: =IF(O2="Pendente",_xlfn.XLOOKUP(relatorio[[#This Row],[Número]],Relatório_CTE!A:A,Relatório_CTE!B:B,"Sem CTE")," ") -> Sem CTE | S2: =IF(relatorio[[#This Row],[NFs Entrada - Winthor]]="Pendente",_xlfn.XLOOKUP(relatorio[[#This Row],[Número]],Relatório_CTE!A:A,Relatório_CTE!H:H,"Sem CTE")," ") -> Sem CTE | T2: =(IF(relatorio[[#This Row],[NFs Entrada - Winthor]]="Pendente",IF(relatorio[[#This Row],[Dt. CTE]]="Sem CTE",relatorio[[#This Row],[Data Emissão]]+_xlfn.XLOOKUP(relatorio[[#This Row],[De_Para]],'Lead Time - Histórico (Fornec.)'!B:B,'Lead Time - Histórico (Fornec.)'!C:C),relatorio[[#This Row],[Dt. CTE]]+_xlfn.XLOOKUP(relatorio[[#This Row],[Cód. Winthor]],'Lead Time - Histórico (Produto)'!A:A,'Lead Time - Histórico (Produto)'!C:C))," ")) -> 45936 | U2: =IFERROR(IF(WEEKDAY(relatorio[[#This Row],[Previsão de entrega - Bruto]],2)=6,relatorio[[#This Row],[Previsão de entrega - Bruto]]+2,IF(WEEKDAY(relatorio[[#This Row],[Previsão de entrega - Bruto]],2)=7,relatorio[[#This Row],[Previsão de entrega - Bruto]]+1,relatorio[[#This Row],[Previsão de entrega - Bruto]]))," ") -> 45936
A3: PRIVADO | B3: PB | C3: 3M DO BRASIL LTDA | D3: 522376 | E3: 45925 | F3: 3000.96 | G3: 7891040118168 | H3: HB004244164 | I3: IV FIX- FIXADOR ESTERIL IV FIX- FIXADOR ESTERIL | J3: 46579 | K3: 32 | L3: =_xlfn.XLOOKUP(relatorio[[#This Row],[Nome PJ Emitente]],De_Para!A:A,De_Para!C:C) -> 3M | M3: {=IF(LEFT(G3&"",1)="0", IFERROR( VALUE(MID(G3&"",_xlfn.AGGREGATE(15,6,ROW(INDIRECT("1:"&LEN(G3&"")))/(MID(G3&"",ROW(INDIRECT("1:"&LEN(G3&""))),1)<>"0"),1),999)), MID(G3&"",_xlfn.AGGREGATE(15,6,ROW(INDIRECT("1:"&LEN(G3&"")))/(MID(G3&"",ROW(INDIRECT("1:"&LEN(G3&""))),1)<>"0"),1),999) ), IFERROR(VALUE(G3),G3))} -> 7891040118168 | N3: =TEXT(relatorio[[#This Row],[Data Emissão]],"mmm") -> set | O3: =_xlfn.XLOOKUP(relatorio[[#This Row],[Número]],relatorio_Entrada_NF!A:A,relatorio_Entrada_NF!A:A,"Pendente") -> Pendente | P3: =_xlfn.XLOOKUP(relatorio[[#This Row],[Nome PJ Emitente]],Material!A:A,Material!B:B,"Medicamento") -> Material | Q3: =IF(relatorio[[#This Row],[Natureza]]="Medicamento",_xlfn.XLOOKUP(relatorio[[#This Row],[EAN]],CadastroProd!U:U,CadastroProd!A:A," "),_xlfn.XLOOKUP(relatorio[[#This Row],['[Item'] Código]],CadastroProd!X:X,CadastroProd!A:A," ")) -> 2187 | R3: =IF(O3="Pendente",_xlfn.XLOOKUP(relatorio[[#This Row],[Número]],Relatório_CTE!A:A,Relatório_CTE!B:B,"Sem CTE")," ") -> Sem CTE | S3: =IF(relatorio[[#This Row],[NFs Entrada - Winthor]]="Pendente",_xlfn.XLOOKUP(relatorio[[#This Row],[Número]],Relatório_CTE!A:A,Relatório_CTE!H:H,"Sem CTE")," ") -> Sem CTE | T3: =(IF(relatorio[[#This Row],[NFs Entrada - Winthor]]="Pendente",IF(relatorio[[#This Row],[Dt. CTE]]="Sem CTE",relatorio[[#This Row],[Data Emissão]]+_xlfn.XLOOKUP(relatorio[[#This Row],[De_Para]],'Lead Time - Histórico (Fornec.)'!B:B,'Lead Time - Histórico (Fornec.)'!C:C),relatorio[[#This Row],[Dt. CTE]]+_xlfn.XLOOKUP(relatorio[[#This Row],[Cód. Winthor]],'Lead Time - Histórico (Produto)'!A:A,'Lead Time - Histórico (Produto)'!C:C))," ")) -> 45936 | U3: =IFERROR(IF(WEEKDAY(relatorio[[#This Row],[Previsão de entrega - Bruto]],2)=6,relatorio[[#This Row],[Previsão de entrega - Bruto]]+2,IF(WEEKDAY(relatorio[[#This Row],[Previsão de entrega - Bruto]],2)=7,relatorio[[#This Row],[Previsão de entrega - Bruto]]+1,relatorio[[#This Row],[Previsão de entrega - Bruto]]))," ") -> 45936
A4: PUBLICO | B4: PE | C4: Aspen Pharma Industria Farmaceutica Ltda | D4: 267737 | E4: 45924 | F4: 34704 | G4: 7895858016821 | H4: 000000000007057867 | I4: DIPRIVAN 1% PFS 1X50ML BR (C1) ASP | J4: 46386 | K4: 200 | L4: =_xlfn.XLOOKUP(relatorio[[#This Row],[Nome PJ Emitente]],De_Para!A:A,De_Para!C:C) -> Aspen | M4: {=IF(LEFT(G4&"",1)="0", IFERROR( VALUE(MID(G4&"",_xlfn.AGGREGATE(15,6,ROW(INDIRECT("1:"&LEN(G4&"")))/(MID(G4&"",ROW(INDIRECT("1:"&LEN(G4&""))),1)<>"0"),1),999)), MID(G4&"",_xlfn.AGGREGATE(15,6,ROW(INDIRECT("1:"&LEN(G4&"")))/(MID(G4&"",ROW(INDIRECT("1:"&LEN(G4&""))),1)<>"0"),1),999) ), IFERROR(VALUE(G4),G4))} -> 7895858016821 | N4: =TEXT(relatorio[[#This Row],[Data Emissão]],"mmm") -> set | O4: =_xlfn.XLOOKUP(relatorio[[#This Row],[Número]],relatorio_Entrada_NF!A:A,relatorio_Entrada_NF!A:A,"Pendente") -> Pendente | P4: =_xlfn.XLOOKUP(relatorio[[#This Row],[Nome PJ Emitente]],Material!A:A,Material!B:B,"Medicamento") -> Medicamento | Q4: =IF(relatorio[[#This Row],[Natureza]]="Medicamento",_xlfn.XLOOKUP(relatorio[[#This Row],[EAN]],CadastroProd!U:U,CadastroProd!A:A," "),_xlfn.XLOOKUP(relatorio[[#This Row],['[Item'] Código]],CadastroProd!X:X,CadastroProd!A:A," ")) -> 869 | R4: =IF(O4="Pendente",_xlfn.XLOOKUP(relatorio[[#This Row],[Número]],Relatório_CTE!A:A,Relatório_CTE!B:B,"Sem CTE")," ") -> Sem CTE | S4: =IF(relatorio[[#This Row],[NFs Entrada - Winthor]]="Pendente",_xlfn.XLOOKUP(relatorio[[#This Row],[Número]],Relatório_CTE!A:A,Relatório_CTE!H:H,"Sem CTE")," ") -> Sem CTE | T4: =(IF(relatorio[[#This Row],[NFs Entrada - Winthor]]="Pendente",IF(relatorio[[#This Row],[Dt. CTE]]="Sem CTE",relatorio[[#This Row],[Data Emissão]]+_xlfn.XLOOKUP(relatorio[[#This Row],[De_Para]],'Lead Time - Histórico (Fornec.)'!B:B,'Lead Time - Histórico (Fornec.)'!C:C),relatorio[[#This Row],[Dt. CTE]]+_xlfn.XLOOKUP(relatorio[[#This Row],[Cód. Winthor]],'Lead Time - Histórico (Produto)'!A:A,'Lead Time - Histórico (Produto)'!C:C))," ")) -> 45930 | U4: =IFERROR(IF(WEEKDAY(relatorio[[#This Row],[Previsão de entrega - Bruto]],2)=6,relatorio[[#This Row],[Previsão de entrega - Bruto]]+2,IF(WEEKDAY(relatorio[[#This Row],[Previsão de entrega - Bruto]],2)=7,relatorio[[#This Row],[Previsão de entrega - Bruto]]+1,relatorio[[#This Row],[Previsão de entrega - Bruto]]))," ") -> 45930
A5: PRIVADO | B5: PE | C5: Bayer S/A | D5: 288919 | E5: 45924 | F5: 176334.37 | G5: 7891106913881 | H5: 000000000086961458 | I5: NUBEQA 300MG TAFI BT 1X120 BR | J5: 46721 | K5: 15 | L5: =_xlfn.XLOOKUP(relatorio[[#This Row],[Nome PJ Emitente]],De_Para!A:A,De_Para!C:C) -> Bayer | M5: {=IF(LEFT(G5&"",1)="0", IFERROR( VALUE(MID(G5&"",_xlfn.AGGREGATE(15,6,ROW(INDIRECT("1:"&LEN(G5&"")))/(MID(G5&"",ROW(INDIRECT("1:"&LEN(G5&""))),1)<>"0"),1),999)), MID(G5&"",_xlfn.AGGREGATE(15,6,ROW(INDIRECT("1:"&LEN(G5&"")))/(MID(G5&"",ROW(INDIRECT("1:"&LEN(G5&""))),1)<>"0"),1),999) ), IFERROR(VALUE(G5),G5))} -> 7891106913881 | N5: =TEXT(relatorio[[#This Row],[Data Emissão]],"mmm") -> set | O5: =_xlfn.XLOOKUP(relatorio[[#This Row],[Número]],relatorio_Entrada_NF!A:A,relatorio_Entrada_NF!A:A,"Pendente") -> Pendente | P5: =_xlfn.XLOOKUP(relatorio[[#This Row],[Nome PJ Emitente]],Material!A:A,Material!B:B,"Medicamento") -> Medicamento | Q5: =IF(relatorio[[#This Row],[Natureza]]="Medicamento",_xlfn.XLOOKUP(relatorio[[#This Row],[EAN]],CadastroProd!U:U,CadastroProd!A:A," "),_xlfn.XLOOKUP(relatorio[[#This Row],['[Item'] Código]],CadastroProd!X:X,CadastroProd!A:A," ")) -> 2382 | R5: =IF(O5="Pendente",_xlfn.XLOOKUP(relatorio[[#This Row],[Número]],Relatório_CTE!A:A,Relatório_CTE!B:B,"Sem CTE")," ") -> Sem CTE | S5: =IF(relatorio[[#This Row],[NFs Entrada - Winthor]]="Pendente",_xlfn.XLOOKUP(relatorio[[#This Row],[Número]],Relatório_CTE!A:A,Relatório_CTE!H:H,"Sem CTE")," ") -> Sem CTE | T5: =(IF(relatorio[[#This Row],[NFs Entrada - Winthor]]="Pendente",IF(relatorio[[#This Row],[Dt. CTE]]="Sem CTE",relatorio[[#This Row],[Data Emissão]]+_xlfn.XLOOKUP(relatorio[[#This Row],[De_Para]],'Lead Time - Histórico (Fornec.)'!B:B,'Lead Time - Histórico (Fornec.)'!C:C),relatorio[[#This Row],[Dt. CTE]]+_xlfn.XLOOKUP(relatorio[[#This Row],[Cód. Winthor]],'Lead Time - Histórico (Produto)'!A:A,'Lead Time - Histórico (Produto)'!C:C))," ")) -> 45935 | U5: =IFERROR(IF(WEEKDAY(relatorio[[#This Row],[Previsão de entrega - Bruto]],2)=6,relatorio[[#This Row],[Previsão de entrega - Bruto]]+2,IF(WEEKDAY(relatorio[[#This Row],[Previsão de entrega - Bruto]],2)=7,relatorio[[#This Row],[Previsão de entrega - Bruto]]+1,relatorio[[#This Row],[Previsão de entrega - Bruto]]))," ") -> 45936
A6: PUBLICO, VALOR DIVERGENTE (PÚBLICO ) | B6: PE | C6: MOKSHA8 BRASIL INDUSTRIA E COM | D6: 57029 | E6: 45924 | F6: 384.62 | G6: 7898216367955 | H6: 100497 | I6: URBANIL CPR 10MG X 20 M8 | J6: 46568 | K6: 45 | L6: =_xlfn.XLOOKUP(relatorio[[#This Row],[Nome PJ Emitente]],De_Para!A:A,De_Para!C:C) -> Moksha8 | M6: {=IF(LEFT(G6&"",1)="0", IFERROR( VALUE(MID(G6&"",_xlfn.AGGREGATE(15,6,ROW(INDIRECT("1:"&LEN(G6&"")))/(MID(G6&"",ROW(INDIRECT("1:"&LEN(G6&""))),1)<>"0"),1),999)), MID(G6&"",_xlfn.AGGREGATE(15,6,ROW(INDIRECT("1:"&LEN(G6&"")))/(MID(G6&"",ROW(INDIRECT("1:"&LEN(G6&""))),1)<>"0"),1),999) ), IFERROR(VALUE(G6),G6))} -> 7898216367955 | N6: =TEXT(relatorio[[#This Row],[Data Emissão]],"mmm") -> set | O6: =_xlfn.XLOOKUP(relatorio[[#This Row],[Número]],relatorio_Entrada_NF!A:A,relatorio_Entrada_NF!A:A,"Pendente") -> Pendente | P6: =_xlfn.XLOOKUP(relatorio[[#This Row],[Nome PJ Emitente]],Material!A:A,Material!B:B,"Medicamento") -> Medicamento | Q6: =IF(relatorio[[#This Row],[Natureza]]="Medicamento",_xlfn.XLOOKUP(relatorio[[#This Row],[EAN]],CadastroProd!U:U,CadastroProd!A:A," "),_xlfn.XLOOKUP(relatorio[[#This Row],['[Item'] Código]],CadastroProd!X:X,CadastroProd!A:A," ")) -> 1514 | R6: =IF(O6="Pendente",_xlfn.XLOOKUP(relatorio[[#This Row],[Número]],Relatório_CTE!A:A,Relatório_CTE!B:B,"Sem CTE")," ") -> Sem CTE | S6: =IF(relatorio[[#This Row],[NFs Entrada - Winthor]]="Pendente",_xlfn.XLOOKUP(relatorio[[#This Row],[Número]],Relatório_CTE!A:A,Relatório_CTE!H:H,"Sem CTE")," ") -> Sem CTE | T6: =(IF(relatorio[[#This Row],[NFs Entrada - Winthor]]="Pendente",IF(relatorio[[#This Row],[Dt. CTE]]="Sem CTE",relatorio[[#This Row],[Data Emissão]]+_xlfn.XLOOKUP(relatorio[[#This Row],[De_Para]],'Lead Time - Histórico (Fornec.)'!B:B,'Lead Time - Histórico (Fornec.)'!C:C),relatorio[[#This Row],[Dt. CTE]]+_xlfn.XLOOKUP(relatorio[[#This Row],[Cód. Winthor]],'Lead Time - Histórico (Produto)'!A:A,'Lead Time - Histórico (Produto)'!C:C))," ")) -> 45942 | U6: =IFERROR(IF(WEEKDAY(relatorio[[#This Row],[Previsão de entrega - Bruto]],2)=6,relatorio[[#This Row],[Previsão de entrega - Bruto]]+2,IF(WEEKDAY(relatorio[[#This Row],[Previsão de entrega - Bruto]],2)=7,relatorio[[#This Row],[Previsão de entrega - Bruto]]+1,relatorio[[#This Row],[Previsão de entrega - Bruto]]))," ") -> 45943
A7: PUBLICO | B7: PB | C7: Astellas Farma Brasil Imp e Distrib de Medicamentos Ltda. | D7: 56041 | E7: 45924 | F7: 52202.32 | G7: 7899337001070 | H7: 1000861 | I7: XTANDI TAB 40 4X28 BR | J7: 46752 | K7: 6 | L7: =_xlfn.XLOOKUP(relatorio[[#This Row],[Nome PJ Emitente]],De_Para!A:A,De_Para!C:C) -> Astellas | M7: {=IF(LEFT(G7&"",1)="0", IFERROR( VALUE(MID(G7&"",_xlfn.AGGREGATE(15,6,ROW(INDIRECT("1:"&LEN(G7&"")))/(MID(G7&"",ROW(INDIRECT("1:"&LEN(G7&""))),1)<>"0"),1),999)), MID(G7&"",_xlfn.AGGREGATE(15,6,ROW(INDIRECT("1:"&LEN(G7&"")))/(MID(G7&"",ROW(INDIRECT("1:"&LEN(G7&""))),1)<>"0"),1),999) ), IFERROR(VALUE(G7),G7))} -> 7899337001070 | N7: =TEXT(relatorio[[#This Row],[Data Emissão]],"mmm") -> set | O7: =_xlfn.XLOOKUP(relatorio[[#This Row],[Número]],relatorio_Entrada_NF!A:A,relatorio_Entrada_NF!A:A,"Pendente") -> Pendente | P7: =_xlfn.XLOOKUP(relatorio[[#This Row],[Nome PJ Emitente]],Material!A:A,Material!B:B,"Medicamento") -> Medicamento | Q7: =IF(relatorio[[#This Row],[Natureza]]="Medicamento",_xlfn.XLOOKUP(relatorio[[#This Row],[EAN]],CadastroProd!U:U,CadastroProd!A:A," "),_xlfn.XLOOKUP(relatorio[[#This Row],['[Item'] Código]],CadastroProd!X:X,CadastroProd!A:A," ")) -> 3092 | R7: =IF(O7="Pendente",_xlfn.XLOOKUP(relatorio[[#This Row],[Número]],Relatório_CTE!A:A,Relatório_CTE!B:B,"Sem CTE")," ") -> Sem CTE | S7: =IF(relatorio[[#This Row],[NFs Entrada - Winthor]]="Pendente",_xlfn.XLOOKUP(relatorio[[#This Row],[Número]],Relatório_CTE!A:A,Relatório_CTE!H:H,"Sem CTE")," ") -> Sem CTE | T7: =(IF(relatorio[[#This Row],[NFs Entrada - Winthor]]="Pendente",IF(relatorio[[#This Row],[Dt. CTE]]="Sem CTE",relatorio[[#This Row],[Data Emissão]]+_xlfn.XLOOKUP(relatorio[[#This Row],[De_Para]],'Lead Time - Histórico (Fornec.)'!B:B,'Lead Time - Histórico (Fornec.)'!C:C),relatorio[[#This Row],[Dt. CTE]]+_xlfn.XLOOKUP(relatorio[[#This Row],[Cód. Winthor]],'Lead Time - Histórico (Produto)'!A:A,'Lead Time - Histórico (Produto)'!C:C))," ")) -> 45932 | U7: =IFERROR(IF(WEEKDAY(relatorio[[#This Row],[Previsão de entrega - Bruto]],2)=6,relatorio[[#This Row],[Previsão de entrega - Bruto]]+2,IF(WEEKDAY(relatorio[[#This Row],[Previsão de entrega - Bruto]],2)=7,relatorio[[#This Row],[Previsão de entrega - Bruto]]+1,relatorio[[#This Row],[Previsão de entrega - Bruto]]))," ") -> 45932
A8: PUBLICO | B8: PB | C8: NOVARTIS BIOCIENCIAS SA | D8: 502164 | E8: 45924 | F8: 47248.51 | G8: 7896261020795 | H8: 733310 | I8: VOTRIENT 400MG 60 CE | J8: 46568 | K8: 6 | L8: =_xlfn.XLOOKUP(relatorio[[#This Row],[Nome PJ Emitente]],De_Para!A:A,De_Para!C:C) -> Novartis | M8: {=IF(LEFT(G8&"",1)="0", IFERROR( VALUE(MID(G8&"",_xlfn.AGGREGATE(15,6,ROW(INDIRECT("1:"&LEN(G8&"")))/(MID(G8&"",ROW(INDIRECT("1:"&LEN(G8&""))),1)<>"0"),1),999)), MID(G8&"",_xlfn.AGGREGATE(15,6,ROW(INDIRECT("1:"&LEN(G8&"")))/(MID(G8&"",ROW(INDIRECT("1:"&LEN(G8&""))),1)<>"0"),1),999) ), IFERROR(VALUE(G8),G8))} -> 7896261020795 | N8: =TEXT(relatorio[[#This Row],[Data Emissão]],"mmm") -> set | O8: =_xlfn.XLOOKUP(relatorio[[#This Row],[Número]],relatorio_Entrada_NF!A:A,relatorio_Entrada_NF!A:A,"Pendente") -> Pendente | P8: =_xlfn.XLOOKUP(relatorio[[#This Row],[Nome PJ Emitente]],Material!A:A,Material!B:B,"Medicamento") -> Medicamento | Q8: =IF(relatorio[[#This Row],[Natureza]]="Medicamento",_xlfn.XLOOKUP(relatorio[[#This Row],[EAN]],CadastroProd!U:U,CadastroProd!A:A," "),_xlfn.XLOOKUP(relatorio[[#This Row],['[Item'] Código]],CadastroProd!X:X,CadastroProd!A:A," ")) -> 1430 | R8: =IF(O8="Pendente",_xlfn.XLOOKUP(relatorio[[#This Row],[Número]],Relatório_CTE!A:A,Relatório_CTE!B:B,"Sem CTE")," ") -> Sem CTE | S8: =IF(relatorio[[#This Row],[NFs Entrada - Winthor]]="Pendente",_xlfn.XLOOKUP(relatorio[[#This Row],[Número]],Relatório_CTE!A:A,Relatório_CTE!H:H,"Sem CTE")," ") -> Sem CTE | T8: =(IF(relatorio[[#This Row],[NFs Entrada - Winthor]]="Pendente",IF(relatorio[[#This Row],[Dt. CTE]]="Sem CTE",relatorio[[#This Row],[Data Emissão]]+_xlfn.XLOOKUP(relatorio[[#This Row],[De_Para]],'Lead Time - Histórico (Fornec.)'!B:B,'Lead Time - Histórico (Fornec.)'!C:C),relatorio[[#This Row],[Dt. CTE]]+_xlfn.XLOOKUP(relatorio[[#This Row],[Cód. Winthor]],'Lead Time - Histórico (Produto)'!A:A,'Lead Time - Histórico (Produto)'!C:C))," ")) -> 45934 | U8: =IFERROR(IF(WEEKDAY(relatorio[[#This Row],[Previsão de entrega - Bruto]],2)=6,relatorio[[#This Row],[Previsão de entrega - Bruto]]+2,IF(WEEKDAY(relatorio[[#This Row],[Previsão de entrega - Bruto]],2)=7,relatorio[[#This Row],[Previsão de entrega - Bruto]]+1,relatorio[[#This Row],[Previsão de entrega - Bruto]]))," ") -> 45936
A9: PUBLICO | B9: PB | C9: NOVARTIS BIOCIENCIAS SA | D9: 502165 | E9: 45924 | F9: 517591.34 | G9: 7896261023185 | H9: 302105 | I9: KISQALI 200 MG 63 CE | J9: 46326 | K9: 44 | L9: =_xlfn.XLOOKUP(relatorio[[#This Row],[Nome PJ Emitente]],De_Para!A:A,De_Para!C:C) -> Novartis | M9: {=IF(LEFT(G9&"",1)="0", IFERROR( VALUE(MID(G9&"",_xlfn.AGGREGATE(15,6,ROW(INDIRECT("1:"&LEN(G9&"")))/(MID(G9&"",ROW(INDIRECT("1:"&LEN(G9&""))),1)<>"0"),1),999)), MID(G9&"",_xlfn.AGGREGATE(15,6,ROW(INDIRECT("1:"&LEN(G9&"")))/(MID(G9&"",ROW(INDIRECT("1:"&LEN(G9&""))),1)<>"0"),1),999) ), IFERROR(VALUE(G9),G9))} -> 7896261023185 | N9: =TEXT(relatorio[[#This Row],[Data Emissão]],"mmm") -> set | O9: =_xlfn.XLOOKUP(relatorio[[#This Row],[Número]],relatorio_Entrada_NF!A:A,relatorio_Entrada_NF!A:A,"Pendente") -> Pendente | P9: =_xlfn.XLOOKUP(relatorio[[#This Row],[Nome PJ Emitente]],Material!A:A,Material!B:B,"Medicamento") -> Medicamento | Q9: =IF(relatorio[[#This Row],[Natureza]]="Medicamento",_xlfn.XLOOKUP(relatorio[[#This Row],[EAN]],CadastroProd!U:U,CadastroProd!A:A," "),_xlfn.XLOOKUP(relatorio[[#This Row],['[Item'] Código]],CadastroProd!X:X,CadastroProd!A:A," ")) -> 3759 | R9: =IF(O9="Pendente",_xlfn.XLOOKUP(relatorio[[#This Row],[Número]],Relatório_CTE!A:A,Relatório_CTE!B:B,"Sem CTE")," ") -> Sem CTE | S9: =IF(relatorio[[#This Row],[NFs Entrada - Winthor]]="Pendente",_xlfn.XLOOKUP(relatorio[[#This Row],[Número]],Relatório_CTE!A:A,Relatório_CTE!H:H,"Sem CTE")," ") -> Sem CTE | T9: =(IF(relatorio[[#This Row],[NFs Entrada - Winthor]]="Pendente",IF(relatorio[[#This Row],[Dt. CTE]]="Sem CTE",relatorio[[#This Row],[Data Emissão]]+_xlfn.XLOOKUP(relatorio[[#This Row],[De_Para]],'Lead Time - Histórico (Fornec.)'!B:B,'Lead Time - Histórico (Fornec.)'!C:C),relatorio[[#This Row],[Dt. CTE]]+_xlfn.XLOOKUP(relatorio[[#This Row],[Cód. Winthor]],'Lead Time - Histórico (Produto)'!A:A,'Lead Time - Histórico (Produto)'!C:C))," ")) -> 45934 | U9: =IFERROR(IF(WEEKDAY(relatorio[[#This Row],[Previsão de entrega - Bruto]],2)=6,relatorio[[#This Row],[Previsão de entrega - Bruto]]+2,IF(WEEKDAY(relatorio[[#This Row],[Previsão de entrega - Bruto]],2)=7,relatorio[[#This Row],[Previsão de entrega - Bruto]]+1,relatorio[[#This Row],[Previsão de entrega - Bruto]]))," ") -> 45936
A10: PUBLICO | B10: PB | C10: NOVARTIS BIOCIENCIAS SA | D10: 50115 | E10: 45924 | F10: 160113.55 | G10: 7896261020382 | H10: 749202 | I10: XOLAIR 150MG/1ML (1) SERINGA | J10: 46265 | K10: 408 | L10: =_xlfn.XLOOKUP(relatorio[[#This Row],[Nome PJ Emitente]],De_Para!A:A,De_Para!C:C) -> Novartis | M10: {=IF(LEFT(G10&"",1)="0", IFERROR( VALUE(MID(G10&"",_xlfn.AGGREGATE(15,6,ROW(INDIRECT("1:"&LEN(G10&"")))/(MID(G10&"",ROW(INDIRECT("1:"&LEN(G10&""))),1)<>"0"),1),999)), MID(G10&"",_xlfn.AGGREGATE(15,6,ROW(INDIRECT("1:"&LEN(G10&"")))/(MID(G10&"",ROW(INDIRECT("1:"&LEN(G10&""))),1)<>"0"),1),999) ), IFERROR(VALUE(G10),G10))} -> 7896261020382 | N10: =TEXT(relatorio[[#This Row],[Data Emissão]],"mmm") -> set | O10: =_xlfn.XLOOKUP(relatorio[[#This Row],[Número]],relatorio_Entrada_NF!A:A,relatorio_Entrada_NF!A:A,"Pendente") -> Pendente | P10: =_xlfn.XLOOKUP(relatorio[[#This Row],[Nome PJ Emitente]],Material!A:A,Material!B:B,"Medicamento") -> Medicamento | Q10: =IF(relatorio[[#This Row],[Natureza]]="Medicamento",_xlfn.XLOOKUP(relatorio[[#This Row],[EAN]],CadastroProd!U:U,CadastroProd!A:A," "),_xlfn.XLOOKUP(relatorio[[#This Row],['[Item'] Código]],CadastroProd!X:X,CadastroProd!A:A," ")) -> 2438 | R10: =IF(O10="Pendente",_xlfn.XLOOKUP(relatorio[[#This Row],[Número]],Relatório_CTE!A:A,Relatório_CTE!B:B,"Sem CTE")," ") -> 6778 | S10: =IF(relatorio[[#This Row],[NFs Entrada - Winthor]]="Pendente",_xlfn.XLOOKUP(relatorio[[#This Row],[Número]],Relatório_CTE!A:A,Relatório_CTE!H:H,"Sem CTE")," ") -> 45924 | T10: =(IF(relatorio[[#This Row],[NFs Entrada - Winthor]]="Pendente",IF(relatorio[[#This Row],[Dt. CTE]]="Sem CTE",relatorio[[#This Row],[Data Emissão]]+_xlfn.XLOOKUP(relatorio[[#This Row],[De_Para]],'Lead Time - Histórico (Fornec.)'!B:B,'Lead Time - Histórico (Fornec.)'!C:C),relatorio[[#This Row],[Dt. CTE]]+_xlfn.XLOOKUP(relatorio[[#This Row],[Cód. Winthor]],'Lead Time - Histórico (Produto)'!A:A,'Lead Time - Histórico (Produto)'!C:C))," ")) -> 45929 | U10: =IFERROR(IF(WEEKDAY(relatorio[[#This Row],[Previsão de entrega - Bruto]],2)=6,relatorio[[#This Row],[Previsão de entrega - Bruto]]+2,IF(WEEKDAY(relatorio[[#This Row],[Previsão de entrega - Bruto]],2)=7,relatorio[[#This Row],[Previsão de entrega - Bruto]]+1,relatorio[[#This Row],[Previsão de entrega - Bruto]]))," ") -> 45929
A11: PUBLICO | B11: CE | C11: Bayer S/A | D11: 288743 | E11: 45924 | F11: 70914.62 | G11: 7891106913881 | H11: 000000000086961458 | I11: NUBEQA 300MG TAFI BT 1X120 BR | J11: 46721 | K11: 6 | L11: =_xlfn.XLOOKUP(relatorio[[#This Row],[Nome PJ Emitente]],De_Para!A:A,De_Para!C:C) -> Bayer | M11: {=IF(LEFT(G11&"",1)="0", IFERROR( VALUE(MID(G11&"",_xlfn.AGGREGATE(15,6,ROW(INDIRECT("1:"&LEN(G11&"")))/(MID(G11&"",ROW(INDIRECT("1:"&LEN(G11&""))),1)<>"0"),1),999)), MID(G11&"",_xlfn.AGGREGATE(15,6,ROW(INDIRECT("1:"&LEN(G11&"")))/(MID(G11&"",ROW(INDIRECT("1:"&LEN(G11&""))),1)<>"0"),1),999) ), IFERROR(VALUE(G11),G11))} -> 7891106913881 | N11: =TEXT(relatorio[[#This Row],[Data Emissão]],"mmm") -> set | O11: =_xlfn.XLOOKUP(relatorio[[#This Row],[Número]],relatorio_Entrada_NF!A:A,relatorio_Entrada_NF!A:A,"Pendente") -> Pendente | P11: =_xlfn.XLOOKUP(relatorio[[#This Row],[Nome PJ Emitente]],Material!A:A,Material!B:B,"Medicamento") -> Medicamento | Q11: =IF(relatorio[[#This Row],[Natureza]]="Medicamento",_xlfn.XLOOKUP(relatorio[[#This Row],[EAN]],CadastroProd!U:U,CadastroProd!A:A," "),_xlfn.XLOOKUP(relatorio[[#This Row],['[Item'] Código]],CadastroProd!X:X,CadastroProd!A:A," ")) -> 2382 | R11: =IF(O11="Pendente",_xlfn.XLOOKUP(relatorio[[#This Row],[Número]],Relatório_CTE!A:A,Relatório_CTE!B:B,"Sem CTE")," ") -> Sem CTE | S11: =IF(relatorio[[#This Row],[NFs Entrada - Winthor]]="Pendente",_xlfn.XLOOKUP(relatorio[[#This Row],[Número]],Relatório_CTE!A:A,Relatório_CTE!H:H,"Sem CTE")," ") -> Sem CTE | T11: =(IF(relatorio[[#This Row],[NFs Entrada - Winthor]]="Pendente",IF(relatorio[[#This Row],[Dt. CTE]]="Sem CTE",relatorio[[#This Row],[Data Emissão]]+_xlfn.XLOOKUP(relatorio[[#This Row],[De_Para]],'Lead Time - Histórico (Fornec.)'!B:B,'Lead Time - Histórico (Fornec.)'!C:C),relatorio[[#This Row],[Dt. CTE]]+_xlfn.XLOOKUP(relatorio[[#This Row],[Cód. Winthor]],'Lead Time - Histórico (Produto)'!A:A,'Lead Time - Histórico (Produto)'!C:C))," ")) -> 45935 | U11: =IFERROR(IF(WEEKDAY(relatorio[[#This Row],[Previsão de entrega - Bruto]],2)=6,relatorio[[#This Row],[Previsão de entrega - Bruto]]+2,IF(WEEKDAY(relatorio[[#This Row],[Previsão de entrega - Bruto]],2)=7,relatorio[[#This Row],[Previsão de entrega - Bruto]]+1,relatorio[[#This Row],[Previsão de entrega - Bruto]]))," ") -> 45936
A12: PRIVADO | B12: CE | C12: Bayer S/A | D12: 288920 | E12: 45924 | F12: 176332.6 | G12: 7891106913881 | H12: 000000000086961458 | I12: NUBEQA 300MG TAFI BT 1X120 BR | J12: 46721 | K12: 15 | L12: =_xlfn.XLOOKUP(relatorio[[#This Row],[Nome PJ Emitente]],De_Para!A:A,De_Para!C:C) -> Bayer | M12: {=IF(LEFT(G12&"",1)="0", IFERROR( VALUE(MID(G12&"",_xlfn.AGGREGATE(15,6,ROW(INDIRECT("1:"&LEN(G12&"")))/(MID(G12&"",ROW(INDIRECT("1:"&LEN(G12&""))),1)<>"0"),1),999)), MID(G12&"",_xlfn.AGGREGATE(15,6,ROW(INDIRECT("1:"&LEN(G12&"")))/(MID(G12&"",ROW(INDIRECT("1:"&LEN(G12&""))),1)<>"0"),1),999) ), IFERROR(VALUE(G12),G12))} -> 7891106913881 | N12: =TEXT(relatorio[[#This Row],[Data Emissão]],"mmm") -> set | O12: =_xlfn.XLOOKUP(relatorio[[#This Row],[Número]],relatorio_Entrada_NF!A:A,relatorio_Entrada_NF!A:A,"Pendente") -> Pendente | P12: =_xlfn.XLOOKUP(relatorio[[#This Row],[Nome PJ Emitente]],Material!A:A,Material!B:B,"Medicamento") -> Medicamento | Q12: =IF(relatorio[[#This Row],[Natureza]]="Medicamento",_xlfn.XLOOKUP(relatorio[[#This Row],[EAN]],CadastroProd!U:U,CadastroProd!A:A," "),_xlfn.XLOOKUP(relatorio[[#This Row],['[Item'] Código]],CadastroProd!X:X,CadastroProd!A:A," ")) -> 2382 | R12: =IF(O12="Pendente",_xlfn.XLOOKUP(relatorio[[#This Row],[Número]],Relatório_CTE!A:A,Relatório_CTE!B:B,"Sem CTE")," ") -> Sem CTE | S12: =IF(relatorio[[#This Row],[NFs Entrada - Winthor]]="Pendente",_xlfn.XLOOKUP(relatorio[[#This Row],[Número]],Relatório_CTE!A:A,Relatório_CTE!H:H,"Sem CTE")," ") -> Sem CTE | T12: =(IF(relatorio[[#This Row],[NFs Entrada - Winthor]]="Pendente",IF(relatorio[[#This Row],[Dt. CTE]]="Sem CTE",relatorio[[#This Row],[Data Emissão]]+_xlfn.XLOOKUP(relatorio[[#This Row],[De_Para]],'Lead Time - Histórico (Fornec.)'!B:B,'Lead Time - Histórico (Fornec.)'!C:C),relatorio[[#This Row],[Dt. CTE]]+_xlfn.XLOOKUP(relatorio[[#This Row],[Cód. Winthor]],'Lead Time - Histórico (Produto)'!A:A,'Lead Time - Histórico (Produto)'!C:C))," ")) -> 45935 | U12: =IFERROR(IF(WEEKDAY(relatorio[[#This Row],[Previsão de entrega - Bruto]],2)=6,relatorio[[#This Row],[Previsão de entrega - Bruto]]+2,IF(WEEKDAY(relatorio[[#This Row],[Previsão de entrega - Bruto]],2)=7,relatorio[[#This Row],[Previsão de entrega - Bruto]]+1,relatorio[[#This Row],[Previsão de entrega - Bruto]]))," ") -> 45936
A13: PRIVADO | B13: CE | C13: LIBBS FARMACEUTICA Ltda | D13: 343366 | E13: 45924 | F13: 318.86 | G13: 7896094202818 | H13: 000000000000150926 | I13: ONTAX 300 MG OR | J13: 46568 | K13: 1 | L13: =_xlfn.XLOOKUP(relatorio[[#This Row],[Nome PJ Emitente]],De_Para!A:A,De_Para!C:C) -> Libbs | M13: {=IF(LEFT(G13&"",1)="0", IFERROR( VALUE(MID(G13&"",_xlfn.AGGREGATE(15,6,ROW(INDIRECT("1:"&LEN(G13&"")))/(MID(G13&"",ROW(INDIRECT("1:"&LEN(G13&""))),1)<>"0"),1),999)), MID(G13&"",_xlfn.AGGREGATE(15,6,ROW(INDIRECT("1:"&LEN(G13&"")))/(MID(G13&"",ROW(INDIRECT("1:"&LEN(G13&""))),1)<>"0"),1),999) ), IFERROR(VALUE(G13),G13))} -> 7896094202818 | N13: =TEXT(relatorio[[#This Row],[Data Emissão]],"mmm") -> set | O13: =_xlfn.XLOOKUP(relatorio[[#This Row],[Número]],relatorio_Entrada_NF!A:A,relatorio_Entrada_NF!A:A,"Pendente") -> Pendente | P13: =_xlfn.XLOOKUP(relatorio[[#This Row],[Nome PJ Emitente]],Material!A:A,Material!B:B,"Medicamento") -> Medicamento | Q13: =IF(relatorio[[#This Row],[Natureza]]="Medicamento",_xlfn.XLOOKUP(relatorio[[#This Row],[EAN]],CadastroProd!U:U,CadastroProd!A:A," "),_xlfn.XLOOKUP(relatorio[[#This Row],['[Item'] Código]],CadastroProd!X:X,CadastroProd!A:A," ")) -> 2575 | R13: =IF(O13="Pendente",_xlfn.XLOOKUP(relatorio[[#This Row],[Número]],Relatório_CTE!A:A,Relatório_CTE!B:B,"Sem CTE")," ") -> 914647 | S13: =IF(relatorio[[#This Row],[NFs Entrada - Winthor]]="Pendente",_xlfn.XLOOKUP(relatorio[[#This Row],[Número]],Relatório_CTE!A:A,Relatório_CTE!H:H,"Sem CTE")," ") -> 45925 | T13: =(IF(relatorio[[#This Row],[NFs Entrada - Winthor]]="Pendente",IF(relatorio[[#This Row],[Dt. CTE]]="Sem CTE",relatorio[[#This Row],[Data Emissão]]+_xlfn.XLOOKUP(relatorio[[#This Row],[De_Para]],'Lead Time - Histórico (Fornec.)'!B:B,'Lead Time - Histórico (Fornec.)'!C:C),relatorio[[#This Row],[Dt. CTE]]+_xlfn.XLOOKUP(relatorio[[#This Row],[Cód. Winthor]],'Lead Time - Histórico (Produto)'!A:A,'Lead Time - Histórico (Produto)'!C:C))," ")) -> 45931 | U13: =IFERROR(IF(WEEKDAY(relatorio[[#This Row],[Previsão de entrega - Bruto]],2)=6,relatorio[[#This Row],[Previsão de entrega - Bruto]]+2,IF(WEEKDAY(relatorio[[#This Row],[Previsão de entrega - Bruto]],2)=7,relatorio[[#This Row],[Previsão de entrega - Bruto]]+1,relatorio[[#This Row],[Previsão de entrega - Bruto]]))," ") -> 45931
... A83: PRIVADO | B83: PE | C83: CELLTRION HEALTHCARE DIST PROD FARMACEUTICOS DO BRASIL LTDA | D83: 8207 | E83: 45919 | F83: 66240 | G83: 7898576550035 | H83: M06fDP440IVX1 | I83: HERZUMA 440 MG/20ML LOTE 5A6C222 Fab.:5/7/2025 Val.:2/28/2031 | J83: 47907 | K83: 48 | L83: =_xlfn.XLOOKUP(relatorio[[#This Row],[Nome PJ Emitente]],De_Para!A:A,De_Para!C:C) -> Celltrion | M83: {=IF(LEFT(G83&"",1)="0", IFERROR( VALUE(MID(G83&"",_xlfn.AGGREGATE(15,6,ROW(INDIRECT("1:"&LEN(G83&"")))/(MID(G83&"",ROW(INDIRECT("1:"&LEN(G83&""))),1)<>"0"),1),999)), MID(G83&"",_xlfn.AGGREGATE(15,6,ROW(INDIRECT("1:"&LEN(G83&"")))/(MID(G83&"",ROW(INDIRECT("1:"&LEN(G83&""))),1)<>"0"),1),999) ), IFERROR(VALUE(G83),G83))} -> 7898576550035 | N83: =TEXT(relatorio[[#This Row],[Data Emissão]],"mmm") -> set | O83: =_xlfn.XLOOKUP(relatorio[[#This Row],[Número]],relatorio_Entrada_NF!A:A,relatorio_Entrada_NF!A:A,"Pendente") -> Pendente | P83: =_xlfn.XLOOKUP(relatorio[[#This Row],[Nome PJ Emitente]],Material!A:A,Material!B:B,"Medicamento") -> Medicamento | Q83: =IF(relatorio[[#This Row],[Natureza]]="Medicamento",_xlfn.XLOOKUP(relatorio[[#This Row],[EAN]],CadastroProd!U:U,CadastroProd!A:A," "),_xlfn.XLOOKUP(relatorio[[#This Row],['[Item'] Código]],CadastroProd!X:X,CadastroProd!A:A," ")) -> 2421 | R83: =IF(O83="Pendente",_xlfn.XLOOKUP(relatorio[[#This Row],[Número]],Relatório_CTE!A:A,Relatório_CTE!B:B,"Sem CTE")," ") -> 44718 | S83: =IF(relatorio[[#This Row],[NFs Entrada - Winthor]]="Pendente",_xlfn.XLOOKUP(relatorio[[#This Row],[Número]],Relatório_CTE!A:A,Relatório_CTE!H:H,"Sem CTE")," ") -> 45923 | T83: =(IF(relatorio[[#This Row],[NFs Entrada - Winthor]]="Pendente",IF(relatorio[[#This Row],[Dt. CTE]]="Sem CTE",relatorio[[#This Row],[Data Emissão]]+_xlfn.XLOOKUP(relatorio[[#This Row],[De_Para]],'Lead Time - Histórico (Fornec.)'!B:B,'Lead Time - Histórico (Fornec.)'!C:C),relatorio[[#This Row],[Dt. CTE]]+_xlfn.XLOOKUP(relatorio[[#This Row],[Cód. Winthor]],'Lead Time - Histórico (Produto)'!A:A,'Lead Time - Histórico (Produto)'!C:C))," ")) -> 45927 | U83: =IFERROR(IF(WEEKDAY(relatorio[[#This Row],[Previsão de entrega - Bruto]],2)=6,relatorio[[#This Row],[Previsão de entrega - Bruto]]+2,IF(WEEKDAY(relatorio[[#This Row],[Previsão de entrega - Bruto]],2)=7,relatorio[[#This Row],[Previsão de entrega - Bruto]]+1,relatorio[[#This Row],[Previsão de entrega - Bruto]]))," ") -> 45929
A84: PUBLICO | B84: PE | C84: GABISA MEDICAL INTERNATIONAL S.A. | D84: 36372 | E84: 45919 | F84: 4904.17 | G84: 7898943128010 | H84: 230-06 | I84: CANULA NASAL PARA OXIGENOTERAPIA GMI FR:06 - 2,10 M (NEONATAL) | K84: 300 | L84: =_xlfn.XLOOKUP(relatorio[[#This Row],[Nome PJ Emitente]],De_Para!A:A,De_Para!C:C) -> GMI | M84: {=IF(LEFT(G84&"",1)="0", IFERROR( VALUE(MID(G84&"",_xlfn.AGGREGATE(15,6,ROW(INDIRECT("1:"&LEN(G84&"")))/(MID(G84&"",ROW(INDIRECT("1:"&LEN(G84&""))),1)<>"0"),1),999)), MID(G84&"",_xlfn.AGGREGATE(15,6,ROW(INDIRECT("1:"&LEN(G84&"")))/(MID(G84&"",ROW(INDIRECT("1:"&LEN(G84&""))),1)<>"0"),1),999) ), IFERROR(VALUE(G84),G84))} -> 7898943128010 | N84: =TEXT(relatorio[[#This Row],[Data Emissão]],"mmm") -> set | O84: =_xlfn.XLOOKUP(relatorio[[#This Row],[Número]],relatorio_Entrada_NF!A:A,relatorio_Entrada_NF!A:A,"Pendente") -> Pendente | P84: =_xlfn.XLOOKUP(relatorio[[#This Row],[Nome PJ Emitente]],Material!A:A,Material!B:B,"Medicamento") -> Material | Q84: =IF(relatorio[[#This Row],[Natureza]]="Medicamento",_xlfn.XLOOKUP(relatorio[[#This Row],[EAN]],CadastroProd!U:U,CadastroProd!A:A," "),_xlfn.XLOOKUP(relatorio[[#This Row],['[Item'] Código]],CadastroProd!X:X,CadastroProd!A:A," ")) -> 3143 | R84: =IF(O84="Pendente",_xlfn.XLOOKUP(relatorio[[#This Row],[Número]],Relatório_CTE!A:A,Relatório_CTE!B:B,"Sem CTE")," ") -> 11121064 | S84: =IF(relatorio[[#This Row],[NFs Entrada - Winthor]]="Pendente",_xlfn.XLOOKUP(relatorio[[#This Row],[Número]],Relatório_CTE!A:A,Relatório_CTE!H:H,"Sem CTE")," ") -> 45925 | T84: =(IF(relatorio[[#This Row],[NFs Entrada - Winthor]]="Pendente",IF(relatorio[[#This Row],[Dt. CTE]]="Sem CTE",relatorio[[#This Row],[Data Emissão]]+_xlfn.XLOOKUP(relatorio[[#This Row],[De_Para]],'Lead Time - Histórico (Fornec.)'!B:B,'Lead Time - Histórico (Fornec.)'!C:C),relatorio[[#This Row],[Dt. CTE]]+_xlfn.XLOOKUP(relatorio[[#This Row],[Cód. Winthor]],'Lead Time - Histórico (Produto)'!A:A,'Lead Time - Histórico (Produto)'!C:C))," ")) -> 45942 | U84: =IFERROR(IF(WEEKDAY(relatorio[[#This Row],[Previsão de entrega - Bruto]],2)=6,relatorio[[#This Row],[Previsão de entrega - Bruto]]+2,IF(WEEKDAY(relatorio[[#This Row],[Previsão de entrega - Bruto]],2)=7,relatorio[[#This Row],[Previsão de entrega - Bruto]]+1,relatorio[[#This Row],[Previsão de entrega - Bruto]]))," ") -> 45943
A85: PUBLICO | B85: PE | C85: 3M DO BRASIL LTDA | D85: 511798 | E85: 45919 | F85: 50686.4 | G85: 50707387802252 | H85: HB004800296 | I85: 1657R TEGADERM CHG CX C/25 3M TEGADERM CHG | J85: 46471 | K85: 40 | L85: =_xlfn.XLOOKUP(relatorio[[#This Row],[Nome PJ Emitente]],De_Para!A:A,De_Para!C:C) -> 3M | M85: {=IF(LEFT(G85&"",1)="0", IFERROR( VALUE(MID(G85&"",_xlfn.AGGREGATE(15,6,ROW(INDIRECT("1:"&LEN(G85&"")))/(MID(G85&"",ROW(INDIRECT("1:"&LEN(G85&""))),1)<>"0"),1),999)), MID(G85&"",_xlfn.AGGREGATE(15,6,ROW(INDIRECT("1:"&LEN(G85&"")))/(MID(G85&"",ROW(INDIRECT("1:"&LEN(G85&""))),1)<>"0"),1),999) ), IFERROR(VALUE(G85),G85))} -> 50707387802252 | N85: =TEXT(relatorio[[#This Row],[Data Emissão]],"mmm") -> set | O85: =_xlfn.XLOOKUP(relatorio[[#This Row],[Número]],relatorio_Entrada_NF!A:A,relatorio_Entrada_NF!A:A,"Pendente") -> Pendente | P85: =_xlfn.XLOOKUP(relatorio[[#This Row],[Nome PJ Emitente]],Material!A:A,Material!B:B,"Medicamento") -> Material | Q85: =IF(relatorio[[#This Row],[Natureza]]="Medicamento",_xlfn.XLOOKUP(relatorio[[#This Row],[EAN]],CadastroProd!U:U,CadastroProd!A:A," "),_xlfn.XLOOKUP(relatorio[[#This Row],['[Item'] Código]],CadastroProd!X:X,CadastroProd!A:A," ")) -> 3329 | R85: =IF(O85="Pendente",_xlfn.XLOOKUP(relatorio[[#This Row],[Número]],Relatório_CTE!A:A,Relatório_CTE!B:B,"Sem CTE")," ") -> 2314657 | S85: =IF(relatorio[[#This Row],[NFs Entrada - Winthor]]="Pendente",_xlfn.XLOOKUP(relatorio[[#This Row],[Número]],Relatório_CTE!A:A,Relatório_CTE!H:H,"Sem CTE")," ") -> 45919 | T85: =(IF(relatorio[[#This Row],[NFs Entrada - Winthor]]="Pendente",IF(relatorio[[#This Row],[Dt. CTE]]="Sem CTE",relatorio[[#This Row],[Data Emissão]]+_xlfn.XLOOKUP(relatorio[[#This Row],[De_Para]],'Lead Time - Histórico (Fornec.)'!B:B,'Lead Time - Histórico (Fornec.)'!C:C),relatorio[[#This Row],[Dt. CTE]]+_xlfn.XLOOKUP(relatorio[[#This Row],[Cód. Winthor]],'Lead Time - Histórico (Produto)'!A:A,'Lead Time - Histórico (Produto)'!C:C))," ")) -> 45933 | U85: =IFERROR(IF(WEEKDAY(relatorio[[#This Row],[Previsão de entrega - Bruto]],2)=6,relatorio[[#This Row],[Previsão de entrega - Bruto]]+2,IF(WEEKDAY(relatorio[[#This Row],[Previsão de entrega - Bruto]],2)=7,relatorio[[#This Row],[Previsão de entrega - Bruto]]+1,relatorio[[#This Row],[Previsão de entrega - Bruto]]))," ") -> 45933
A86: PRIVADO | B86: PE | C86: NOVARTIS BIOCIENCIAS SA | D86: 501817 | E86: 45919 | F86: 20125.53 | G86: 7896261020689 | H86: 751315 | I86: REVOLADE 50MG 14 CE | J86: 46446 | K86: 5 | L86: =_xlfn.XLOOKUP(relatorio[[#This Row],[Nome PJ Emitente]],De_Para!A:A,De_Para!C:C) -> Novartis | M86: {=IF(LEFT(G86&"",1)="0", IFERROR( VALUE(MID(G86&"",_xlfn.AGGREGATE(15,6,ROW(INDIRECT("1:"&LEN(G86&"")))/(MID(G86&"",ROW(INDIRECT("1:"&LEN(G86&""))),1)<>"0"),1),999)), MID(G86&"",_xlfn.AGGREGATE(15,6,ROW(INDIRECT("1:"&LEN(G86&"")))/(MID(G86&"",ROW(INDIRECT("1:"&LEN(G86&""))),1)<>"0"),1),999) ), IFERROR(VALUE(G86),G86))} -> 7896261020689 | N86: =TEXT(relatorio[[#This Row],[Data Emissão]],"mmm") -> set | O86: =_xlfn.XLOOKUP(relatorio[[#This Row],[Número]],relatorio_Entrada_NF!A:A,relatorio_Entrada_NF!A:A,"Pendente") -> Pendente | P86: =_xlfn.XLOOKUP(relatorio[[#This Row],[Nome PJ Emitente]],Material!A:A,Material!B:B,"Medicamento") -> Medicamento | Q86: =IF(relatorio[[#This Row],[Natureza]]="Medicamento",_xlfn.XLOOKUP(relatorio[[#This Row],[EAN]],CadastroProd!U:U,CadastroProd!A:A," "),_xlfn.XLOOKUP(relatorio[[#This Row],['[Item'] Código]],CadastroProd!X:X,CadastroProd!A:A," ")) -> 1344 | R86: =IF(O86="Pendente",_xlfn.XLOOKUP(relatorio[[#This Row],[Número]],Relatório_CTE!A:A,Relatório_CTE!B:B,"Sem CTE")," ") -> 382539 | S86: =IF(relatorio[[#This Row],[NFs Entrada - Winthor]]="Pendente",_xlfn.XLOOKUP(relatorio[[#This Row],[Número]],Relatório_CTE!A:A,Relatório_CTE!H:H,"Sem CTE")," ") -> 45923 | T86: =(IF(relatorio[[#This Row],[NFs Entrada - Winthor]]="Pendente",IF(relatorio[[#This Row],[Dt. CTE]]="Sem CTE",relatorio[[#This Row],[Data Emissão]]+_xlfn.XLOOKUP(relatorio[[#This Row],[De_Para]],'Lead Time - Histórico (Fornec.)'!B:B,'Lead Time - Histórico (Fornec.)'!C:C),relatorio[[#This Row],[Dt. CTE]]+_xlfn.XLOOKUP(relatorio[[#This Row],[Cód. Winthor]],'Lead Time - Histórico (Produto)'!A:A,'Lead Time - Histórico (Produto)'!C:C))," ")) -> 45928 | U86: =IFERROR(IF(WEEKDAY(relatorio[[#This Row],[Previsão de entrega - Bruto]],2)=6,relatorio[[#This Row],[Previsão de entrega - Bruto]]+2,IF(WEEKDAY(relatorio[[#This Row],[Previsão de entrega - Bruto]],2)=7,relatorio[[#This Row],[Previsão de entrega - Bruto]]+1,relatorio[[#This Row],[Previsão de entrega - Bruto]]))," ") -> 45929
A87: PRIVADO | B87: PB | C87: ABBVIE FARMACEUTICA LTDA | D87: 152020 | E87: 45919 | F87: 292555.35 | G87: 07897316802939 | H87: 91223BR | I87: BOTOX 100 Units/Vial | J87: 46507 | K87: 74 | L87: =_xlfn.XLOOKUP(relatorio[[#This Row],[Nome PJ Emitente]],De_Para!A:A,De_Para!C:C) -> Abbvie | M87: {=IF(LEFT(G87&"",1)="0", IFERROR( VALUE(MID(G87&"",_xlfn.AGGREGATE(15,6,ROW(INDIRECT("1:"&LEN(G87&"")))/(MID(G87&"",ROW(INDIRECT("1:"&LEN(G87&""))),1)<>"0"),1),999)), MID(G87&"",_xlfn.AGGREGATE(15,6,ROW(INDIRECT("1:"&LEN(G87&"")))/(MID(G87&"",ROW(INDIRECT("1:"&LEN(G87&""))),1)<>"0"),1),999) ), IFERROR(VALUE(G87),G87))} -> 7897316802939 | N87: =TEXT(relatorio[[#This Row],[Data Emissão]],"mmm") -> set | O87: =_xlfn.XLOOKUP(relatorio[[#This Row],[Número]],relatorio_Entrada_NF!A:A,relatorio_Entrada_NF!A:A,"Pendente") -> 152020 | P87: =_xlfn.XLOOKUP(relatorio[[#This Row],[Nome PJ Emitente]],Material!A:A,Material!B:B,"Medicamento") -> Medicamento | Q87: =IF(relatorio[[#This Row],[Natureza]]="Medicamento",_xlfn.XLOOKUP(relatorio[[#This Row],[EAN]],CadastroProd!U:U,CadastroProd!A:A," "),_xlfn.XLOOKUP(relatorio[[#This Row],['[Item'] Código]],CadastroProd!X:X,CadastroProd!A:A," ")) -> 2938 | R87: =IF(O87="Pendente",_xlfn.XLOOKUP(relatorio[[#This Row],[Número]],Relatório_CTE!A:A,Relatório_CTE!B:B,"Sem CTE")," ") | S87: =IF(relatorio[[#This Row],[NFs Entrada - Winthor]]="Pendente",_xlfn.XLOOKUP(relatorio[[#This Row],[Número]],Relatório_CTE!A:A,Relatório_CTE!H:H,"Sem CTE")," ") | T87: =(IF(relatorio[[#This Row],[NFs Entrada - Winthor]]="Pendente",IF(relatorio[[#This Row],[Dt. CTE]]="Sem CTE",relatorio[[#This Row],[Data Emissão]]+_xlfn.XLOOKUP(relatorio[[#This Row],[De_Para]],'Lead Time - Histórico (Fornec.)'!B:B,'Lead Time - Histórico (Fornec.)'!C:C),relatorio[[#This Row],[Dt. CTE]]+_xlfn.XLOOKUP(relatorio[[#This Row],[Cód. Winthor]],'Lead Time - Histórico (Produto)'!A:A,'Lead Time - Histórico (Produto)'!C:C))," ")) | U87: =IFERROR(IF(WEEKDAY(relatorio[[#This Row],[Previsão de entrega - Bruto]],2)=6,relatorio[[#This Row],[Previsão de entrega - Bruto]]+2,IF(WEEKDAY(relatorio[[#This Row],[Previsão de entrega - Bruto]],2)=7,relatorio[[#This Row],[Previsão de entrega - Bruto]]+1,relatorio[[#This Row],[Previsão de entrega - Bruto]]))," ")
A88: PRIVADO | B88: PB | C88: ABBVIE FARMACEUTICA LTDA | D88: 152020 | E88: 45919 | F88: 292555.35 | G88: 07897316805015 | H88: 93251BR | I88: BOTOX 200 Units/Vial | J88: 46538 | K88: 163 | L88: =_xlfn.XLOOKUP(relatorio[[#This Row],[Nome PJ Emitente]],De_Para!A:A,De_Para!C:C) -> Abbvie | M88: {=IF(LEFT(G88&"",1)="0", IFERROR( VALUE(MID(G88&"",_xlfn.AGGREGATE(15,6,ROW(INDIRECT("1:"&LEN(G88&"")))/(MID(G88&"",ROW(INDIRECT("1:"&LEN(G88&""))),1)<>"0"),1),999)), MID(G88&"",_xlfn.AGGREGATE(15,6,ROW(INDIRECT("1:"&LEN(G88&"")))/(MID(G88&"",ROW(INDIRECT("1:"&LEN(G88&""))),1)<>"0"),1),999) ), IFERROR(VALUE(G88),G88))} -> 7897316805015 | N88: =TEXT(relatorio[[#This Row],[Data Emissão]],"mmm") -> set | O88: =_xlfn.XLOOKUP(relatorio[[#This Row],[Número]],relatorio_Entrada_NF!A:A,relatorio_Entrada_NF!A:A,"Pendente") -> 152020 | P88: =_xlfn.XLOOKUP(relatorio[[#This Row],[Nome PJ Emitente]],Material!A:A,Material!B:B,"Medicamento") -> Medicamento | Q88: =IF(relatorio[[#This Row],[Natureza]]="Medicamento",_xlfn.XLOOKUP(relatorio[[#This Row],[EAN]],CadastroProd!U:U,CadastroProd!A:A," "),_xlfn.XLOOKUP(relatorio[[#This Row],['[Item'] Código]],CadastroProd!X:X,CadastroProd!A:A," ")) -> 2940 | R88: =IF(O88="Pendente",_xlfn.XLOOKUP(relatorio[[#This Row],[Número]],Relatório_CTE!A:A,Relatório_CTE!B:B,"Sem CTE")," ") | S88: =IF(relatorio[[#This Row],[NFs Entrada - Winthor]]="Pendente",_xlfn.XLOOKUP(relatorio[[#This Row],[Número]],Relatório_CTE!A:A,Relatório_CTE!H:H,"Sem CTE")," ") | T88: =(IF(relatorio[[#This Row],[NFs Entrada - Winthor]]="Pendente",IF(relatorio[[#This Row],[Dt. CTE]]="Sem CTE",relatorio[[#This Row],[Data Emissão]]+_xlfn.XLOOKUP(relatorio[[#This Row],[De_Para]],'Lead Time - Histórico (Fornec.)'!B:B,'Lead Time - Histórico (Fornec.)'!C:C),relatorio[[#This Row],[Dt. CTE]]+_xlfn.XLOOKUP(relatorio[[#This Row],[Cód. Winthor]],'Lead Time - Histórico (Produto)'!A:A,'Lead Time - Histórico (Produto)'!C:C))," ")) | U88: =IFERROR(IF(WEEKDAY(relatorio[[#This Row],[Previsão de entrega - Bruto]],2)=6,relatorio[[#This Row],[Previsão de entrega - Bruto]]+2,IF(WEEKDAY(relatorio[[#This Row],[Previsão de entrega - Bruto]],2)=7,relatorio[[#This Row],[Previsão de entrega - Bruto]]+1,relatorio[[#This Row],[Previsão de entrega - Bruto]]))," ")
A89: PRIVADO | B89: PB | C89: CELLTRION HEALTHCARE DIST PROD FARMACEUTICOS DO BRASIL LTDA | D89: 8204 | E89: 45919 | F89: 52231.2 | G89: 7898576550332 | H89: M17fDP040AIX1 | I89: YUFLYMA SC 40MG/0,4ML LOTE 3LAT06T1D Fab.:9/19/2023 Val.:8/31/2026 | J89: 46265 | K89: 60 | L89: =_xlfn.XLOOKUP(relatorio[[#This Row],[Nome PJ Emitente]],De_Para!A:A,De_Para!C:C) -> Celltrion | M89: {=IF(LEFT(G89&"",1)="0", IFERROR( VALUE(MID(G89&"",_xlfn.AGGREGATE(15,6,ROW(INDIRECT("1:"&LEN(G89&"")))/(MID(G89&"",ROW(INDIRECT("1:"&LEN(G89&""))),1)<>"0"),1),999)), MID(G89&"",_xlfn.AGGREGATE(15,6,ROW(INDIRECT("1:"&LEN(G89&"")))/(MID(G89&"",ROW(INDIRECT("1:"&LEN(G89&""))),1)<>"0"),1),999) ), IFERROR(VALUE(G89),G89))} -> 7898576550332 | N89: =TEXT(relatorio[[#This Row],[Data Emissão]],"mmm") -> set | O89: =_xlfn.XLOOKUP(relatorio[[#This Row],[Número]],relatorio_Entrada_NF!A:A,relatorio_Entrada_NF!A:A,"Pendente") -> Pendente | P89: =_xlfn.XLOOKUP(relatorio[[#This Row],[Nome PJ Emitente]],Material!A:A,Material!B:B,"Medicamento") -> Medicamento | Q89: =IF(relatorio[[#This Row],[Natureza]]="Medicamento",_xlfn.XLOOKUP(relatorio[[#This Row],[EAN]],CadastroProd!U:U,CadastroProd!A:A," "),_xlfn.XLOOKUP(relatorio[[#This Row],['[Item'] Código]],CadastroProd!X:X,CadastroProd!A:A," ")) -> 3280 | R89: =IF(O89="Pendente",_xlfn.XLOOKUP(relatorio[[#This Row],[Número]],Relatório_CTE!A:A,Relatório_CTE!B:B,"Sem CTE")," ") -> 44711 | S89: =IF(relatorio[[#This Row],[NFs Entrada - Winthor]]="Pendente",_xlfn.XLOOKUP(relatorio[[#This Row],[Número]],Relatório_CTE!A:A,Relatório_CTE!H:H,"Sem CTE")," ") -> 45923 | T89: =(IF(relatorio[[#This Row],[NFs Entrada - Winthor]]="Pendente",IF(relatorio[[#This Row],[Dt. CTE]]="Sem CTE",relatorio[[#This Row],[Data Emissão]]+_xlfn.XLOOKUP(relatorio[[#This Row],[De_Para]],'Lead Time - Histórico (Fornec.)'!B:B,'Lead Time - Histórico (Fornec.)'!C:C),relatorio[[#This Row],[Dt. CTE]]+_xlfn.XLOOKUP(relatorio[[#This Row],[Cód. Winthor]],'Lead Time - Histórico (Produto)'!A:A,'Lead Time - Histórico (Produto)'!C:C))," ")) -> 45926 | U89: =IFERROR(IF(WEEKDAY(relatorio[[#This Row],[Previsão de entrega - Bruto]],2)=6,relatorio[[#This Row],[Previsão de entrega - Bruto]]+2,IF(WEEKDAY(relatorio[[#This Row],[Previsão de entrega - Bruto]],2)=7,relatorio[[#This Row],[Previsão de entrega - Bruto]]+1,relatorio[[#This Row],[Previsão de entrega - Bruto]]))," ") -> 45926
A90: PRIVADO | B90: PB | C90: GABISA MEDICAL INTERNATIONAL S.A. | D90: 36370 | E90: 45919 | F90: 2827.7 | G90: 7898943128010 | H90: 230-06 | I90: CANULA NASAL PARA OXIGENOTERAPIA GMI FR:06 - 2,10 M (NEONATAL) | K90: 144 | L90: =_xlfn.XLOOKUP(relatorio[[#This Row],[Nome PJ Emitente]],De_Para!A:A,De_Para!C:C) -> GMI | M90: {=IF(LEFT(G90&"",1)="0", IFERROR( VALUE(MID(G90&"",_xlfn.AGGREGATE(15,6,ROW(INDIRECT("1:"&LEN(G90&"")))/(MID(G90&"",ROW(INDIRECT("1:"&LEN(G90&""))),1)<>"0"),1),999)), MID(G90&"",_xlfn.AGGREGATE(15,6,ROW(INDIRECT("1:"&LEN(G90&"")))/(MID(G90&"",ROW(INDIRECT("1:"&LEN(G90&""))),1)<>"0"),1),999) ), IFERROR(VALUE(G90),G90))} -> 7898943128010 | N90: =TEXT(relatorio[[#This Row],[Data Emissão]],"mmm") -> set | O90: =_xlfn.XLOOKUP(relatorio[[#This Row],[Número]],relatorio_Entrada_NF!A:A,relatorio_Entrada_NF!A:A,"Pendente") -> Pendente | P90: =_xlfn.XLOOKUP(relatorio[[#This Row],[Nome PJ Emitente]],Material!A:A,Material!B:B,"Medicamento") -> Material | Q90: =IF(relatorio[[#This Row],[Natureza]]="Medicamento",_xlfn.XLOOKUP(relatorio[[#This Row],[EAN]],CadastroProd!U:U,CadastroProd!A:A," "),_xlfn.XLOOKUP(relatorio[[#This Row],['[Item'] Código]],CadastroProd!X:X,CadastroProd!A:A," ")) -> 3143 | R90: =IF(O90="Pendente",_xlfn.XLOOKUP(relatorio[[#This Row],[Número]],Relatório_CTE!A:A,Relatório_CTE!B:B,"Sem CTE")," ") -> 11121010 | S90: =IF(relatorio[[#This Row],[NFs Entrada - Winthor]]="Pendente",_xlfn.XLOOKUP(relatorio[[#This Row],[Número]],Relatório_CTE!A:A,Relatório_CTE!H:H,"Sem CTE")," ") -> 45925 | T90: =(IF(relatorio[[#This Row],[NFs Entrada - Winthor]]="Pendente",IF(relatorio[[#This Row],[Dt. CTE]]="Sem CTE",relatorio[[#This Row],[Data Emissão]]+_xlfn.XLOOKUP(relatorio[[#This Row],[De_Para]],'Lead Time - Histórico (Fornec.)'!B:B,'Lead Time - Histórico (Fornec.)'!C:C),relatorio[[#This Row],[Dt. CTE]]+_xlfn.XLOOKUP(relatorio[[#This Row],[Cód. Winthor]],'Lead Time - Histórico (Produto)'!A:A,'Lead Time - Histórico (Produto)'!C:C))," ")) -> 45942 | U90: =IFERROR(IF(WEEKDAY(relatorio[[#This Row],[Previsão de entrega - Bruto]],2)=6,relatorio[[#This Row],[Previsão de entrega - Bruto]]+2,IF(WEEKDAY(relatorio[[#This Row],[Previsão de entrega - Bruto]],2)=7,relatorio[[#This Row],[Previsão de entrega - Bruto]]+1,relatorio[[#This Row],[Previsão de entrega - Bruto]]))," ") -> 45943
A91: PRIVADO | B91: PB | C91: GABISA MEDICAL INTERNATIONAL S.A. | D91: 36370 | E91: 45919 | F91: 2827.7 | G91: 7898943128980 | H91: 544-25 | I91: CATETER UMBILICAL GMI FR:2,5 | K91: 10 | L91: =_xlfn.XLOOKUP(relatorio[[#This Row],[Nome PJ Emitente]],De_Para!A:A,De_Para!C:C) -> GMI | M91: {=IF(LEFT(G91&"",1)="0", IFERROR( VALUE(MID(G91&"",_xlfn.AGGREGATE(15,6,ROW(INDIRECT("1:"&LEN(G91&"")))/(MID(G91&"",ROW(INDIRECT("1:"&LEN(G91&""))),1)<>"0"),1),999)), MID(G91&"",_xlfn.AGGREGATE(15,6,ROW(INDIRECT("1:"&LEN(G91&"")))/(MID(G91&"",ROW(INDIRECT("1:"&LEN(G91&""))),1)<>"0"),1),999) ), IFERROR(VALUE(G91),G91))} -> 7898943128980 | N91: =TEXT(relatorio[[#This Row],[Data Emissão]],"mmm") -> set | O91: =_xlfn.XLOOKUP(relatorio[[#This Row],[Número]],relatorio_Entrada_NF!A:A,relatorio_Entrada_NF!A:A,"Pendente") -> Pendente | P91: =_xlfn.XLOOKUP(relatorio[[#This Row],[Nome PJ Emitente]],Material!A:A,Material!B:B,"Medicamento") -> Material | Q91: =IF(relatorio[[#This Row],[Natureza]]="Medicamento",_xlfn.XLOOKUP(relatorio[[#This Row],[EAN]],CadastroProd!U:U,CadastroProd!A:A," "),_xlfn.XLOOKUP(relatorio[[#This Row],['[Item'] Código]],CadastroProd!X:X,CadastroProd!A:A," ")) -> 3149 | R91: =IF(O91="Pendente",_xlfn.XLOOKUP(relatorio[[#This Row],[Número]],Relatório_CTE!A:A,Relatório_CTE!B:B,"Sem CTE")," ") -> 11121010 | S91: =IF(relatorio[[#This Row],[NFs Entrada - Winthor]]="Pendente",_xlfn.XLOOKUP(relatorio[[#This Row],[Número]],Relatório_CTE!A:A,Relatório_CTE!H:H,"Sem CTE")," ") -> 45925 | T91: =(IF(relatorio[[#This Row],[NFs Entrada - Winthor]]="Pendente",IF(relatorio[[#This Row],[Dt. CTE]]="Sem CTE",relatorio[[#This Row],[Data Emissão]]+_xlfn.XLOOKUP(relatorio[[#This Row],[De_Para]],'Lead Time - Histórico (Fornec.)'!B:B,'Lead Time - Histórico (Fornec.)'!C:C),relatorio[[#This Row],[Dt. CTE]]+_xlfn.XLOOKUP(relatorio[[#This Row],[Cód. Winthor]],'Lead Time - Histórico (Produto)'!A:A,'Lead Time - Histórico (Produto)'!C:C))," ")) -> 45936 | U91: =IFERROR(IF(WEEKDAY(relatorio[[#This Row],[Previsão de entrega - Bruto]],2)=6,relatorio[[#This Row],[Previsão de entrega - Bruto]]+2,IF(WEEKDAY(relatorio[[#This Row],[Previsão de entrega - Bruto]],2)=7,relatorio[[#This Row],[Previsão de entrega - Bruto]]+1,relatorio[[#This Row],[Previsão de entrega - Bruto]]))," ") -> 45936
A92: PRIVADO | B92: PB | C92: GABISA MEDICAL INTERNATIONAL S.A. | D92: 36370 | E92: 45919 | F92: 2827.7 | G92: 7898660491121 | H92: EXTV10-2 | I92: GABILINK - EXTENSOR VALVULADO SAFETY GMI NEONATAL 2 VIAS | K92: 50 | L92: =_xlfn.XLOOKUP(relatorio[[#This Row],[Nome PJ Emitente]],De_Para!A:A,De_Para!C:C) -> GMI | M92: {=IF(LEFT(G92&"",1)="0", IFERROR( VALUE(MID(G92&"",_xlfn.AGGREGATE(15,6,ROW(INDIRECT("1:"&LEN(G92&"")))/(MID(G92&"",ROW(INDIRECT("1:"&LEN(G92&""))),1)<>"0"),1),999)), MID(G92&"",_xlfn.AGGREGATE(15,6,ROW(INDIRECT("1:"&LEN(G92&"")))/(MID(G92&"",ROW(INDIRECT("1:"&LEN(G92&""))),1)<>"0"),1),999) ), IFERROR(VALUE(G92),G92))} -> 7898660491121 | N92: =TEXT(relatorio[[#This Row],[Data Emissão]],"mmm") -> set | O92: =_xlfn.XLOOKUP(relatorio[[#This Row],[Número]],relatorio_Entrada_NF!A:A,relatorio_Entrada_NF!A:A,"Pendente") -> Pendente | P92: =_xlfn.XLOOKUP(relatorio[[#This Row],[Nome PJ Emitente]],Material!A:A,Material!B:B,"Medicamento") -> Material | Q92: =IF(relatorio[[#This Row],[Natureza]]="Medicamento",_xlfn.XLOOKUP(relatorio[[#This Row],[EAN]],CadastroProd!U:U,CadastroProd!A:A," "),_xlfn.XLOOKUP(relatorio[[#This Row],['[Item'] Código]],CadastroProd!X:X,CadastroProd!A:A," ")) -> 3155 | R92: =IF(O92="Pendente",_xlfn.XLOOKUP(relatorio[[#This Row],[Número]],Relatório_CTE!A:A,Relatório_CTE!B:B,"Sem CTE")," ") -> 11121010 | S92: =IF(relatorio[[#This Row],[NFs Entrada - Winthor]]="Pendente",_xlfn.XLOOKUP(relatorio[[#This Row],[Número]],Relatório_CTE!A:A,Relatório_CTE!H:H,"Sem CTE")," ") -> 45925 | T92: =(IF(relatorio[[#This Row],[NFs Entrada - Winthor]]="Pendente",IF(relatorio[[#This Row],[Dt. CTE]]="Sem CTE",relatorio[[#This Row],[Data Emissão]]+_xlfn.XLOOKUP(relatorio[[#This Row],[De_Para]],'Lead Time - Histórico (Fornec.)'!B:B,'Lead Time - Histórico (Fornec.)'!C:C),relatorio[[#This Row],[Dt. CTE]]+_xlfn.XLOOKUP(relatorio[[#This Row],[Cód. Winthor]],'Lead Time - Histórico (Produto)'!A:A,'Lead Time - Histórico (Produto)'!C:C))," ")) -> #N/A | U92: =IFERROR(IF(WEEKDAY(relatorio[[#This Row],[Previsão de entrega - Bruto]],2)=6,relatorio[[#This Row],[Previsão de entrega - Bruto]]+2,IF(WEEKDAY(relatorio[[#This Row],[Previsão de entrega - Bruto]],2)=7,relatorio[[#This Row],[Previsão de entrega - Bruto]]+1,relatorio[[#This Row],[Previsão de entrega - Bruto]]))," ")
A93: PRIVADO | B93: PB | C93: 3M DO BRASIL LTDA | D93: 511799 | E93: 45919 | F93: 3259.43 | G93: 7891040285327 | H93: HB004558647 | I93: 54500 MANTA AQ UNDBD AD C/10 3M BAIR HUGGER MANTA 54500 | J93: 46877 | K93: 2 | L93: =_xlfn.XLOOKUP(relatorio[[#This Row],[Nome PJ Emitente]],De_Para!A:A,De_Para!C:C) -> 3M | M93: {=IF(LEFT(G93&"",1)="0", IFERROR( VALUE(MID(G93&"",_xlfn.AGGREGATE(15,6,ROW(INDIRECT("1:"&LEN(G93&"")))/(MID(G93&"",ROW(INDIRECT("1:"&LEN(G93&""))),1)<>"0"),1),999)), MID(G93&"",_xlfn.AGGREGATE(15,6,ROW(INDIRECT("1:"&LEN(G93&"")))/(MID(G93&"",ROW(INDIRECT("1:"&LEN(G93&""))),1)<>"0"),1),999) ), IFERROR(VALUE(G93),G93))} -> 7891040285327 | N93: =TEXT(relatorio[[#This Row],[Data Emissão]],"mmm") -> set | O93: =_xlfn.XLOOKUP(relatorio[[#This Row],[Número]],relatorio_Entrada_NF!A:A,relatorio_Entrada_NF!A:A,"Pendente") -> Pendente | P93: =_xlfn.XLOOKUP(relatorio[[#This Row],[Nome PJ Emitente]],Material!A:A,Material!B:B,"Medicamento") -> Material | Q93: =IF(relatorio[[#This Row],[Natureza]]="Medicamento",_xlfn.XLOOKUP(relatorio[[#This Row],[EAN]],CadastroProd!U:U,CadastroProd!A:A," "),_xlfn.XLOOKUP(relatorio[[#This Row],['[Item'] Código]],CadastroProd!X:X,CadastroProd!A:A," ")) -> 3762 | R93: =IF(O93="Pendente",_xlfn.XLOOKUP(relatorio[[#This Row],[Número]],Relatório_CTE!A:A,Relatório_CTE!B:B,"Sem CTE")," ") -> 2314651 | S93: =IF(relatorio[[#This Row],[NFs Entrada - Winthor]]="Pendente",_xlfn.XLOOKUP(relatorio[[#This Row],[Número]],Relatório_CTE!A:A,Relatório_CTE!H:H,"Sem CTE")," ") -> 45919 | T93: =(IF(relatorio[[#This Row],[NFs Entrada - Winthor]]="Pendente",IF(relatorio[[#This Row],[Dt. CTE]]="Sem CTE",relatorio[[#This Row],[Data Emissão]]+_xlfn.XLOOKUP(relatorio[[#This Row],[De_Para]],'Lead Time - Histórico (Fornec.)'!B:B,'Lead Time - Histórico (Fornec.)'!C:C),relatorio[[#This Row],[Dt. CTE]]+_xlfn.XLOOKUP(relatorio[[#This Row],[Cód. Winthor]],'Lead Time - Histórico (Produto)'!A:A,'Lead Time - Histórico (Produto)'!C:C))," ")) -> #N/A | U93: =IFERROR(IF(WEEKDAY(relatorio[[#This Row],[Previsão de entrega - Bruto]],2)=6,relatorio[[#This Row],[Previsão de entrega - Bruto]]+2,IF(WEEKDAY(relatorio[[#This Row],[Previsão de entrega - Bruto]],2)=7,relatorio[[#This Row],[Previsão de entrega - Bruto]]+1,relatorio[[#This Row],[Previsão de entrega - Bruto]]))," ")
A94: PRIVADO | B94: PB | C94: 3M DO BRASIL LTDA | D94: 511799 | E94: 45919 | F94: 3259.43 | G94: SEM GTIN | H94: HB004559207 | I94: 52500 MANTA AQ MEMBRO INF C/10 3M BAIR HUGGER MANTA 52500 | J94: 46936 | K94: 2 | L94: =_xlfn.XLOOKUP(relatorio[[#This Row],[Nome PJ Emitente]],De_Para!A:A,De_Para!C:C) -> 3M | M94: {=IF(LEFT(G94&"",1)="0", IFERROR( VALUE(MID(G94&"",_xlfn.AGGREGATE(15,6,ROW(INDIRECT("1:"&LEN(G94&"")))/(MID(G94&"",ROW(INDIRECT("1:"&LEN(G94&""))),1)<>"0"),1),999)), MID(G94&"",_xlfn.AGGREGATE(15,6,ROW(INDIRECT("1:"&LEN(G94&"")))/(MID(G94&"",ROW(INDIRECT("1:"&LEN(G94&""))),1)<>"0"),1),999) ), IFERROR(VALUE(G94),G94))} -> SEM GTIN | N94: =TEXT(relatorio[[#This Row],[Data Emissão]],"mmm") -> set | O94: =_xlfn.XLOOKUP(relatorio[[#This Row],[Número]],relatorio_Entrada_NF!A:A,relatorio_Entrada_NF!A:A,"Pendente") -> Pendente | P94: =_xlfn.XLOOKUP(relatorio[[#This Row],[Nome PJ Emitente]],Material!A:A,Material!B:B,"Medicamento") -> Material | Q94: =IF(relatorio[[#This Row],[Natureza]]="Medicamento",_xlfn.XLOOKUP(relatorio[[#This Row],[EAN]],CadastroProd!U:U,CadastroProd!A:A," "),_xlfn.XLOOKUP(relatorio[[#This Row],['[Item'] Código]],CadastroProd!X:X,CadastroProd!A:A," ")) -> 2335 | R94: =IF(O94="Pendente",_xlfn.XLOOKUP(relatorio[[#This Row],[Número]],Relatório_CTE!A:A,Relatório_CTE!B:B,"Sem CTE")," ") -> 2314651 | S94: =IF(relatorio[[#This Row],[NFs Entrada - Winthor]]="Pendente",_xlfn.XLOOKUP(relatorio[[#This Row],[Número]],Relatório_CTE!A:A,Relatório_CTE!H:H,"Sem CTE")," ") -> 45919 | T94: =(IF(relatorio[[#This Row],[NFs Entrada - Winthor]]="Pendente",IF(relatorio[[#This Row],[Dt. CTE]]="Sem CTE",relatorio[[#This Row],[Data Emissão]]+_xlfn.XLOOKUP(relatorio[[#This Row],[De_Para]],'Lead Time - Histórico (Fornec.)'!B:B,'Lead Time - Histórico (Fornec.)'!C:C),relatorio[[#This Row],[Dt. CTE]]+_xlfn.XLOOKUP(relatorio[[#This Row],[Cód. Winthor]],'Lead Time - Histórico (Produto)'!A:A,'Lead Time - Histórico (Produto)'!C:C))," ")) -> 45935 | U94: =IFERROR(IF(WEEKDAY(relatorio[[#This Row],[Previsão de entrega - Bruto]],2)=6,relatorio[[#This Row],[Previsão de entrega - Bruto]]+2,IF(WEEKDAY(relatorio[[#This Row],[Previsão de entrega - Bruto]],2)=7,relatorio[[#This Row],[Previsão de entrega - Bruto]]+1,relatorio[[#This Row],[Previsão de entrega - Bruto]]))," ") -> 45936
A95: PUBLICO | B95: PB | C95: ADIUM S.A. | D95: 494888 | E95: 45919 | F95: 8702.26 | G95: 7892953000496 | H95: 907227 | I95: ELIGARD DS 22,5MG PL+DIL | J95: 46397 | K95: 16 | L95: =_xlfn.XLOOKUP(relatorio[[#This Row],[Nome PJ Emitente]],De_Para!A:A,De_Para!C:C) -> Adium | M95: {=IF(LEFT(G95&"",1)="0", IFERROR( VALUE(MID(G95&"",_xlfn.AGGREGATE(15,6,ROW(INDIRECT("1:"&LEN(G95&"")))/(MID(G95&"",ROW(INDIRECT("1:"&LEN(G95&""))),1)<>"0"),1),999)), MID(G95&"",_xlfn.AGGREGATE(15,6,ROW(INDIRECT("1:"&LEN(G95&"")))/(MID(G95&"",ROW(INDIRECT("1:"&LEN(G95&""))),1)<>"0"),1),999) ), IFERROR(VALUE(G95),G95))} -> 7892953000496 | N95: =TEXT(relatorio[[#This Row],[Data Emissão]],"mmm") -> set | O95: =_xlfn.XLOOKUP(relatorio[[#This Row],[Número]],relatorio_Entrada_NF!A:A,relatorio_Entrada_NF!A:A,"Pendente") -> 494888 | P95: =_xlfn.XLOOKUP(relatorio[[#This Row],[Nome PJ Emitente]],Material!A:A,Material!B:B,"Medicamento") -> Medicamento | Q95: =IF(relatorio[[#This Row],[Natureza]]="Medicamento",_xlfn.XLOOKUP(relatorio[[#This Row],[EAN]],CadastroProd!U:U,CadastroProd!A:A," "),_xlfn.XLOOKUP(relatorio[[#This Row],['[Item'] Código]],CadastroProd!X:X,CadastroProd!A:A," ")) -> 1566 | R95: =IF(O95="Pendente",_xlfn.XLOOKUP(relatorio[[#This Row],[Número]],Relatório_CTE!A:A,Relatório_CTE!B:B,"Sem CTE")," ") | S95: =IF(relatorio[[#This Row],[NFs Entrada - Winthor]]="Pendente",_xlfn.XLOOKUP(relatorio[[#This Row],[Número]],Relatório_CTE!A:A,Relatório_CTE!H:H,"Sem CTE")," ") | T95: =(IF(relatorio[[#This Row],[NFs Entrada - Winthor]]="Pendente",IF(relatorio[[#This Row],[Dt. CTE]]="Sem CTE",relatorio[[#This Row],[Data Emissão]]+_xlfn.XLOOKUP(relatorio[[#This Row],[De_Para]],'Lead Time - Histórico (Fornec.)'!B:B,'Lead Time - Histórico (Fornec.)'!C:C),relatorio[[#This Row],[Dt. CTE]]+_xlfn.XLOOKUP(relatorio[[#This Row],[Cód. Winthor]],'Lead Time - Histórico (Produto)'!A:A,'Lead Time - Histórico (Produto)'!C:C))," ")) | U95: =IFERROR(IF(WEEKDAY(relatorio[[#This Row],[Previsão de entrega - Bruto]],2)=6,relatorio[[#This Row],[Previsão de entrega - Bruto]]+2,IF(WEEKDAY(relatorio[[#This Row],[Previsão de entrega - Bruto]],2)=7,relatorio[[#This Row],[Previsão de entrega - Bruto]]+1,relatorio[[#This Row],[Previsão de entrega - Bruto]]))," ")
A96: PUBLICO | B96: PB | C96: NOVARTIS BIOCIENCIAS SA | D96: 501806 | E96: 45919 | F96: 83577.69 | G96: 7896261020450 | H96: 734974 | I96: MEKINIST 2MG 30 CE | J96: 46326 | K96: 6 | L96: =_xlfn.XLOOKUP(relatorio[[#This Row],[Nome PJ Emitente]],De_Para!A:A,De_Para!C:C) -> Novartis | M96: {=IF(LEFT(G96&"",1)="0", IFERROR( VALUE(MID(G96&"",_xlfn.AGGREGATE(15,6,ROW(INDIRECT("1:"&LEN(G96&"")))/(MID(G96&"",ROW(INDIRECT("1:"&LEN(G96&""))),1)<>"0"),1),999)), MID(G96&"",_xlfn.AGGREGATE(15,6,ROW(INDIRECT("1:"&LEN(G96&"")))/(MID(G96&"",ROW(INDIRECT("1:"&LEN(G96&""))),1)<>"0"),1),999) ), IFERROR(VALUE(G96),G96))} -> 7896261020450 | N96: =TEXT(relatorio[[#This Row],[Data Emissão]],"mmm") -> set | O96: =_xlfn.XLOOKUP(relatorio[[#This Row],[Número]],relatorio_Entrada_NF!A:A,relatorio_Entrada_NF!A:A,"Pendente") -> Pendente | P96: =_xlfn.XLOOKUP(relatorio[[#This Row],[Nome PJ Emitente]],Material!A:A,Material!B:B,"Medicamento") -> Medicamento | Q96: =IF(relatorio[[#This Row],[Natureza]]="Medicamento",_xlfn.XLOOKUP(relatorio[[#This Row],[EAN]],CadastroProd!U:U,CadastroProd!A:A," "),_xlfn.XLOOKUP(relatorio[[#This Row],['[Item'] Código]],CadastroProd!X:X,CadastroProd!A:A," ")) -> 1296 | R96: =IF(O96="Pendente",_xlfn.XLOOKUP(relatorio[[#This Row],[Número]],Relatório_CTE!A:A,Relatório_CTE!B:B,"Sem CTE")," ") -> 382531 | S96: =IF(relatorio[[#This Row],[NFs Entrada - Winthor]]="Pendente",_xlfn.XLOOKUP(relatorio[[#This Row],[Número]],Relatório_CTE!A:A,Relatório_CTE!H:H,"Sem CTE")," ") -> 45924 | T96: =(IF(relatorio[[#This Row],[NFs Entrada - Winthor]]="Pendente",IF(relatorio[[#This Row],[Dt. CTE]]="Sem CTE",relatorio[[#This Row],[Data Emissão]]+_xlfn.XLOOKUP(relatorio[[#This Row],[De_Para]],'Lead Time - Histórico (Fornec.)'!B:B,'Lead Time - Histórico (Fornec.)'!C:C),relatorio[[#This Row],[Dt. CTE]]+_xlfn.XLOOKUP(relatorio[[#This Row],[Cód. Winthor]],'Lead Time - Histórico (Produto)'!A:A,'Lead Time - Histórico (Produto)'!C:C))," ")) -> 45929 | U96: =IFERROR(IF(WEEKDAY(relatorio[[#This Row],[Previsão de entrega - Bruto]],2)=6,relatorio[[#This Row],[Previsão de entrega - Bruto]]+2,IF(WEEKDAY(relatorio[[#This Row],[Previsão de entrega - Bruto]],2)=7,relatorio[[#This Row],[Previsão de entrega - Bruto]]+1,relatorio[[#This Row],[Previsão de entrega - Bruto]]))," ") -> 45929
A97: PUBLICO | B97: PB | C97: NOVARTIS BIOCIENCIAS SA | D97: 501807 | E97: 45919 | F97: 27859.23 | G97: 7896261020450 | H97: 734974 | I97: MEKINIST 2MG 30 CE | J97: 46295 | K97: 2 | L97: =_xlfn.XLOOKUP(relatorio[[#This Row],[Nome PJ Emitente]],De_Para!A:A,De_Para!C:C) -> Novartis | M97: {=IF(LEFT(G97&"",1)="0", IFERROR( VALUE(MID(G97&"",_xlfn.AGGREGATE(15,6,ROW(INDIRECT("1:"&LEN(G97&"")))/(MID(G97&"",ROW(INDIRECT("1:"&LEN(G97&""))),1)<>"0"),1),999)), MID(G97&"",_xlfn.AGGREGATE(15,6,ROW(INDIRECT("1:"&LEN(G97&"")))/(MID(G97&"",ROW(INDIRECT("1:"&LEN(G97&""))),1)<>"0"),1),999) ), IFERROR(VALUE(G97),G97))} -> 7896261020450 | N97: =TEXT(relatorio[[#This Row],[Data Emissão]],"mmm") -> set | O97: =_xlfn.XLOOKUP(relatorio[[#This Row],[Número]],relatorio_Entrada_NF!A:A,relatorio_Entrada_NF!A:A,"Pendente") -> Pendente | P97: =_xlfn.XLOOKUP(relatorio[[#This Row],[Nome PJ Emitente]],Material!A:A,Material!B:B,"Medicamento") -> Medicamento | Q97: =IF(relatorio[[#This Row],[Natureza]]="Medicamento",_xlfn.XLOOKUP(relatorio[[#This Row],[EAN]],CadastroProd!U:U,CadastroProd!A:A," "),_xlfn.XLOOKUP(relatorio[[#This Row],['[Item'] Código]],CadastroProd!X:X,CadastroProd!A:A," ")) -> 1296 | R97: =IF(O97="Pendente",_xlfn.XLOOKUP(relatorio[[#This Row],[Número]],Relatório_CTE!A:A,Relatório_CTE!B:B,"Sem CTE")," ") -> 382533 | S97: =IF(relatorio[[#This Row],[NFs Entrada - Winthor]]="Pendente",_xlfn.XLOOKUP(relatorio[[#This Row],[Número]],Relatório_CTE!A:A,Relatório_CTE!H:H,"Sem CTE")," ") -> 45924 | T97: =(IF(relatorio[[#This Row],[NFs Entrada - Winthor]]="Pendente",IF(relatorio[[#This Row],[Dt. CTE]]="Sem CTE",relatorio[[#This Row],[Data Emissão]]+_xlfn.XLOOKUP(relatorio[[#This Row],[De_Para]],'Lead Time - Histórico (Fornec.)'!B:B,'Lead Time - Histórico (Fornec.)'!C:C),relatorio[[#This Row],[Dt. CTE]]+_xlfn.XLOOKUP(relatorio[[#This Row],[Cód. Winthor]],'Lead Time - Histórico (Produto)'!A:A,'Lead Time - Histórico (Produto)'!C:C))," ")) -> 45929 | U97: =IFERROR(IF(WEEKDAY(relatorio[[#This Row],[Previsão de entrega - Bruto]],2)=6,relatorio[[#This Row],[Previsão de entrega - Bruto]]+2,IF(WEEKDAY(relatorio[[#This Row],[Previsão de entrega - Bruto]],2)=7,relatorio[[#This Row],[Previsão de entrega - Bruto]]+1,relatorio[[#This Row],[Previsão de entrega - Bruto]]))," ") -> 45929
A98: PRIVADO | B98: CE | C98: GLAXOSMITHKLINE BRASIL LTDA | D98: 251539 | E98: 45919 | F98: 62349.98 | G98: 7896015592066 | H98: 60000000126651 | I98: ZEJULA 100MG 56CAPS | J98: 46326 | K98: 2 | L98: =_xlfn.XLOOKUP(relatorio[[#This Row],[Nome PJ Emitente]],De_Para!A:A,De_Para!C:C) -> GSK | M98: {=IF(LEFT(G98&"",1)="0", IFERROR( VALUE(MID(G98&"",_xlfn.AGGREGATE(15,6,ROW(INDIRECT("1:"&LEN(G98&"")))/(MID(G98&"",ROW(INDIRECT("1:"&LEN(G98&""))),1)<>"0"),1),999)), MID(G98&"",_xlfn.AGGREGATE(15,6,ROW(INDIRECT("1:"&LEN(G98&"")))/(MID(G98&"",ROW(INDIRECT("1:"&LEN(G98&""))),1)<>"0"),1),999) ), IFERROR(VALUE(G98),G98))} -> 7896015592066 | N98: =TEXT(relatorio[[#This Row],[Data Emissão]],"mmm") -> set | O98: =_xlfn.XLOOKUP(relatorio[[#This Row],[Número]],relatorio_Entrada_NF!A:A,relatorio_Entrada_NF!A:A,"Pendente") -> Pendente | P98: =_xlfn.XLOOKUP(relatorio[[#This Row],[Nome PJ Emitente]],Material!A:A,Material!B:B,"Medicamento") -> Medicamento | Q98: =IF(relatorio[[#This Row],[Natureza]]="Medicamento",_xlfn.XLOOKUP(relatorio[[#This Row],[EAN]],CadastroProd!U:U,CadastroProd!A:A," "),_xlfn.XLOOKUP(relatorio[[#This Row],['[Item'] Código]],CadastroProd!X:X,CadastroProd!A:A," ")) -> 3199 | R98: =IF(O98="Pendente",_xlfn.XLOOKUP(relatorio[[#This Row],[Número]],Relatório_CTE!A:A,Relatório_CTE!B:B,"Sem CTE")," ") -> 1435 | S98: =IF(relatorio[[#This Row],[NFs Entrada - Winthor]]="Pendente",_xlfn.XLOOKUP(relatorio[[#This Row],[Número]],Relatório_CTE!A:A,Relatório_CTE!H:H,"Sem CTE")," ") -> 45922 | T98: =(IF(relatorio[[#This Row],[NFs Entrada - Winthor]]="Pendente",IF(relatorio[[#This Row],[Dt. CTE]]="Sem CTE",relatorio[[#This Row],[Data Emissão]]+_xlfn.XLOOKUP(relatorio[[#This Row],[De_Para]],'Lead Time - Histórico (Fornec.)'!B:B,'Lead Time - Histórico (Fornec.)'!C:C),relatorio[[#This Row],[Dt. CTE]]+_xlfn.XLOOKUP(relatorio[[#This Row],[Cód. Winthor]],'Lead Time - Histórico (Produto)'!A:A,'Lead Time - Histórico (Produto)'!C:C))," ")) -> 45925 | U98: =IFERROR(IF(WEEKDAY(relatorio[[#This Row],[Previsão de entrega - Bruto]],2)=6,relatorio[[#This Row],[Previsão de entrega - Bruto]]+2,IF(WEEKDAY(relatorio[[#This Row],[Previsão de entrega - Bruto]],2)=7,relatorio[[#This Row],[Previsão de entrega - Bruto]]+1,relatorio[[#This Row],[Previsão de entrega - Bruto]]))," ") -> 45925
A99: PRIVADO | B99: CE | C99: GLAXOSMITHKLINE BRASIL LTDA | D99: 251539 | E99: 45919 | F99: 62349.98 | G99: 7896015592059 | H99: 60000000130642 | I99: ZEJULA 100MG 28CAPS | J99: 46326 | K99: 2 | L99: =_xlfn.XLOOKUP(relatorio[[#This Row],[Nome PJ Emitente]],De_Para!A:A,De_Para!C:C) -> GSK | M99: {=IF(LEFT(G99&"",1)="0", IFERROR( VALUE(MID(G99&"",_xlfn.AGGREGATE(15,6,ROW(INDIRECT("1:"&LEN(G99&"")))/(MID(G99&"",ROW(INDIRECT("1:"&LEN(G99&""))),1)<>"0"),1),999)), MID(G99&"",_xlfn.AGGREGATE(15,6,ROW(INDIRECT("1:"&LEN(G99&"")))/(MID(G99&"",ROW(INDIRECT("1:"&LEN(G99&""))),1)<>"0"),1),999) ), IFERROR(VALUE(G99),G99))} -> 7896015592059 | N99: =TEXT(relatorio[[#This Row],[Data Emissão]],"mmm") -> set | O99: =_xlfn.XLOOKUP(relatorio[[#This Row],[Número]],relatorio_Entrada_NF!A:A,relatorio_Entrada_NF!A:A,"Pendente") -> Pendente | P99: =_xlfn.XLOOKUP(relatorio[[#This Row],[Nome PJ Emitente]],Material!A:A,Material!B:B,"Medicamento") -> Medicamento | Q99: =IF(relatorio[[#This Row],[Natureza]]="Medicamento",_xlfn.XLOOKUP(relatorio[[#This Row],[EAN]],CadastroProd!U:U,CadastroProd!A:A," "),_xlfn.XLOOKUP(relatorio[[#This Row],['[Item'] Código]],CadastroProd!X:X,CadastroProd!A:A," ")) -> 3335 | R99: =IF(O99="Pendente",_xlfn.XLOOKUP(relatorio[[#This Row],[Número]],Relatório_CTE!A:A,Relatório_CTE!B:B,"Sem CTE")," ") -> 1435 | S99: =IF(relatorio[[#This Row],[NFs Entrada - Winthor]]="Pendente",_xlfn.XLOOKUP(relatorio[[#This Row],[Número]],Relatório_CTE!A:A,Relatório_CTE!H:H,"Sem CTE")," ") -> 45922 | T99: =(IF(relatorio[[#This Row],[NFs Entrada - Winthor]]="Pendente",IF(relatorio[[#This Row],[Dt. CTE]]="Sem CTE",relatorio[[#This Row],[Data Emissão]]+_xlfn.XLOOKUP(relatorio[[#This Row],[De_Para]],'Lead Time - Histórico (Fornec.)'!B:B,'Lead Time - Histórico (Fornec.)'!C:C),relatorio[[#This Row],[Dt. CTE]]+_xlfn.XLOOKUP(relatorio[[#This Row],[Cód. Winthor]],'Lead Time - Histórico (Produto)'!A:A,'Lead Time - Histórico (Produto)'!C:C))," ")) -> 45926 | U99: =IFERROR(IF(WEEKDAY(relatorio[[#This Row],[Previsão de entrega - Bruto]],2)=6,relatorio[[#This Row],[Previsão de entrega - Bruto]]+2,IF(WEEKDAY(relatorio[[#This Row],[Previsão de entrega - Bruto]],2)=7,relatorio[[#This Row],[Previsão de entrega - Bruto]]+1,relatorio[[#This Row],[Previsão de entrega - Bruto]]))," ") -> 45926
A100: PRIVADO | B100: CE | C100: GLAXOSMITHKLINE BRASIL LTDA | D100: 251540 | E100: 45919 | F100: 9407.19 | G100: 7896015592059 | H100: 60000000130642 | I100: ZEJULA 100MG 28CAPS | J100: 46326 | K100: 1 | L100: =_xlfn.XLOOKUP(relatorio[[#This Row],[Nome PJ Emitente]],De_Para!A:A,De_Para!C:C) -> GSK | M100: {=IF(LEFT(G100&"",1)="0", IFERROR( VALUE(MID(G100&"",_xlfn.AGGREGATE(15,6,ROW(INDIRECT("1:"&LEN(G100&"")))/(MID(G100&"",ROW(INDIRECT("1:"&LEN(G100&""))),1)<>"0"),1),999)), MID(G100&"",_xlfn.AGGREGATE(15,6,ROW(INDIRECT("1:"&LEN(G100&"")))/(MID(G100&"",ROW(INDIRECT("1:"&LEN(G100&""))),1)<>"0"),1),999) ), IFERROR(VALUE(G100),G100))} -> 7896015592059 | N100: =TEXT(relatorio[[#This Row],[Data Emissão]],"mmm") -> set | O100: =_xlfn.XLOOKUP(relatorio[[#This Row],[Número]],relatorio_Entrada_NF!A:A,relatorio_Entrada_NF!A:A,"Pendente") -> Pendente | P100: =_xlfn.XLOOKUP(relatorio[[#This Row],[Nome PJ Emitente]],Material!A:A,Material!B:B,"Medicamento") -> Medicamento | Q100: =IF(relatorio[[#This Row],[Natureza]]="Medicamento",_xlfn.XLOOKUP(relatorio[[#This Row],[EAN]],CadastroProd!U:U,CadastroProd!A:A," "),_xlfn.XLOOKUP(relatorio[[#This Row],['[Item'] Código]],CadastroProd!X:X,CadastroProd!A:A," ")) -> 3335 | R100: =IF(O100="Pendente",_xlfn.XLOOKUP(relatorio[[#This Row],[Número]],Relatório_CTE!A:A,Relatório_CTE!B:B,"Sem CTE")," ") -> 1435 | S100: =IF(relatorio[[#This Row],[NFs Entrada - Winthor]]="Pendente",_xlfn.XLOOKUP(relatorio[[#This Row],[Número]],Relatório_CTE!A:A,Relatório_CTE!H:H,"Sem CTE")," ") -> 45922 | T100: =(IF(relatorio[[#This Row],[NFs Entrada - Winthor]]="Pendente",IF(relatorio[[#This Row],[Dt. CTE]]="Sem CTE",relatorio[[#This Row],[Data Emissão]]+_xlfn.XLOOKUP(relatorio[[#This Row],[De_Para]],'Lead Time - Histórico (Fornec.)'!B:B,'Lead Time - Histórico (Fornec.)'!C:C),relatorio[[#This Row],[Dt. CTE]]+_xlfn.XLOOKUP(relatorio[[#This Row],[Cód. Winthor]],'Lead Time - Histórico (Produto)'!A:A,'Lead Time - Histórico (Produto)'!C:C))," ")) -> 45926 | U100: =IFERROR(IF(WEEKDAY(relatorio[[#This Row],[Previsão de entrega - Bruto]],2)=6,relatorio[[#This Row],[Previsão de entrega - Bruto]]+2,IF(WEEKDAY(relatorio[[#This Row],[Previsão de entrega - Bruto]],2)=7,relatorio[[#This Row],[Previsão de entrega - Bruto]]+1,relatorio[[#This Row],[Previsão de entrega - Bruto]]))," ") -> 45926
A101: PRIVADO | B101: CE | C101: GLAXOSMITHKLINE BRASIL LTDA | D101: 251541 | E101: 45919 | F101: 19689.47 | G101: 7896015592066 | H101: 60000000126651 | I101: ZEJULA 100MG 56CAPS | J101: 46326 | K101: 1 | L101: =_xlfn.XLOOKUP(relatorio[[#This Row],[Nome PJ Emitente]],De_Para!A:A,De_Para!C:C) -> GSK | M101: {=IF(LEFT(G101&"",1)="0", IFERROR( VALUE(MID(G101&"",_xlfn.AGGREGATE(15,6,ROW(INDIRECT("1:"&LEN(G101&"")))/(MID(G101&"",ROW(INDIRECT("1:"&LEN(G101&""))),1)<>"0"),1),999)), MID(G101&"",_xlfn.AGGREGATE(15,6,ROW(INDIRECT("1:"&LEN(G101&"")))/(MID(G101&"",ROW(INDIRECT("1:"&LEN(G101&""))),1)<>"0"),1),999) ), IFERROR(VALUE(G101),G101))} -> 7896015592066 | N101: =TEXT(relatorio[[#This Row],[Data Emissão]],"mmm") -> set | O101: =_xlfn.XLOOKUP(relatorio[[#This Row],[Número]],relatorio_Entrada_NF!A:A,relatorio_Entrada_NF!A:A,"Pendente") -> Pendente | P101: =_xlfn.XLOOKUP(relatorio[[#This Row],[Nome PJ Emitente]],Material!A:A,Material!B:B,"Medicamento") -> Medicamento | Q101: =IF(relatorio[[#This Row],[Natureza]]="Medicamento",_xlfn.XLOOKUP(relatorio[[#This Row],[EAN]],CadastroProd!U:U,CadastroProd!A:A," "),_xlfn.XLOOKUP(relatorio[[#This Row],['[Item'] Código]],CadastroProd!X:X,CadastroProd!A:A," ")) -> 3199 | R101: =IF(O101="Pendente",_xlfn.XLOOKUP(relatorio[[#This Row],[Número]],Relatório_CTE!A:A,Relatório_CTE!B:B,"Sem CTE")," ") -> 1435 | S101: =IF(relatorio[[#This Row],[NFs Entrada - Winthor]]="Pendente",_xlfn.XLOOKUP(relatorio[[#This Row],[Número]],Relatório_CTE!A:A,Relatório_CTE!H:H,"Sem CTE")," ") -> 45922 | T101: =(IF(relatorio[[#This Row],[NFs Entrada - Winthor]]="Pendente",IF(relatorio[[#This Row],[Dt. CTE]]="Sem CTE",relatorio[[#This Row],[Data Emissão]]+_xlfn.XLOOKUP(relatorio[[#This Row],[De_Para]],'Lead Time - Histórico (Fornec.)'!B:B,'Lead Time - Histórico (Fornec.)'!C:C),relatorio[[#This Row],[Dt. CTE]]+_xlfn.XLOOKUP(relatorio[[#This Row],[Cód. Winthor]],'Lead Time - Histórico (Produto)'!A:A,'Lead Time - Histórico (Produto)'!C:C))," ")) -> 45925 | U101: =IFERROR(IF(WEEKDAY(relatorio[[#This Row],[Previsão de entrega - Bruto]],2)=6,relatorio[[#This Row],[Previsão de entrega - Bruto]]+2,IF(WEEKDAY(relatorio[[#This Row],[Previsão de entrega - Bruto]],2)=7,relatorio[[#This Row],[Previsão de entrega - Bruto]]+1,relatorio[[#This Row],[Previsão de entrega - Bruto]]))," ") -> 45925
A102: PRIVADO | B102: CE | C102: Eli Lilly do Brasil Ltda. | D102: 447284 | E102: 45919 | F102: 142850.65 | G102: 7896382708480 | H102: TA533769VBL | I102: VERZENIOS 150MG X30 COMP BL | J102: 46507 | K102: 20 | L102: =_xlfn.XLOOKUP(relatorio[[#This Row],[Nome PJ Emitente]],De_Para!A:A,De_Para!C:C) -> Eli Lilly | M102: {=IF(LEFT(G102&"",1)="0", IFERROR( VALUE(MID(G102&"",_xlfn.AGGREGATE(15,6,ROW(INDIRECT("1:"&LEN(G102&"")))/(MID(G102&"",ROW(INDIRECT("1:"&LEN(G102&""))),1)<>"0"),1),999)), MID(G102&"",_xlfn.AGGREGATE(15,6,ROW(INDIRECT("1:"&LEN(G102&"")))/(MID(G102&"",ROW(INDIRECT("1:"&LEN(G102&""))),1)<>"0"),1),999) ), IFERROR(VALUE(G102),G102))} -> 7896382708480 | N102: =TEXT(relatorio[[#This Row],[Data Emissão]],"mmm") -> set | O102: =_xlfn.XLOOKUP(relatorio[[#This Row],[Número]],relatorio_Entrada_NF!A:A,relatorio_Entrada_NF!A:A,"Pendente") -> Pendente | P102: =_xlfn.XLOOKUP(relatorio[[#This Row],[Nome PJ Emitente]],Material!A:A,Material!B:B,"Medicamento") -> Medicamento | Q102: =IF(relatorio[[#This Row],[Natureza]]="Medicamento",_xlfn.XLOOKUP(relatorio[[#This Row],[EAN]],CadastroProd!U:U,CadastroProd!A:A," "),_xlfn.XLOOKUP(relatorio[[#This Row],['[Item'] Código]],CadastroProd!X:X,CadastroProd!A:A," ")) -> 2889 | R102: =IF(O102="Pendente",_xlfn.XLOOKUP(relatorio[[#This Row],[Número]],Relatório_CTE!A:A,Relatório_CTE!B:B,"Sem CTE")," ") -> 132939 | S102: =IF(relatorio[[#This Row],[NFs Entrada - Winthor]]="Pendente",_xlfn.XLOOKUP(relatorio[[#This Row],[Número]],Relatório_CTE!A:A,Relatório_CTE!H:H,"Sem CTE")," ") -> 45923 | T102: =(IF(relatorio[[#This Row],[NFs Entrada - Winthor]]="Pendente",IF(relatorio[[#This Row],[Dt. CTE]]="Sem CTE",relatorio[[#This Row],[Data Emissão]]+_xlfn.XLOOKUP(relatorio[[#This Row],[De_Para]],'Lead Time - Histórico (Fornec.)'!B:B,'Lead Time - Histórico (Fornec.)'!C:C),relatorio[[#This Row],[Dt. CTE]]+_xlfn.XLOOKUP(relatorio[[#This Row],[Cód. Winthor]],'Lead Time - Histórico (Produto)'!A:A,'Lead Time - Histórico (Produto)'!C:C))," ")) -> 45934 | U102: =IFERROR(IF(WEEKDAY(relatorio[[#This Row],[Previsão de entrega - Bruto]],2)=6,relatorio[[#This Row],[Previsão de entrega - Bruto]]+2,IF(WEEKDAY(relatorio[[#This Row],[Previsão de entrega - Bruto]],2)=7,relatorio[[#This Row],[Previsão de entrega - Bruto]]+1,relatorio[[#This Row],[Previsão de entrega - Bruto]]))," ") -> 45936
A103: PRIVADO | B103: CE | C103: Eli Lilly do Brasil Ltda. | D103: 447293 | E103: 45919 | F103: 222262.18 | G103: 7896382708060 | H103: PS1445001BL | I103: TALTZ AUTOINJECTOR 80MG X 1PEND BL | J103: 46387 | K103: 50 | L103: =_xlfn.XLOOKUP(relatorio[[#This Row],[Nome PJ Emitente]],De_Para!A:A,De_Para!C:C) -> Eli Lilly | M103: {=IF(LEFT(G103&"",1)="0", IFERROR( VALUE(MID(G103&"",_xlfn.AGGREGATE(15,6,ROW(INDIRECT("1:"&LEN(G103&"")))/(MID(G103&"",ROW(INDIRECT("1:"&LEN(G103&""))),1)<>"0"),1),999)), MID(G103&"",_xlfn.AGGREGATE(15,6,ROW(INDIRECT("1:"&LEN(G103&"")))/(MID(G103&"",ROW(INDIRECT("1:"&LEN(G103&""))),1)<>"0"),1),999) ), IFERROR(VALUE(G103),G103))} -> 7896382708060 | N103: =TEXT(relatorio[[#This Row],[Data Emissão]],"mmm") -> set | O103: =_xlfn.XLOOKUP(relatorio[[#This Row],[Número]],relatorio_Entrada_NF!A:A,relatorio_Entrada_NF!A:A,"Pendente") -> Pendente | P103: =_xlfn.XLOOKUP(relatorio[[#This Row],[Nome PJ Emitente]],Material!A:A,Material!B:B,"Medicamento") -> Medicamento | Q103: =IF(relatorio[[#This Row],[Natureza]]="Medicamento",_xlfn.XLOOKUP(relatorio[[#This Row],[EAN]],CadastroProd!U:U,CadastroProd!A:A," "),_xlfn.XLOOKUP(relatorio[[#This Row],['[Item'] Código]],CadastroProd!X:X,CadastroProd!A:A," ")) -> 3330 | R103: =IF(O103="Pendente",_xlfn.XLOOKUP(relatorio[[#This Row],[Número]],Relatório_CTE!A:A,Relatório_CTE!B:B,"Sem CTE")," ") -> 133206 | S103: =IF(relatorio[[#This Row],[NFs Entrada - Winthor]]="Pendente",_xlfn.XLOOKUP(relatorio[[#This Row],[Número]],Relatório_CTE!A:A,Relatório_CTE!H:H,"Sem CTE")," ") -> 45923 | T103: =(IF(relatorio[[#This Row],[NFs Entrada - Winthor]]="Pendente",IF(relatorio[[#This Row],[Dt. CTE]]="Sem CTE",relatorio[[#This Row],[Data Emissão]]+_xlfn.XLOOKUP(relatorio[[#This Row],[De_Para]],'Lead Time - Histórico (Fornec.)'!B:B,'Lead Time - Histórico (Fornec.)'!C:C),relatorio[[#This Row],[Dt. CTE]]+_xlfn.XLOOKUP(relatorio[[#This Row],[Cód. Winthor]],'Lead Time - Histórico (Produto)'!A:A,'Lead Time - Histórico (Produto)'!C:C))," ")) -> 45927 | U103: =IFERROR(IF(WEEKDAY(relatorio[[#This Row],[Previsão de entrega - Bruto]],2)=6,relatorio[[#This Row],[Previsão de entrega - Bruto]]+2,IF(WEEKDAY(relatorio[[#This Row],[Previsão de entrega - Bruto]],2)=7,relatorio[[#This Row],[Previsão de entrega - Bruto]]+1,relatorio[[#This Row],[Previsão de entrega - Bruto]]))," ") -> 45929
A104: PRIVADO | B104: CE | C104: Eli Lilly do Brasil Ltda. | D104: 447294 | E104: 45919 | F104: 15615.56 | G104: 7896382708299 | H104: TA447969VBL | I104: OLUMIANT 4MG X 30 COMP BL | J104: 46660 | K104: 4 | L104: =_xlfn.XLOOKUP(relatorio[[#This Row],[Nome PJ Emitente]],De_Para!A:A,De_Para!C:C) -> Eli Lilly | M104: {=IF(LEFT(G104&"",1)="0", IFERROR( VALUE(MID(G104&"",_xlfn.AGGREGATE(15,6,ROW(INDIRECT("1:"&LEN(G104&"")))/(MID(G104&"",ROW(INDIRECT("1:"&LEN(G104&""))),1)<>"0"),1),999)), MID(G104&"",_xlfn.AGGREGATE(15,6,ROW(INDIRECT("1:"&LEN(G104&"")))/(MID(G104&"",ROW(INDIRECT("1:"&LEN(G104&""))),1)<>"0"),1),999) ), IFERROR(VALUE(G104),G104))} -> 7896382708299 | N104: =TEXT(relatorio[[#This Row],[Data Emissão]],"mmm") -> set | O104: =_xlfn.XLOOKUP(relatorio[[#This Row],[Número]],relatorio_Entrada_NF!A:A,relatorio_Entrada_NF!A:A,"Pendente") -> Pendente | P104: =_xlfn.XLOOKUP(relatorio[[#This Row],[Nome PJ Emitente]],Material!A:A,Material!B:B,"Medicamento") -> Medicamento | Q104: =IF(relatorio[[#This Row],[Natureza]]="Medicamento",_xlfn.XLOOKUP(relatorio[[#This Row],[EAN]],CadastroProd!U:U,CadastroProd!A:A," "),_xlfn.XLOOKUP(relatorio[[#This Row],['[Item'] Código]],CadastroProd!X:X,CadastroProd!A:A," ")) -> 3322 | R104: =IF(O104="Pendente",_xlfn.XLOOKUP(relatorio[[#This Row],[Número]],Relatório_CTE!A:A,Relatório_CTE!B:B,"Sem CTE")," ") -> 132939 | S104: =IF(relatorio[[#This Row],[NFs Entrada - Winthor]]="Pendente",_xlfn.XLOOKUP(relatorio[[#This Row],[Número]],Relatório_CTE!A:A,Relatório_CTE!H:H,"Sem CTE")," ") -> 45923 | T104: =(IF(relatorio[[#This Row],[NFs Entrada - Winthor]]="Pendente",IF(relatorio[[#This Row],[Dt. CTE]]="Sem CTE",relatorio[[#This Row],[Data Emissão]]+_xlfn.XLOOKUP(relatorio[[#This Row],[De_Para]],'Lead Time - Histórico (Fornec.)'!B:B,'Lead Time - Histórico (Fornec.)'!C:C),relatorio[[#This Row],[Dt. CTE]]+_xlfn.XLOOKUP(relatorio[[#This Row],[Cód. Winthor]],'Lead Time - Histórico (Produto)'!A:A,'Lead Time - Histórico (Produto)'!C:C))," ")) -> 45930 | U104: =IFERROR(IF(WEEKDAY(relatorio[[#This Row],[Previsão de entrega - Bruto]],2)=6,relatorio[[#This Row],[Previsão de entrega - Bruto]]+2,IF(WEEKDAY(relatorio[[#This Row],[Previsão de entrega - Bruto]],2)=7,relatorio[[#This Row],[Previsão de entrega - Bruto]]+1,relatorio[[#This Row],[Previsão de entrega - Bruto]]))," ") -> 45930
... A191: PRIVADO | B191: CE | C191: 3M DO BRASIL LTDA | D191: 509463 | E191: 45917 | F191: 106791.55 | G191: 7891040010745 | H191: H0001400839 | I191: 1530 50MMX10M CARRETEL FITA CIRURGICA HIPO. MICROPORE | J191: 46579 | K191: 3960 | L191: =_xlfn.XLOOKUP(relatorio[[#This Row],[Nome PJ Emitente]],De_Para!A:A,De_Para!C:C) -> 3M | M191: {=IF(LEFT(G191&"",1)="0", IFERROR( VALUE(MID(G191&"",_xlfn.AGGREGATE(15,6,ROW(INDIRECT("1:"&LEN(G191&"")))/(MID(G191&"",ROW(INDIRECT("1:"&LEN(G191&""))),1)<>"0"),1),999)), MID(G191&"",_xlfn.AGGREGATE(15,6,ROW(INDIRECT("1:"&LEN(G191&"")))/(MID(G191&"",ROW(INDIRECT("1:"&LEN(G191&""))),1)<>"0"),1),999) ), IFERROR(VALUE(G191),G191))} -> 7891040010745 | N191: =TEXT(relatorio[[#This Row],[Data Emissão]],"mmm") -> set | O191: =_xlfn.XLOOKUP(relatorio[[#This Row],[Número]],relatorio_Entrada_NF!A:A,relatorio_Entrada_NF!A:A,"Pendente") -> Pendente | P191: =_xlfn.XLOOKUP(relatorio[[#This Row],[Nome PJ Emitente]],Material!A:A,Material!B:B,"Medicamento") -> Material | Q191: =IF(relatorio[[#This Row],[Natureza]]="Medicamento",_xlfn.XLOOKUP(relatorio[[#This Row],[EAN]],CadastroProd!U:U,CadastroProd!A:A," "),_xlfn.XLOOKUP(relatorio[[#This Row],['[Item'] Código]],CadastroProd!X:X,CadastroProd!A:A," ")) -> 2175 | R191: =IF(O191="Pendente",_xlfn.XLOOKUP(relatorio[[#This Row],[Número]],Relatório_CTE!A:A,Relatório_CTE!B:B,"Sem CTE")," ") -> 4791 | S191: =IF(relatorio[[#This Row],[NFs Entrada - Winthor]]="Pendente",_xlfn.XLOOKUP(relatorio[[#This Row],[Número]],Relatório_CTE!A:A,Relatório_CTE!H:H,"Sem CTE")," ") -> 45918 | T191: =(IF(relatorio[[#This Row],[NFs Entrada - Winthor]]="Pendente",IF(relatorio[[#This Row],[Dt. CTE]]="Sem CTE",relatorio[[#This Row],[Data Emissão]]+_xlfn.XLOOKUP(relatorio[[#This Row],[De_Para]],'Lead Time - Histórico (Fornec.)'!B:B,'Lead Time - Histórico (Fornec.)'!C:C),relatorio[[#This Row],[Dt. CTE]]+_xlfn.XLOOKUP(relatorio[[#This Row],[Cód. Winthor]],'Lead Time - Histórico (Produto)'!A:A,'Lead Time - Histórico (Produto)'!C:C))," ")) -> 45934 | U191: =IFERROR(IF(WEEKDAY(relatorio[[#This Row],[Previsão de entrega - Bruto]],2)=6,relatorio[[#This Row],[Previsão de entrega - Bruto]]+2,IF(WEEKDAY(relatorio[[#This Row],[Previsão de entrega - Bruto]],2)=7,relatorio[[#This Row],[Previsão de entrega - Bruto]]+1,relatorio[[#This Row],[Previsão de entrega - Bruto]]))," ") -> 45936
A192: PRIVADO | B192: CE | C192: 3M DO BRASIL LTDA | D192: 509463 | E192: 45917 | F192: 106791.55 | G192: SEM GTIN | H192: H0001556473 | I192: 2269T NEO 10 SC C/ 3 UNID CADA ELETRODO RED DOT | K192: 2 | L192: =_xlfn.XLOOKUP(relatorio[[#This Row],[Nome PJ Emitente]],De_Para!A:A,De_Para!C:C) -> 3M | M192: {=IF(LEFT(G192&"",1)="0", IFERROR( VALUE(MID(G192&"",_xlfn.AGGREGATE(15,6,ROW(INDIRECT("1:"&LEN(G192&"")))/(MID(G192&"",ROW(INDIRECT("1:"&LEN(G192&""))),1)<>"0"),1),999)), MID(G192&"",_xlfn.AGGREGATE(15,6,ROW(INDIRECT("1:"&LEN(G192&"")))/(MID(G192&"",ROW(INDIRECT("1:"&LEN(G192&""))),1)<>"0"),1),999) ), IFERROR(VALUE(G192),G192))} -> SEM GTIN | N192: =TEXT(relatorio[[#This Row],[Data Emissão]],"mmm") -> set | O192: =_xlfn.XLOOKUP(relatorio[[#This Row],[Número]],relatorio_Entrada_NF!A:A,relatorio_Entrada_NF!A:A,"Pendente") -> Pendente | P192: =_xlfn.XLOOKUP(relatorio[[#This Row],[Nome PJ Emitente]],Material!A:A,Material!B:B,"Medicamento") -> Material | Q192: =IF(relatorio[[#This Row],[Natureza]]="Medicamento",_xlfn.XLOOKUP(relatorio[[#This Row],[EAN]],CadastroProd!U:U,CadastroProd!A:A," "),_xlfn.XLOOKUP(relatorio[[#This Row],['[Item'] Código]],CadastroProd!X:X,CadastroProd!A:A," ")) -> 2367 | R192: =IF(O192="Pendente",_xlfn.XLOOKUP(relatorio[[#This Row],[Número]],Relatório_CTE!A:A,Relatório_CTE!B:B,"Sem CTE")," ") -> 4791 | S192: =IF(relatorio[[#This Row],[NFs Entrada - Winthor]]="Pendente",_xlfn.XLOOKUP(relatorio[[#This Row],[Número]],Relatório_CTE!A:A,Relatório_CTE!H:H,"Sem CTE")," ") -> 45918 | T192: =(IF(relatorio[[#This Row],[NFs Entrada - Winthor]]="Pendente",IF(relatorio[[#This Row],[Dt. CTE]]="Sem CTE",relatorio[[#This Row],[Data Emissão]]+_xlfn.XLOOKUP(relatorio[[#This Row],[De_Para]],'Lead Time - Histórico (Fornec.)'!B:B,'Lead Time - Histórico (Fornec.)'!C:C),relatorio[[#This Row],[Dt. CTE]]+_xlfn.XLOOKUP(relatorio[[#This Row],[Cód. Winthor]],'Lead Time - Histórico (Produto)'!A:A,'Lead Time - Histórico (Produto)'!C:C))," ")) -> 45933 | U192: =IFERROR(IF(WEEKDAY(relatorio[[#This Row],[Previsão de entrega - Bruto]],2)=6,relatorio[[#This Row],[Previsão de entrega - Bruto]]+2,IF(WEEKDAY(relatorio[[#This Row],[Previsão de entrega - Bruto]],2)=7,relatorio[[#This Row],[Previsão de entrega - Bruto]]+1,relatorio[[#This Row],[Previsão de entrega - Bruto]]))," ") -> 45933
A193: PRIVADO | B193: CE | C193: 3M DO BRASIL LTDA | D193: 509463 | E193: 45917 | F193: 106791.55 | G193: 7891040086870 | H193: H0002033613 | I193: 9160F UNIVERSAL REM CX C/ 200 PLACA ELETROCIRURGICA | J193: 46775 | K193: 5400 | L193: =_xlfn.XLOOKUP(relatorio[[#This Row],[Nome PJ Emitente]],De_Para!A:A,De_Para!C:C) -> 3M | M193: {=IF(LEFT(G193&"",1)="0", IFERROR( VALUE(MID(G193&"",_xlfn.AGGREGATE(15,6,ROW(INDIRECT("1:"&LEN(G193&"")))/(MID(G193&"",ROW(INDIRECT("1:"&LEN(G193&""))),1)<>"0"),1),999)), MID(G193&"",_xlfn.AGGREGATE(15,6,ROW(INDIRECT("1:"&LEN(G193&"")))/(MID(G193&"",ROW(INDIRECT("1:"&LEN(G193&""))),1)<>"0"),1),999) ), IFERROR(VALUE(G193),G193))} -> 7891040086870 | N193: =TEXT(relatorio[[#This Row],[Data Emissão]],"mmm") -> set | O193: =_xlfn.XLOOKUP(relatorio[[#This Row],[Número]],relatorio_Entrada_NF!A:A,relatorio_Entrada_NF!A:A,"Pendente") -> Pendente | P193: =_xlfn.XLOOKUP(relatorio[[#This Row],[Nome PJ Emitente]],Material!A:A,Material!B:B,"Medicamento") -> Material | Q193: =IF(relatorio[[#This Row],[Natureza]]="Medicamento",_xlfn.XLOOKUP(relatorio[[#This Row],[EAN]],CadastroProd!U:U,CadastroProd!A:A," "),_xlfn.XLOOKUP(relatorio[[#This Row],['[Item'] Código]],CadastroProd!X:X,CadastroProd!A:A," ")) -> 2380 | R193: =IF(O193="Pendente",_xlfn.XLOOKUP(relatorio[[#This Row],[Número]],Relatório_CTE!A:A,Relatório_CTE!B:B,"Sem CTE")," ") -> 4791 | S193: =IF(relatorio[[#This Row],[NFs Entrada - Winthor]]="Pendente",_xlfn.XLOOKUP(relatorio[[#This Row],[Número]],Relatório_CTE!A:A,Relatório_CTE!H:H,"Sem CTE")," ") -> 45918 | T193: =(IF(relatorio[[#This Row],[NFs Entrada - Winthor]]="Pendente",IF(relatorio[[#This Row],[Dt. CTE]]="Sem CTE",relatorio[[#This Row],[Data Emissão]]+_xlfn.XLOOKUP(relatorio[[#This Row],[De_Para]],'Lead Time - Histórico (Fornec.)'!B:B,'Lead Time - Histórico (Fornec.)'!C:C),relatorio[[#This Row],[Dt. CTE]]+_xlfn.XLOOKUP(relatorio[[#This Row],[Cód. Winthor]],'Lead Time - Histórico (Produto)'!A:A,'Lead Time - Histórico (Produto)'!C:C))," ")) -> 45933 | U193: =IFERROR(IF(WEEKDAY(relatorio[[#This Row],[Previsão de entrega - Bruto]],2)=6,relatorio[[#This Row],[Previsão de entrega - Bruto]]+2,IF(WEEKDAY(relatorio[[#This Row],[Previsão de entrega - Bruto]],2)=7,relatorio[[#This Row],[Previsão de entrega - Bruto]]+1,relatorio[[#This Row],[Previsão de entrega - Bruto]]))," ") -> 45933
A194: PRIVADO | B194: CE | C194: 3M DO BRASIL LTDA | D194: 509463 | E194: 45917 | F194: 106791.55 | G194: 7891040285389 | H194: HB004558860 | I194: 55501 MANTA AQ PED UNDERB C/10 3M BAIR HUGGER MANTA 55501 | J194: 46862 | K194: 15 | L194: =_xlfn.XLOOKUP(relatorio[[#This Row],[Nome PJ Emitente]],De_Para!A:A,De_Para!C:C) -> 3M | M194: {=IF(LEFT(G194&"",1)="0", IFERROR( VALUE(MID(G194&"",_xlfn.AGGREGATE(15,6,ROW(INDIRECT("1:"&LEN(G194&"")))/(MID(G194&"",ROW(INDIRECT("1:"&LEN(G194&""))),1)<>"0"),1),999)), MID(G194&"",_xlfn.AGGREGATE(15,6,ROW(INDIRECT("1:"&LEN(G194&"")))/(MID(G194&"",ROW(INDIRECT("1:"&LEN(G194&""))),1)<>"0"),1),999) ), IFERROR(VALUE(G194),G194))} -> 7891040285389 | N194: =TEXT(relatorio[[#This Row],[Data Emissão]],"mmm") -> set | O194: =_xlfn.XLOOKUP(relatorio[[#This Row],[Número]],relatorio_Entrada_NF!A:A,relatorio_Entrada_NF!A:A,"Pendente") -> Pendente | P194: =_xlfn.XLOOKUP(relatorio[[#This Row],[Nome PJ Emitente]],Material!A:A,Material!B:B,"Medicamento") -> Material | Q194: =IF(relatorio[[#This Row],[Natureza]]="Medicamento",_xlfn.XLOOKUP(relatorio[[#This Row],[EAN]],CadastroProd!U:U,CadastroProd!A:A," "),_xlfn.XLOOKUP(relatorio[[#This Row],['[Item'] Código]],CadastroProd!X:X,CadastroProd!A:A," ")) -> 2332 | R194: =IF(O194="Pendente",_xlfn.XLOOKUP(relatorio[[#This Row],[Número]],Relatório_CTE!A:A,Relatório_CTE!B:B,"Sem CTE")," ") -> 4791 | S194: =IF(relatorio[[#This Row],[NFs Entrada - Winthor]]="Pendente",_xlfn.XLOOKUP(relatorio[[#This Row],[Número]],Relatório_CTE!A:A,Relatório_CTE!H:H,"Sem CTE")," ") -> 45918 | T194: =(IF(relatorio[[#This Row],[NFs Entrada - Winthor]]="Pendente",IF(relatorio[[#This Row],[Dt. CTE]]="Sem CTE",relatorio[[#This Row],[Data Emissão]]+_xlfn.XLOOKUP(relatorio[[#This Row],[De_Para]],'Lead Time - Histórico (Fornec.)'!B:B,'Lead Time - Histórico (Fornec.)'!C:C),relatorio[[#This Row],[Dt. CTE]]+_xlfn.XLOOKUP(relatorio[[#This Row],[Cód. Winthor]],'Lead Time - Histórico (Produto)'!A:A,'Lead Time - Histórico (Produto)'!C:C))," ")) -> 45933 | U194: =IFERROR(IF(WEEKDAY(relatorio[[#This Row],[Previsão de entrega - Bruto]],2)=6,relatorio[[#This Row],[Previsão de entrega - Bruto]]+2,IF(WEEKDAY(relatorio[[#This Row],[Previsão de entrega - Bruto]],2)=7,relatorio[[#This Row],[Previsão de entrega - Bruto]]+1,relatorio[[#This Row],[Previsão de entrega - Bruto]]))," ") -> 45933
A195: PRIVADO | B195: CE | C195: 3M DO BRASIL LTDA | D195: 509463 | E195: 45917 | F195: 106791.55 | G195: SEM GTIN | H195: HB004559207 | I195: 52500 MANTA AQ MEMBRO INF C/10 3M BAIR HUGGER MANTA 52500 | J195: 46936 | K195: 10 | L195: =_xlfn.XLOOKUP(relatorio[[#This Row],[Nome PJ Emitente]],De_Para!A:A,De_Para!C:C) -> 3M | M195: {=IF(LEFT(G195&"",1)="0", IFERROR( VALUE(MID(G195&"",_xlfn.AGGREGATE(15,6,ROW(INDIRECT("1:"&LEN(G195&"")))/(MID(G195&"",ROW(INDIRECT("1:"&LEN(G195&""))),1)<>"0"),1),999)), MID(G195&"",_xlfn.AGGREGATE(15,6,ROW(INDIRECT("1:"&LEN(G195&"")))/(MID(G195&"",ROW(INDIRECT("1:"&LEN(G195&""))),1)<>"0"),1),999) ), IFERROR(VALUE(G195),G195))} -> SEM GTIN | N195: =TEXT(relatorio[[#This Row],[Data Emissão]],"mmm") -> set | O195: =_xlfn.XLOOKUP(relatorio[[#This Row],[Número]],relatorio_Entrada_NF!A:A,relatorio_Entrada_NF!A:A,"Pendente") -> Pendente | P195: =_xlfn.XLOOKUP(relatorio[[#This Row],[Nome PJ Emitente]],Material!A:A,Material!B:B,"Medicamento") -> Material | Q195: =IF(relatorio[[#This Row],[Natureza]]="Medicamento",_xlfn.XLOOKUP(relatorio[[#This Row],[EAN]],CadastroProd!U:U,CadastroProd!A:A," "),_xlfn.XLOOKUP(relatorio[[#This Row],['[Item'] Código]],CadastroProd!X:X,CadastroProd!A:A," ")) -> 2335 | R195: =IF(O195="Pendente",_xlfn.XLOOKUP(relatorio[[#This Row],[Número]],Relatório_CTE!A:A,Relatório_CTE!B:B,"Sem CTE")," ") -> 4791 | S195: =IF(relatorio[[#This Row],[NFs Entrada - Winthor]]="Pendente",_xlfn.XLOOKUP(relatorio[[#This Row],[Número]],Relatório_CTE!A:A,Relatório_CTE!H:H,"Sem CTE")," ") -> 45918 | T195: =(IF(relatorio[[#This Row],[NFs Entrada - Winthor]]="Pendente",IF(relatorio[[#This Row],[Dt. CTE]]="Sem CTE",relatorio[[#This Row],[Data Emissão]]+_xlfn.XLOOKUP(relatorio[[#This Row],[De_Para]],'Lead Time - Histórico (Fornec.)'!B:B,'Lead Time - Histórico (Fornec.)'!C:C),relatorio[[#This Row],[Dt. CTE]]+_xlfn.XLOOKUP(relatorio[[#This Row],[Cód. Winthor]],'Lead Time - Histórico (Produto)'!A:A,'Lead Time - Histórico (Produto)'!C:C))," ")) -> 45934 | U195: =IFERROR(IF(WEEKDAY(relatorio[[#This Row],[Previsão de entrega - Bruto]],2)=6,relatorio[[#This Row],[Previsão de entrega - Bruto]]+2,IF(WEEKDAY(relatorio[[#This Row],[Previsão de entrega - Bruto]],2)=7,relatorio[[#This Row],[Previsão de entrega - Bruto]]+1,relatorio[[#This Row],[Previsão de entrega - Bruto]]))," ") -> 45936
A196: PRIVADO | B196: CE | C196: 3M DO BRASIL LTDA | D196: 509463 | E196: 45917 | F196: 106791.55 | G196: SEM GTIN | H196: HB004559256 | I196: 63500 MANTA AQ UNDER COMPL C/5 3M BAIR HUGGER MANTA 63500 | J196: 46945 | K196: 92 | L196: =_xlfn.XLOOKUP(relatorio[[#This Row],[Nome PJ Emitente]],De_Para!A:A,De_Para!C:C) -> 3M | M196: {=IF(LEFT(G196&"",1)="0", IFERROR( VALUE(MID(G196&"",_xlfn.AGGREGATE(15,6,ROW(INDIRECT("1:"&LEN(G196&"")))/(MID(G196&"",ROW(INDIRECT("1:"&LEN(G196&""))),1)<>"0"),1),999)), MID(G196&"",_xlfn.AGGREGATE(15,6,ROW(INDIRECT("1:"&LEN(G196&"")))/(MID(G196&"",ROW(INDIRECT("1:"&LEN(G196&""))),1)<>"0"),1),999) ), IFERROR(VALUE(G196),G196))} -> SEM GTIN | N196: =TEXT(relatorio[[#This Row],[Data Emissão]],"mmm") -> set | O196: =_xlfn.XLOOKUP(relatorio[[#This Row],[Número]],relatorio_Entrada_NF!A:A,relatorio_Entrada_NF!A:A,"Pendente") -> Pendente | P196: =_xlfn.XLOOKUP(relatorio[[#This Row],[Nome PJ Emitente]],Material!A:A,Material!B:B,"Medicamento") -> Material | Q196: =IF(relatorio[[#This Row],[Natureza]]="Medicamento",_xlfn.XLOOKUP(relatorio[[#This Row],[EAN]],CadastroProd!U:U,CadastroProd!A:A," "),_xlfn.XLOOKUP(relatorio[[#This Row],['[Item'] Código]],CadastroProd!X:X,CadastroProd!A:A," ")) -> 2337 | R196: =IF(O196="Pendente",_xlfn.XLOOKUP(relatorio[[#This Row],[Número]],Relatório_CTE!A:A,Relatório_CTE!B:B,"Sem CTE")," ") -> 4791 | S196: =IF(relatorio[[#This Row],[NFs Entrada - Winthor]]="Pendente",_xlfn.XLOOKUP(relatorio[[#This Row],[Número]],Relatório_CTE!A:A,Relatório_CTE!H:H,"Sem CTE")," ") -> 45918 | T196: =(IF(relatorio[[#This Row],[NFs Entrada - Winthor]]="Pendente",IF(relatorio[[#This Row],[Dt. CTE]]="Sem CTE",relatorio[[#This Row],[Data Emissão]]+_xlfn.XLOOKUP(relatorio[[#This Row],[De_Para]],'Lead Time - Histórico (Fornec.)'!B:B,'Lead Time - Histórico (Fornec.)'!C:C),relatorio[[#This Row],[Dt. CTE]]+_xlfn.XLOOKUP(relatorio[[#This Row],[Cód. Winthor]],'Lead Time - Histórico (Produto)'!A:A,'Lead Time - Histórico (Produto)'!C:C))," ")) -> 45933 | U196: =IFERROR(IF(WEEKDAY(relatorio[[#This Row],[Previsão de entrega - Bruto]],2)=6,relatorio[[#This Row],[Previsão de entrega - Bruto]]+2,IF(WEEKDAY(relatorio[[#This Row],[Previsão de entrega - Bruto]],2)=7,relatorio[[#This Row],[Previsão de entrega - Bruto]]+1,relatorio[[#This Row],[Previsão de entrega - Bruto]]))," ") -> 45933
A197: PRIVADO | B197: CE | C197: 3M DO BRASIL LTDA | D197: 509464 | E197: 45917 | F197: 6285.6 | G197: 7891040313204 | H197: HB004672265 | I197: COBAN NL 2082 50MMX4.5M 3M COBAN NL 2082 50MMX4.5M | J197: 46910 | K197: 540 | L197: =_xlfn.XLOOKUP(relatorio[[#This Row],[Nome PJ Emitente]],De_Para!A:A,De_Para!C:C) -> 3M | M197: {=IF(LEFT(G197&"",1)="0", IFERROR( VALUE(MID(G197&"",_xlfn.AGGREGATE(15,6,ROW(INDIRECT("1:"&LEN(G197&"")))/(MID(G197&"",ROW(INDIRECT("1:"&LEN(G197&""))),1)<>"0"),1),999)), MID(G197&"",_xlfn.AGGREGATE(15,6,ROW(INDIRECT("1:"&LEN(G197&"")))/(MID(G197&"",ROW(INDIRECT("1:"&LEN(G197&""))),1)<>"0"),1),999) ), IFERROR(VALUE(G197),G197))} -> 7891040313204 | N197: =TEXT(relatorio[[#This Row],[Data Emissão]],"mmm") -> set | O197: =_xlfn.XLOOKUP(relatorio[[#This Row],[Número]],relatorio_Entrada_NF!A:A,relatorio_Entrada_NF!A:A,"Pendente") -> Pendente | P197: =_xlfn.XLOOKUP(relatorio[[#This Row],[Nome PJ Emitente]],Material!A:A,Material!B:B,"Medicamento") -> Material | Q197: =IF(relatorio[[#This Row],[Natureza]]="Medicamento",_xlfn.XLOOKUP(relatorio[[#This Row],[EAN]],CadastroProd!U:U,CadastroProd!A:A," "),_xlfn.XLOOKUP(relatorio[[#This Row],['[Item'] Código]],CadastroProd!X:X,CadastroProd!A:A," ")) -> 2248 | R197: =IF(O197="Pendente",_xlfn.XLOOKUP(relatorio[[#This Row],[Número]],Relatório_CTE!A:A,Relatório_CTE!B:B,"Sem CTE")," ") -> 4791 | S197: =IF(relatorio[[#This Row],[NFs Entrada - Winthor]]="Pendente",_xlfn.XLOOKUP(relatorio[[#This Row],[Número]],Relatório_CTE!A:A,Relatório_CTE!H:H,"Sem CTE")," ") -> 45918 | T197: =(IF(relatorio[[#This Row],[NFs Entrada - Winthor]]="Pendente",IF(relatorio[[#This Row],[Dt. CTE]]="Sem CTE",relatorio[[#This Row],[Data Emissão]]+_xlfn.XLOOKUP(relatorio[[#This Row],[De_Para]],'Lead Time - Histórico (Fornec.)'!B:B,'Lead Time - Histórico (Fornec.)'!C:C),relatorio[[#This Row],[Dt. CTE]]+_xlfn.XLOOKUP(relatorio[[#This Row],[Cód. Winthor]],'Lead Time - Histórico (Produto)'!A:A,'Lead Time - Histórico (Produto)'!C:C))," ")) -> 45933 | U197: =IFERROR(IF(WEEKDAY(relatorio[[#This Row],[Previsão de entrega - Bruto]],2)=6,relatorio[[#This Row],[Previsão de entrega - Bruto]]+2,IF(WEEKDAY(relatorio[[#This Row],[Previsão de entrega - Bruto]],2)=7,relatorio[[#This Row],[Previsão de entrega - Bruto]]+1,relatorio[[#This Row],[Previsão de entrega - Bruto]]))," ") -> 45933
A198: PRIVADO | B198: CE | C198: 3M DO BRASIL LTDA | D198: 509465 | E198: 45917 | F198: 356707.4 | G198: 7891040081356 | H198: H0001819558 | I198: 3591 9CMX25CM CX C/25 CURATIVO TRANSPARENTE TEGADERM | J198: 46879 | K198: 68 | L198: =_xlfn.XLOOKUP(relatorio[[#This Row],[Nome PJ Emitente]],De_Para!A:A,De_Para!C:C) -> 3M | M198: {=IF(LEFT(G198&"",1)="0", IFERROR( VALUE(MID(G198&"",_xlfn.AGGREGATE(15,6,ROW(INDIRECT("1:"&LEN(G198&"")))/(MID(G198&"",ROW(INDIRECT("1:"&LEN(G198&""))),1)<>"0"),1),999)), MID(G198&"",_xlfn.AGGREGATE(15,6,ROW(INDIRECT("1:"&LEN(G198&"")))/(MID(G198&"",ROW(INDIRECT("1:"&LEN(G198&""))),1)<>"0"),1),999) ), IFERROR(VALUE(G198),G198))} -> 7891040081356 | N198: =TEXT(relatorio[[#This Row],[Data Emissão]],"mmm") -> set | O198: =_xlfn.XLOOKUP(relatorio[[#This Row],[Número]],relatorio_Entrada_NF!A:A,relatorio_Entrada_NF!A:A,"Pendente") -> Pendente | P198: =_xlfn.XLOOKUP(relatorio[[#This Row],[Nome PJ Emitente]],Material!A:A,Material!B:B,"Medicamento") -> Material | Q198: =IF(relatorio[[#This Row],[Natureza]]="Medicamento",_xlfn.XLOOKUP(relatorio[[#This Row],[EAN]],CadastroProd!U:U,CadastroProd!A:A," "),_xlfn.XLOOKUP(relatorio[[#This Row],['[Item'] Código]],CadastroProd!X:X,CadastroProd!A:A," ")) -> 2213 | R198: =IF(O198="Pendente",_xlfn.XLOOKUP(relatorio[[#This Row],[Número]],Relatório_CTE!A:A,Relatório_CTE!B:B,"Sem CTE")," ") -> 4791 | S198: =IF(relatorio[[#This Row],[NFs Entrada - Winthor]]="Pendente",_xlfn.XLOOKUP(relatorio[[#This Row],[Número]],Relatório_CTE!A:A,Relatório_CTE!H:H,"Sem CTE")," ") -> 45918 | T198: =(IF(relatorio[[#This Row],[NFs Entrada - Winthor]]="Pendente",IF(relatorio[[#This Row],[Dt. CTE]]="Sem CTE",relatorio[[#This Row],[Data Emissão]]+_xlfn.XLOOKUP(relatorio[[#This Row],[De_Para]],'Lead Time - Histórico (Fornec.)'!B:B,'Lead Time - Histórico (Fornec.)'!C:C),relatorio[[#This Row],[Dt. CTE]]+_xlfn.XLOOKUP(relatorio[[#This Row],[Cód. Winthor]],'Lead Time - Histórico (Produto)'!A:A,'Lead Time - Histórico (Produto)'!C:C))," ")) -> 45933 | U198: =IFERROR(IF(WEEKDAY(relatorio[[#This Row],[Previsão de entrega - Bruto]],2)=6,relatorio[[#This Row],[Previsão de entrega - Bruto]]+2,IF(WEEKDAY(relatorio[[#This Row],[Previsão de entrega - Bruto]],2)=7,relatorio[[#This Row],[Previsão de entrega - Bruto]]+1,relatorio[[#This Row],[Previsão de entrega - Bruto]]))," ") -> 45933
A199: PRIVADO | B199: CE | C199: 3M DO BRASIL LTDA | D199: 509465 | E199: 45917 | F199: 356707.4 | G199: 7891040146468 | H199: HB004095228 | I199: 2223 BRQ ELETRODO P/ MONITORIZ ELETRODO P/ MONITORIZ 2223 BRQ | J199: 46570 | K199: 23040 | L199: =_xlfn.XLOOKUP(relatorio[[#This Row],[Nome PJ Emitente]],De_Para!A:A,De_Para!C:C) -> 3M | M199: {=IF(LEFT(G199&"",1)="0", IFERROR( VALUE(MID(G199&"",_xlfn.AGGREGATE(15,6,ROW(INDIRECT("1:"&LEN(G199&"")))/(MID(G199&"",ROW(INDIRECT("1:"&LEN(G199&""))),1)<>"0"),1),999)), MID(G199&"",_xlfn.AGGREGATE(15,6,ROW(INDIRECT("1:"&LEN(G199&"")))/(MID(G199&"",ROW(INDIRECT("1:"&LEN(G199&""))),1)<>"0"),1),999) ), IFERROR(VALUE(G199),G199))} -> 7891040146468 | N199: =TEXT(relatorio[[#This Row],[Data Emissão]],"mmm") -> set | O199: =_xlfn.XLOOKUP(relatorio[[#This Row],[Número]],relatorio_Entrada_NF!A:A,relatorio_Entrada_NF!A:A,"Pendente") -> Pendente | P199: =_xlfn.XLOOKUP(relatorio[[#This Row],[Nome PJ Emitente]],Material!A:A,Material!B:B,"Medicamento") -> Material | Q199: =IF(relatorio[[#This Row],[Natureza]]="Medicamento",_xlfn.XLOOKUP(relatorio[[#This Row],[EAN]],CadastroProd!U:U,CadastroProd!A:A," "),_xlfn.XLOOKUP(relatorio[[#This Row],['[Item'] Código]],CadastroProd!X:X,CadastroProd!A:A," ")) -> 2373 | R199: =IF(O199="Pendente",_xlfn.XLOOKUP(relatorio[[#This Row],[Número]],Relatório_CTE!A:A,Relatório_CTE!B:B,"Sem CTE")," ") -> 4791 | S199: =IF(relatorio[[#This Row],[NFs Entrada - Winthor]]="Pendente",_xlfn.XLOOKUP(relatorio[[#This Row],[Número]],Relatório_CTE!A:A,Relatório_CTE!H:H,"Sem CTE")," ") -> 45918 | T199: =(IF(relatorio[[#This Row],[NFs Entrada - Winthor]]="Pendente",IF(relatorio[[#This Row],[Dt. CTE]]="Sem CTE",relatorio[[#This Row],[Data Emissão]]+_xlfn.XLOOKUP(relatorio[[#This Row],[De_Para]],'Lead Time - Histórico (Fornec.)'!B:B,'Lead Time - Histórico (Fornec.)'!C:C),relatorio[[#This Row],[Dt. CTE]]+_xlfn.XLOOKUP(relatorio[[#This Row],[Cód. Winthor]],'Lead Time - Histórico (Produto)'!A:A,'Lead Time - Histórico (Produto)'!C:C))," ")) -> 45934 | U199: =IFERROR(IF(WEEKDAY(relatorio[[#This Row],[Previsão de entrega - Bruto]],2)=6,relatorio[[#This Row],[Previsão de entrega - Bruto]]+2,IF(WEEKDAY(relatorio[[#This Row],[Previsão de entrega - Bruto]],2)=7,relatorio[[#This Row],[Previsão de entrega - Bruto]]+1,relatorio[[#This Row],[Previsão de entrega - Bruto]]))," ") -> 45936
A200: PRIVADO | B200: CE | C200: 3M DO BRASIL LTDA | D200: 509465 | E200: 45917 | F200: 356707.4 | G200: SEM GTIN | H200: HB004253447 | I200: 2258 BR-N NEONAT SC C/ 50 UN 2258 BR-N NEONAT SC C/ 50 UN | J200: 46593 | K200: 20 | L200: =_xlfn.XLOOKUP(relatorio[[#This Row],[Nome PJ Emitente]],De_Para!A:A,De_Para!C:C) -> 3M | M200: {=IF(LEFT(G200&"",1)="0", IFERROR( VALUE(MID(G200&"",_xlfn.AGGREGATE(15,6,ROW(INDIRECT("1:"&LEN(G200&"")))/(MID(G200&"",ROW(INDIRECT("1:"&LEN(G200&""))),1)<>"0"),1),999)), MID(G200&"",_xlfn.AGGREGATE(15,6,ROW(INDIRECT("1:"&LEN(G200&"")))/(MID(G200&"",ROW(INDIRECT("1:"&LEN(G200&""))),1)<>"0"),1),999) ), IFERROR(VALUE(G200),G200))} -> SEM GTIN | N200: =TEXT(relatorio[[#This Row],[Data Emissão]],"mmm") -> set | O200: =_xlfn.XLOOKUP(relatorio[[#This Row],[Número]],relatorio_Entrada_NF!A:A,relatorio_Entrada_NF!A:A,"Pendente") -> Pendente | P200: =_xlfn.XLOOKUP(relatorio[[#This Row],[Nome PJ Emitente]],Material!A:A,Material!B:B,"Medicamento") -> Material | Q200: =IF(relatorio[[#This Row],[Natureza]]="Medicamento",_xlfn.XLOOKUP(relatorio[[#This Row],[EAN]],CadastroProd!U:U,CadastroProd!A:A," "),_xlfn.XLOOKUP(relatorio[[#This Row],['[Item'] Código]],CadastroProd!X:X,CadastroProd!A:A," ")) -> 2371 | R200: =IF(O200="Pendente",_xlfn.XLOOKUP(relatorio[[#This Row],[Número]],Relatório_CTE!A:A,Relatório_CTE!B:B,"Sem CTE")," ") -> 4791 | S200: =IF(relatorio[[#This Row],[NFs Entrada - Winthor]]="Pendente",_xlfn.XLOOKUP(relatorio[[#This Row],[Número]],Relatório_CTE!A:A,Relatório_CTE!H:H,"Sem CTE")," ") -> 45918 | T200: =(IF(relatorio[[#This Row],[NFs Entrada - Winthor]]="Pendente",IF(relatorio[[#This Row],[Dt. CTE]]="Sem CTE",relatorio[[#This Row],[Data Emissão]]+_xlfn.XLOOKUP(relatorio[[#This Row],[De_Para]],'Lead Time - Histórico (Fornec.)'!B:B,'Lead Time - Histórico (Fornec.)'!C:C),relatorio[[#This Row],[Dt. CTE]]+_xlfn.XLOOKUP(relatorio[[#This Row],[Cód. Winthor]],'Lead Time - Histórico (Produto)'!A:A,'Lead Time - Histórico (Produto)'!C:C))," ")) -> 45918 | U200: =IFERROR(IF(WEEKDAY(relatorio[[#This Row],[Previsão de entrega - Bruto]],2)=6,relatorio[[#This Row],[Previsão de entrega - Bruto]]+2,IF(WEEKDAY(relatorio[[#This Row],[Previsão de entrega - Bruto]],2)=7,relatorio[[#This Row],[Previsão de entrega - Bruto]]+1,relatorio[[#This Row],[Previsão de entrega - Bruto]]))," ") -> 45918
A201: PRIVADO | B201: CE | C201: 3M DO BRASIL LTDA | D201: 509465 | E201: 45917 | F201: 356707.4 | G201: 7891040241293 | H201: HB004512594 | I201: CAVILON CREME BARREIRA GBR 92G CAVILON CREME BARREIRA 3392GBR | J201: 46431 | K201: 1128 | L201: =_xlfn.XLOOKUP(relatorio[[#This Row],[Nome PJ Emitente]],De_Para!A:A,De_Para!C:C) -> 3M | M201: {=IF(LEFT(G201&"",1)="0", IFERROR( VALUE(MID(G201&"",_xlfn.AGGREGATE(15,6,ROW(INDIRECT("1:"&LEN(G201&"")))/(MID(G201&"",ROW(INDIRECT("1:"&LEN(G201&""))),1)<>"0"),1),999)), MID(G201&"",_xlfn.AGGREGATE(15,6,ROW(INDIRECT("1:"&LEN(G201&"")))/(MID(G201&"",ROW(INDIRECT("1:"&LEN(G201&""))),1)<>"0"),1),999) ), IFERROR(VALUE(G201),G201))} -> 7891040241293 | N201: =TEXT(relatorio[[#This Row],[Data Emissão]],"mmm") -> set | O201: =_xlfn.XLOOKUP(relatorio[[#This Row],[Número]],relatorio_Entrada_NF!A:A,relatorio_Entrada_NF!A:A,"Pendente") -> Pendente | P201: =_xlfn.XLOOKUP(relatorio[[#This Row],[Nome PJ Emitente]],Material!A:A,Material!B:B,"Medicamento") -> Material | Q201: =IF(relatorio[[#This Row],[Natureza]]="Medicamento",_xlfn.XLOOKUP(relatorio[[#This Row],[EAN]],CadastroProd!U:U,CadastroProd!A:A," "),_xlfn.XLOOKUP(relatorio[[#This Row],['[Item'] Código]],CadastroProd!X:X,CadastroProd!A:A," ")) -> 2240 | R201: =IF(O201="Pendente",_xlfn.XLOOKUP(relatorio[[#This Row],[Número]],Relatório_CTE!A:A,Relatório_CTE!B:B,"Sem CTE")," ") -> 4791 | S201: =IF(relatorio[[#This Row],[NFs Entrada - Winthor]]="Pendente",_xlfn.XLOOKUP(relatorio[[#This Row],[Número]],Relatório_CTE!A:A,Relatório_CTE!H:H,"Sem CTE")," ") -> 45918 | T201: =(IF(relatorio[[#This Row],[NFs Entrada - Winthor]]="Pendente",IF(relatorio[[#This Row],[Dt. CTE]]="Sem CTE",relatorio[[#This Row],[Data Emissão]]+_xlfn.XLOOKUP(relatorio[[#This Row],[De_Para]],'Lead Time - Histórico (Fornec.)'!B:B,'Lead Time - Histórico (Fornec.)'!C:C),relatorio[[#This Row],[Dt. CTE]]+_xlfn.XLOOKUP(relatorio[[#This Row],[Cód. Winthor]],'Lead Time - Histórico (Produto)'!A:A,'Lead Time - Histórico (Produto)'!C:C))," ")) -> 45935 | U201: =IFERROR(IF(WEEKDAY(relatorio[[#This Row],[Previsão de entrega - Bruto]],2)=6,relatorio[[#This Row],[Previsão de entrega - Bruto]]+2,IF(WEEKDAY(relatorio[[#This Row],[Previsão de entrega - Bruto]],2)=7,relatorio[[#This Row],[Previsão de entrega - Bruto]]+1,relatorio[[#This Row],[Previsão de entrega - Bruto]]))," ") -> 45936
A202: PRIVADO | B202: CE | C202: 3M DO BRASIL LTDA | D202: 509465 | E202: 45917 | F202: 356707.4 | G202: SEM GTIN | H202: HB004559264 | I202: 3M FIXADOR TUBOS SONDAS NASAL 3M FIXADOR TUBOS SONDAS NASAL | J202: 46584 | K202: 16 | L202: =_xlfn.XLOOKUP(relatorio[[#This Row],[Nome PJ Emitente]],De_Para!A:A,De_Para!C:C) -> 3M | M202: {=IF(LEFT(G202&"",1)="0", IFERROR( VALUE(MID(G202&"",_xlfn.AGGREGATE(15,6,ROW(INDIRECT("1:"&LEN(G202&"")))/(MID(G202&"",ROW(INDIRECT("1:"&LEN(G202&""))),1)<>"0"),1),999)), MID(G202&"",_xlfn.AGGREGATE(15,6,ROW(INDIRECT("1:"&LEN(G202&"")))/(MID(G202&"",ROW(INDIRECT("1:"&LEN(G202&""))),1)<>"0"),1),999) ), IFERROR(VALUE(G202),G202))} -> SEM GTIN | N202: =TEXT(relatorio[[#This Row],[Data Emissão]],"mmm") -> set | O202: =_xlfn.XLOOKUP(relatorio[[#This Row],[Número]],relatorio_Entrada_NF!A:A,relatorio_Entrada_NF!A:A,"Pendente") -> Pendente | P202: =_xlfn.XLOOKUP(relatorio[[#This Row],[Nome PJ Emitente]],Material!A:A,Material!B:B,"Medicamento") -> Material | Q202: =IF(relatorio[[#This Row],[Natureza]]="Medicamento",_xlfn.XLOOKUP(relatorio[[#This Row],[EAN]],CadastroProd!U:U,CadastroProd!A:A," "),_xlfn.XLOOKUP(relatorio[[#This Row],['[Item'] Código]],CadastroProd!X:X,CadastroProd!A:A," ")) -> 2209 | R202: =IF(O202="Pendente",_xlfn.XLOOKUP(relatorio[[#This Row],[Número]],Relatório_CTE!A:A,Relatório_CTE!B:B,"Sem CTE")," ") -> 4791 | S202: =IF(relatorio[[#This Row],[NFs Entrada - Winthor]]="Pendente",_xlfn.XLOOKUP(relatorio[[#This Row],[Número]],Relatório_CTE!A:A,Relatório_CTE!H:H,"Sem CTE")," ") -> 45918 | T202: =(IF(relatorio[[#This Row],[NFs Entrada - Winthor]]="Pendente",IF(relatorio[[#This Row],[Dt. CTE]]="Sem CTE",relatorio[[#This Row],[Data Emissão]]+_xlfn.XLOOKUP(relatorio[[#This Row],[De_Para]],'Lead Time - Histórico (Fornec.)'!B:B,'Lead Time - Histórico (Fornec.)'!C:C),relatorio[[#This Row],[Dt. CTE]]+_xlfn.XLOOKUP(relatorio[[#This Row],[Cód. Winthor]],'Lead Time - Histórico (Produto)'!A:A,'Lead Time - Histórico (Produto)'!C:C))," ")) -> 45935 | U202: =IFERROR(IF(WEEKDAY(relatorio[[#This Row],[Previsão de entrega - Bruto]],2)=6,relatorio[[#This Row],[Previsão de entrega - Bruto]]+2,IF(WEEKDAY(relatorio[[#This Row],[Previsão de entrega - Bruto]],2)=7,relatorio[[#This Row],[Previsão de entrega - Bruto]]+1,relatorio[[#This Row],[Previsão de entrega - Bruto]]))," ") -> 45936
A203: PRIVADO | B203: CE | C203: 3M DO BRASIL LTDA | D203: 509465 | E203: 45917 | F203: 356707.4 | G203: SEM GTIN | H203: HB004764104 | I203: 1530 12.5MMX10M CARRETEL 1530 12.5MMX10M CARRETEL | J203: 46551 | K203: 120 | L203: =_xlfn.XLOOKUP(relatorio[[#This Row],[Nome PJ Emitente]],De_Para!A:A,De_Para!C:C) -> 3M | M203: {=IF(LEFT(G203&"",1)="0", IFERROR( VALUE(MID(G203&"",_xlfn.AGGREGATE(15,6,ROW(INDIRECT("1:"&LEN(G203&"")))/(MID(G203&"",ROW(INDIRECT("1:"&LEN(G203&""))),1)<>"0"),1),999)), MID(G203&"",_xlfn.AGGREGATE(15,6,ROW(INDIRECT("1:"&LEN(G203&"")))/(MID(G203&"",ROW(INDIRECT("1:"&LEN(G203&""))),1)<>"0"),1),999) ), IFERROR(VALUE(G203),G203))} -> SEM GTIN | N203: =TEXT(relatorio[[#This Row],[Data Emissão]],"mmm") -> set | O203: =_xlfn.XLOOKUP(relatorio[[#This Row],[Número]],relatorio_Entrada_NF!A:A,relatorio_Entrada_NF!A:A,"Pendente") -> Pendente | P203: =_xlfn.XLOOKUP(relatorio[[#This Row],[Nome PJ Emitente]],Material!A:A,Material!B:B,"Medicamento") -> Material | Q203: =IF(relatorio[[#This Row],[Natureza]]="Medicamento",_xlfn.XLOOKUP(relatorio[[#This Row],[EAN]],CadastroProd!U:U,CadastroProd!A:A," "),_xlfn.XLOOKUP(relatorio[[#This Row],['[Item'] Código]],CadastroProd!X:X,CadastroProd!A:A," ")) -> 2173 | R203: =IF(O203="Pendente",_xlfn.XLOOKUP(relatorio[[#This Row],[Número]],Relatório_CTE!A:A,Relatório_CTE!B:B,"Sem CTE")," ") -> 4791 | S203: =IF(relatorio[[#This Row],[NFs Entrada - Winthor]]="Pendente",_xlfn.XLOOKUP(relatorio[[#This Row],[Número]],Relatório_CTE!A:A,Relatório_CTE!H:H,"Sem CTE")," ") -> 45918 | T203: =(IF(relatorio[[#This Row],[NFs Entrada - Winthor]]="Pendente",IF(relatorio[[#This Row],[Dt. CTE]]="Sem CTE",relatorio[[#This Row],[Data Emissão]]+_xlfn.XLOOKUP(relatorio[[#This Row],[De_Para]],'Lead Time - Histórico (Fornec.)'!B:B,'Lead Time - Histórico (Fornec.)'!C:C),relatorio[[#This Row],[Dt. CTE]]+_xlfn.XLOOKUP(relatorio[[#This Row],[Cód. Winthor]],'Lead Time - Histórico (Produto)'!A:A,'Lead Time - Histórico (Produto)'!C:C))," ")) -> 45930 | U203: =IFERROR(IF(WEEKDAY(relatorio[[#This Row],[Previsão de entrega - Bruto]],2)=6,relatorio[[#This Row],[Previsão de entrega - Bruto]]+2,IF(WEEKDAY(relatorio[[#This Row],[Previsão de entrega - Bruto]],2)=7,relatorio[[#This Row],[Previsão de entrega - Bruto]]+1,relatorio[[#This Row],[Previsão de entrega - Bruto]]))," ") -> 45930
A204: PRIVADO | B204: CE | C204: 3M DO BRASIL LTDA | D204: 509465 | E204: 45917 | F204: 356707.4 | G204: SEM GTIN | H204: HB004764112 | I204: 1533 12.5MMX10M CARRETEL (RL) 1533 12.5MMX10M CARRETEL (RL) | J204: 46557 | K204: 120 | L204: =_xlfn.XLOOKUP(relatorio[[#This Row],[Nome PJ Emitente]],De_Para!A:A,De_Para!C:C) -> 3M | M204: {=IF(LEFT(G204&"",1)="0", IFERROR( VALUE(MID(G204&"",_xlfn.AGGREGATE(15,6,ROW(INDIRECT("1:"&LEN(G204&"")))/(MID(G204&"",ROW(INDIRECT("1:"&LEN(G204&""))),1)<>"0"),1),999)), MID(G204&"",_xlfn.AGGREGATE(15,6,ROW(INDIRECT("1:"&LEN(G204&"")))/(MID(G204&"",ROW(INDIRECT("1:"&LEN(G204&""))),1)<>"0"),1),999) ), IFERROR(VALUE(G204),G204))} -> SEM GTIN | N204: =TEXT(relatorio[[#This Row],[Data Emissão]],"mmm") -> set | O204: =_xlfn.XLOOKUP(relatorio[[#This Row],[Número]],relatorio_Entrada_NF!A:A,relatorio_Entrada_NF!A:A,"Pendente") -> Pendente | P204: =_xlfn.XLOOKUP(relatorio[[#This Row],[Nome PJ Emitente]],Material!A:A,Material!B:B,"Medicamento") -> Material | Q204: =IF(relatorio[[#This Row],[Natureza]]="Medicamento",_xlfn.XLOOKUP(relatorio[[#This Row],[EAN]],CadastroProd!U:U,CadastroProd!A:A," "),_xlfn.XLOOKUP(relatorio[[#This Row],['[Item'] Código]],CadastroProd!X:X,CadastroProd!A:A," ")) -> 2177 | R204: =IF(O204="Pendente",_xlfn.XLOOKUP(relatorio[[#This Row],[Número]],Relatório_CTE!A:A,Relatório_CTE!B:B,"Sem CTE")," ") -> 4791 | S204: =IF(relatorio[[#This Row],[NFs Entrada - Winthor]]="Pendente",_xlfn.XLOOKUP(relatorio[[#This Row],[Número]],Relatório_CTE!A:A,Relatório_CTE!H:H,"Sem CTE")," ") -> 45918 | T204: =(IF(relatorio[[#This Row],[NFs Entrada - Winthor]]="Pendente",IF(relatorio[[#This Row],[Dt. CTE]]="Sem CTE",relatorio[[#This Row],[Data Emissão]]+_xlfn.XLOOKUP(relatorio[[#This Row],[De_Para]],'Lead Time - Histórico (Fornec.)'!B:B,'Lead Time - Histórico (Fornec.)'!C:C),relatorio[[#This Row],[Dt. CTE]]+_xlfn.XLOOKUP(relatorio[[#This Row],[Cód. Winthor]],'Lead Time - Histórico (Produto)'!A:A,'Lead Time - Histórico (Produto)'!C:C))," ")) -> #N/A | U204: =IFERROR(IF(WEEKDAY(relatorio[[#This Row],[Previsão de entrega - Bruto]],2)=6,relatorio[[#This Row],[Previsão de entrega - Bruto]]+2,IF(WEEKDAY(relatorio[[#This Row],[Previsão de entrega - Bruto]],2)=7,relatorio[[#This Row],[Previsão de entrega - Bruto]]+1,relatorio[[#This Row],[Previsão de entrega - Bruto]]))," ")
... A236: PRIVADO | B236: CE | C236: 3M DO BRASIL LTDA | D236: 509471 | E236: 45917 | F236: 11656.73 | G236: 7891040081356 | H236: H0001819558 | I236: 3591 9CMX25CM CX C/25 CURATIVO TRANSPARENTE TEGADERM | J236: 46879 | K236: 4 | L236: =_xlfn.XLOOKUP(relatorio[[#This Row],[Nome PJ Emitente]],De_Para!A:A,De_Para!C:C) -> 3M | M236: {=IF(LEFT(G236&"",1)="0", IFERROR( VALUE(MID(G236&"",_xlfn.AGGREGATE(15,6,ROW(INDIRECT("1:"&LEN(G236&"")))/(MID(G236&"",ROW(INDIRECT("1:"&LEN(G236&""))),1)<>"0"),1),999)), MID(G236&"",_xlfn.AGGREGATE(15,6,ROW(INDIRECT("1:"&LEN(G236&"")))/(MID(G236&"",ROW(INDIRECT("1:"&LEN(G236&""))),1)<>"0"),1),999) ), IFERROR(VALUE(G236),G236))} -> 7891040081356 | N236: =TEXT(relatorio[[#This Row],[Data Emissão]],"mmm") -> set | O236: =_xlfn.XLOOKUP(relatorio[[#This Row],[Número]],relatorio_Entrada_NF!A:A,relatorio_Entrada_NF!A:A,"Pendente") -> Pendente | P236: =_xlfn.XLOOKUP(relatorio[[#This Row],[Nome PJ Emitente]],Material!A:A,Material!B:B,"Medicamento") -> Material | Q236: =IF(relatorio[[#This Row],[Natureza]]="Medicamento",_xlfn.XLOOKUP(relatorio[[#This Row],[EAN]],CadastroProd!U:U,CadastroProd!A:A," "),_xlfn.XLOOKUP(relatorio[[#This Row],['[Item'] Código]],CadastroProd!X:X,CadastroProd!A:A," ")) -> 2213 | R236: =IF(O236="Pendente",_xlfn.XLOOKUP(relatorio[[#This Row],[Número]],Relatório_CTE!A:A,Relatório_CTE!B:B,"Sem CTE")," ") -> 4791 | S236: =IF(relatorio[[#This Row],[NFs Entrada - Winthor]]="Pendente",_xlfn.XLOOKUP(relatorio[[#This Row],[Número]],Relatório_CTE!A:A,Relatório_CTE!H:H,"Sem CTE")," ") -> 45918 | T236: =(IF(relatorio[[#This Row],[NFs Entrada - Winthor]]="Pendente",IF(relatorio[[#This Row],[Dt. CTE]]="Sem CTE",relatorio[[#This Row],[Data Emissão]]+_xlfn.XLOOKUP(relatorio[[#This Row],[De_Para]],'Lead Time - Histórico (Fornec.)'!B:B,'Lead Time - Histórico (Fornec.)'!C:C),relatorio[[#This Row],[Dt. CTE]]+_xlfn.XLOOKUP(relatorio[[#This Row],[Cód. Winthor]],'Lead Time - Histórico (Produto)'!A:A,'Lead Time - Histórico (Produto)'!C:C))," ")) -> 45933 | U236: =IFERROR(IF(WEEKDAY(relatorio[[#This Row],[Previsão de entrega - Bruto]],2)=6,relatorio[[#This Row],[Previsão de entrega - Bruto]]+2,IF(WEEKDAY(relatorio[[#This Row],[Previsão de entrega - Bruto]],2)=7,relatorio[[#This Row],[Previsão de entrega - Bruto]]+1,relatorio[[#This Row],[Previsão de entrega - Bruto]]))," ") -> 45933
A237: PRIVADO | B237: CE | C237: 3M DO BRASIL LTDA | D237: 509471 | E237: 45917 | F237: 11656.73 | G237: 7891040146468 | H237: HB004095228 | I237: 2223 BRQ ELETRODO P/ MONITORIZ ELETRODO P/ MONITORIZ 2223 BRQ | K237: 20 | L237: =_xlfn.XLOOKUP(relatorio[[#This Row],[Nome PJ Emitente]],De_Para!A:A,De_Para!C:C) -> 3M | M237: {=IF(LEFT(G237&"",1)="0", IFERROR( VALUE(MID(G237&"",_xlfn.AGGREGATE(15,6,ROW(INDIRECT("1:"&LEN(G237&"")))/(MID(G237&"",ROW(INDIRECT("1:"&LEN(G237&""))),1)<>"0"),1),999)), MID(G237&"",_xlfn.AGGREGATE(15,6,ROW(INDIRECT("1:"&LEN(G237&"")))/(MID(G237&"",ROW(INDIRECT("1:"&LEN(G237&""))),1)<>"0"),1),999) ), IFERROR(VALUE(G237),G237))} -> 7891040146468 | N237: =TEXT(relatorio[[#This Row],[Data Emissão]],"mmm") -> set | O237: =_xlfn.XLOOKUP(relatorio[[#This Row],[Número]],relatorio_Entrada_NF!A:A,relatorio_Entrada_NF!A:A,"Pendente") -> Pendente | P237: =_xlfn.XLOOKUP(relatorio[[#This Row],[Nome PJ Emitente]],Material!A:A,Material!B:B,"Medicamento") -> Material | Q237: =IF(relatorio[[#This Row],[Natureza]]="Medicamento",_xlfn.XLOOKUP(relatorio[[#This Row],[EAN]],CadastroProd!U:U,CadastroProd!A:A," "),_xlfn.XLOOKUP(relatorio[[#This Row],['[Item'] Código]],CadastroProd!X:X,CadastroProd!A:A," ")) -> 2373 | R237: =IF(O237="Pendente",_xlfn.XLOOKUP(relatorio[[#This Row],[Número]],Relatório_CTE!A:A,Relatório_CTE!B:B,"Sem CTE")," ") -> 4791 | S237: =IF(relatorio[[#This Row],[NFs Entrada - Winthor]]="Pendente",_xlfn.XLOOKUP(relatorio[[#This Row],[Número]],Relatório_CTE!A:A,Relatório_CTE!H:H,"Sem CTE")," ") -> 45918 | T237: =(IF(relatorio[[#This Row],[NFs Entrada - Winthor]]="Pendente",IF(relatorio[[#This Row],[Dt. CTE]]="Sem CTE",relatorio[[#This Row],[Data Emissão]]+_xlfn.XLOOKUP(relatorio[[#This Row],[De_Para]],'Lead Time - Histórico (Fornec.)'!B:B,'Lead Time - Histórico (Fornec.)'!C:C),relatorio[[#This Row],[Dt. CTE]]+_xlfn.XLOOKUP(relatorio[[#This Row],[Cód. Winthor]],'Lead Time - Histórico (Produto)'!A:A,'Lead Time - Histórico (Produto)'!C:C))," ")) -> 45934 | U237: =IFERROR(IF(WEEKDAY(relatorio[[#This Row],[Previsão de entrega - Bruto]],2)=6,relatorio[[#This Row],[Previsão de entrega - Bruto]]+2,IF(WEEKDAY(relatorio[[#This Row],[Previsão de entrega - Bruto]],2)=7,relatorio[[#This Row],[Previsão de entrega - Bruto]]+1,relatorio[[#This Row],[Previsão de entrega - Bruto]]))," ") -> 45936
A238: PRIVADO | B238: CE | C238: 3M DO BRASIL LTDA | D238: 509471 | E238: 45917 | F238: 11656.73 | G238: 7891040241293 | H238: HB004512594 | I238: CAVILON CREME BARREIRA GBR 92G CAVILON CREME BARREIRA 3392GBR | J238: 46431 | K238: 12 | L238: =_xlfn.XLOOKUP(relatorio[[#This Row],[Nome PJ Emitente]],De_Para!A:A,De_Para!C:C) -> 3M | M238: {=IF(LEFT(G238&"",1)="0", IFERROR( VALUE(MID(G238&"",_xlfn.AGGREGATE(15,6,ROW(INDIRECT("1:"&LEN(G238&"")))/(MID(G238&"",ROW(INDIRECT("1:"&LEN(G238&""))),1)<>"0"),1),999)), MID(G238&"",_xlfn.AGGREGATE(15,6,ROW(INDIRECT("1:"&LEN(G238&"")))/(MID(G238&"",ROW(INDIRECT("1:"&LEN(G238&""))),1)<>"0"),1),999) ), IFERROR(VALUE(G238),G238))} -> 7891040241293 | N238: =TEXT(relatorio[[#This Row],[Data Emissão]],"mmm") -> set | O238: =_xlfn.XLOOKUP(relatorio[[#This Row],[Número]],relatorio_Entrada_NF!A:A,relatorio_Entrada_NF!A:A,"Pendente") -> Pendente | P238: =_xlfn.XLOOKUP(relatorio[[#This Row],[Nome PJ Emitente]],Material!A:A,Material!B:B,"Medicamento") -> Material | Q238: =IF(relatorio[[#This Row],[Natureza]]="Medicamento",_xlfn.XLOOKUP(relatorio[[#This Row],[EAN]],CadastroProd!U:U,CadastroProd!A:A," "),_xlfn.XLOOKUP(relatorio[[#This Row],['[Item'] Código]],CadastroProd!X:X,CadastroProd!A:A," ")) -> 2240 | R238: =IF(O238="Pendente",_xlfn.XLOOKUP(relatorio[[#This Row],[Número]],Relatório_CTE!A:A,Relatório_CTE!B:B,"Sem CTE")," ") -> 4791 | S238: =IF(relatorio[[#This Row],[NFs Entrada - Winthor]]="Pendente",_xlfn.XLOOKUP(relatorio[[#This Row],[Número]],Relatório_CTE!A:A,Relatório_CTE!H:H,"Sem CTE")," ") -> 45918 | T238: =(IF(relatorio[[#This Row],[NFs Entrada - Winthor]]="Pendente",IF(relatorio[[#This Row],[Dt. CTE]]="Sem CTE",relatorio[[#This Row],[Data Emissão]]+_xlfn.XLOOKUP(relatorio[[#This Row],[De_Para]],'Lead Time - Histórico (Fornec.)'!B:B,'Lead Time - Histórico (Fornec.)'!C:C),relatorio[[#This Row],[Dt. CTE]]+_xlfn.XLOOKUP(relatorio[[#This Row],[Cód. Winthor]],'Lead Time - Histórico (Produto)'!A:A,'Lead Time - Histórico (Produto)'!C:C))," ")) -> 45935 | U238: =IFERROR(IF(WEEKDAY(relatorio[[#This Row],[Previsão de entrega - Bruto]],2)=6,relatorio[[#This Row],[Previsão de entrega - Bruto]]+2,IF(WEEKDAY(relatorio[[#This Row],[Previsão de entrega - Bruto]],2)=7,relatorio[[#This Row],[Previsão de entrega - Bruto]]+1,relatorio[[#This Row],[Previsão de entrega - Bruto]]))," ") -> 45936
A239: PRIVADO | B239: CE | C239: 3M DO BRASIL LTDA | D239: 509471 | E239: 45917 | F239: 11656.73 | G239: 0707387808358 | H239: HB004805477 | I239: 1685 IV ADV 8.5CMX11.5CM CX 50 3M TEGADERM IV ADVANCED | J239: 46897 | K239: 4 | L239: =_xlfn.XLOOKUP(relatorio[[#This Row],[Nome PJ Emitente]],De_Para!A:A,De_Para!C:C) -> 3M | M239: {=IF(LEFT(G239&"",1)="0", IFERROR( VALUE(MID(G239&"",_xlfn.AGGREGATE(15,6,ROW(INDIRECT("1:"&LEN(G239&"")))/(MID(G239&"",ROW(INDIRECT("1:"&LEN(G239&""))),1)<>"0"),1),999)), MID(G239&"",_xlfn.AGGREGATE(15,6,ROW(INDIRECT("1:"&LEN(G239&"")))/(MID(G239&"",ROW(INDIRECT("1:"&LEN(G239&""))),1)<>"0"),1),999) ), IFERROR(VALUE(G239),G239))} -> 707387808358 | N239: =TEXT(relatorio[[#This Row],[Data Emissão]],"mmm") -> set | O239: =_xlfn.XLOOKUP(relatorio[[#This Row],[Número]],relatorio_Entrada_NF!A:A,relatorio_Entrada_NF!A:A,"Pendente") -> Pendente | P239: =_xlfn.XLOOKUP(relatorio[[#This Row],[Nome PJ Emitente]],Material!A:A,Material!B:B,"Medicamento") -> Material | Q239: =IF(relatorio[[#This Row],[Natureza]]="Medicamento",_xlfn.XLOOKUP(relatorio[[#This Row],[EAN]],CadastroProd!U:U,CadastroProd!A:A," "),_xlfn.XLOOKUP(relatorio[[#This Row],['[Item'] Código]],CadastroProd!X:X,CadastroProd!A:A," ")) -> 3561 | R239: =IF(O239="Pendente",_xlfn.XLOOKUP(relatorio[[#This Row],[Número]],Relatório_CTE!A:A,Relatório_CTE!B:B,"Sem CTE")," ") -> 4791 | S239: =IF(relatorio[[#This Row],[NFs Entrada - Winthor]]="Pendente",_xlfn.XLOOKUP(relatorio[[#This Row],[Número]],Relatório_CTE!A:A,Relatório_CTE!H:H,"Sem CTE")," ") -> 45918 | T239: =(IF(relatorio[[#This Row],[NFs Entrada - Winthor]]="Pendente",IF(relatorio[[#This Row],[Dt. CTE]]="Sem CTE",relatorio[[#This Row],[Data Emissão]]+_xlfn.XLOOKUP(relatorio[[#This Row],[De_Para]],'Lead Time - Histórico (Fornec.)'!B:B,'Lead Time - Histórico (Fornec.)'!C:C),relatorio[[#This Row],[Dt. CTE]]+_xlfn.XLOOKUP(relatorio[[#This Row],[Cód. Winthor]],'Lead Time - Histórico (Produto)'!A:A,'Lead Time - Histórico (Produto)'!C:C))," ")) -> 45918 | U239: =IFERROR(IF(WEEKDAY(relatorio[[#This Row],[Previsão de entrega - Bruto]],2)=6,relatorio[[#This Row],[Previsão de entrega - Bruto]]+2,IF(WEEKDAY(relatorio[[#This Row],[Previsão de entrega - Bruto]],2)=7,relatorio[[#This Row],[Previsão de entrega - Bruto]]+1,relatorio[[#This Row],[Previsão de entrega - Bruto]]))," ") -> 45918
A240: PRIVADO | B240: CE | C240: 3M DO BRASIL LTDA | D240: 509471 | E240: 45917 | F240: 11656.73 | G240: 7891040357789 | H240: HB004811426 | I240: 1683BR IV ADV 6.5CMX7CM CX 100 3M TEGADERM IV ADV FIX AVANC | J240: 46920 | K240: 4 | L240: =_xlfn.XLOOKUP(relatorio[[#This Row],[Nome PJ Emitente]],De_Para!A:A,De_Para!C:C) -> 3M | M240: {=IF(LEFT(G240&"",1)="0", IFERROR( VALUE(MID(G240&"",_xlfn.AGGREGATE(15,6,ROW(INDIRECT("1:"&LEN(G240&"")))/(MID(G240&"",ROW(INDIRECT("1:"&LEN(G240&""))),1)<>"0"),1),999)), MID(G240&"",_xlfn.AGGREGATE(15,6,ROW(INDIRECT("1:"&LEN(G240&"")))/(MID(G240&"",ROW(INDIRECT("1:"&LEN(G240&""))),1)<>"0"),1),999) ), IFERROR(VALUE(G240),G240))} -> 7891040357789 | N240: =TEXT(relatorio[[#This Row],[Data Emissão]],"mmm") -> set | O240: =_xlfn.XLOOKUP(relatorio[[#This Row],[Número]],relatorio_Entrada_NF!A:A,relatorio_Entrada_NF!A:A,"Pendente") -> Pendente | P240: =_xlfn.XLOOKUP(relatorio[[#This Row],[Nome PJ Emitente]],Material!A:A,Material!B:B,"Medicamento") -> Material | Q240: =IF(relatorio[[#This Row],[Natureza]]="Medicamento",_xlfn.XLOOKUP(relatorio[[#This Row],[EAN]],CadastroProd!U:U,CadastroProd!A:A," "),_xlfn.XLOOKUP(relatorio[[#This Row],['[Item'] Código]],CadastroProd!X:X,CadastroProd!A:A," ")) -> 3547 | R240: =IF(O240="Pendente",_xlfn.XLOOKUP(relatorio[[#This Row],[Número]],Relatório_CTE!A:A,Relatório_CTE!B:B,"Sem CTE")," ") -> 4791 | S240: =IF(relatorio[[#This Row],[NFs Entrada - Winthor]]="Pendente",_xlfn.XLOOKUP(relatorio[[#This Row],[Número]],Relatório_CTE!A:A,Relatório_CTE!H:H,"Sem CTE")," ") -> 45918 | T240: =(IF(relatorio[[#This Row],[NFs Entrada - Winthor]]="Pendente",IF(relatorio[[#This Row],[Dt. CTE]]="Sem CTE",relatorio[[#This Row],[Data Emissão]]+_xlfn.XLOOKUP(relatorio[[#This Row],[De_Para]],'Lead Time - Histórico (Fornec.)'!B:B,'Lead Time - Histórico (Fornec.)'!C:C),relatorio[[#This Row],[Dt. CTE]]+_xlfn.XLOOKUP(relatorio[[#This Row],[Cód. Winthor]],'Lead Time - Histórico (Produto)'!A:A,'Lead Time - Histórico (Produto)'!C:C))," ")) -> 45918 | U240: =IFERROR(IF(WEEKDAY(relatorio[[#This Row],[Previsão de entrega - Bruto]],2)=6,relatorio[[#This Row],[Previsão de entrega - Bruto]]+2,IF(WEEKDAY(relatorio[[#This Row],[Previsão de entrega - Bruto]],2)=7,relatorio[[#This Row],[Previsão de entrega - Bruto]]+1,relatorio[[#This Row],[Previsão de entrega - Bruto]]))," ") -> 45918
A241: PRIVADO | B241: CE | C241: 3M DO BRASIL LTDA | D241: 509471 | E241: 45917 | F241: 11656.73 | G241: 50707387807684 | H241: HB004816565 | I241: 1610 CX C/100 5CMX5.7CM 3M TEGADERM IV CURATIVO | J241: 46853 | K241: 4 | L241: =_xlfn.XLOOKUP(relatorio[[#This Row],[Nome PJ Emitente]],De_Para!A:A,De_Para!C:C) -> 3M | M241: {=IF(LEFT(G241&"",1)="0", IFERROR( VALUE(MID(G241&"",_xlfn.AGGREGATE(15,6,ROW(INDIRECT("1:"&LEN(G241&"")))/(MID(G241&"",ROW(INDIRECT("1:"&LEN(G241&""))),1)<>"0"),1),999)), MID(G241&"",_xlfn.AGGREGATE(15,6,ROW(INDIRECT("1:"&LEN(G241&"")))/(MID(G241&"",ROW(INDIRECT("1:"&LEN(G241&""))),1)<>"0"),1),999) ), IFERROR(VALUE(G241),G241))} -> 50707387807684 | N241: =TEXT(relatorio[[#This Row],[Data Emissão]],"mmm") -> set | O241: =_xlfn.XLOOKUP(relatorio[[#This Row],[Número]],relatorio_Entrada_NF!A:A,relatorio_Entrada_NF!A:A,"Pendente") -> Pendente | P241: =_xlfn.XLOOKUP(relatorio[[#This Row],[Nome PJ Emitente]],Material!A:A,Material!B:B,"Medicamento") -> Material | Q241: =IF(relatorio[[#This Row],[Natureza]]="Medicamento",_xlfn.XLOOKUP(relatorio[[#This Row],[EAN]],CadastroProd!U:U,CadastroProd!A:A," "),_xlfn.XLOOKUP(relatorio[[#This Row],['[Item'] Código]],CadastroProd!X:X,CadastroProd!A:A," ")) -> 3479 | R241: =IF(O241="Pendente",_xlfn.XLOOKUP(relatorio[[#This Row],[Número]],Relatório_CTE!A:A,Relatório_CTE!B:B,"Sem CTE")," ") -> 4791 | S241: =IF(relatorio[[#This Row],[NFs Entrada - Winthor]]="Pendente",_xlfn.XLOOKUP(relatorio[[#This Row],[Número]],Relatório_CTE!A:A,Relatório_CTE!H:H,"Sem CTE")," ") -> 45918 | T241: =(IF(relatorio[[#This Row],[NFs Entrada - Winthor]]="Pendente",IF(relatorio[[#This Row],[Dt. CTE]]="Sem CTE",relatorio[[#This Row],[Data Emissão]]+_xlfn.XLOOKUP(relatorio[[#This Row],[De_Para]],'Lead Time - Histórico (Fornec.)'!B:B,'Lead Time - Histórico (Fornec.)'!C:C),relatorio[[#This Row],[Dt. CTE]]+_xlfn.XLOOKUP(relatorio[[#This Row],[Cód. Winthor]],'Lead Time - Histórico (Produto)'!A:A,'Lead Time - Histórico (Produto)'!C:C))," ")) -> 45918 | U241: =IFERROR(IF(WEEKDAY(relatorio[[#This Row],[Previsão de entrega - Bruto]],2)=6,relatorio[[#This Row],[Previsão de entrega - Bruto]]+2,IF(WEEKDAY(relatorio[[#This Row],[Previsão de entrega - Bruto]],2)=7,relatorio[[#This Row],[Previsão de entrega - Bruto]]+1,relatorio[[#This Row],[Previsão de entrega - Bruto]]))," ") -> 45918
A242: PRIVADO | B242: CE | C242: 3M DO BRASIL LTDA | D242: 509472 | E242: 45917 | F242: 18308.64 | G242: 7891040081356 | H242: H0001819558 | I242: 3591 9CMX25CM CX C/25 CURATIVO TRANSPARENTE TEGADERM | J242: 46879 | K242: 4 | L242: =_xlfn.XLOOKUP(relatorio[[#This Row],[Nome PJ Emitente]],De_Para!A:A,De_Para!C:C) -> 3M | M242: {=IF(LEFT(G242&"",1)="0", IFERROR( VALUE(MID(G242&"",_xlfn.AGGREGATE(15,6,ROW(INDIRECT("1:"&LEN(G242&"")))/(MID(G242&"",ROW(INDIRECT("1:"&LEN(G242&""))),1)<>"0"),1),999)), MID(G242&"",_xlfn.AGGREGATE(15,6,ROW(INDIRECT("1:"&LEN(G242&"")))/(MID(G242&"",ROW(INDIRECT("1:"&LEN(G242&""))),1)<>"0"),1),999) ), IFERROR(VALUE(G242),G242))} -> 7891040081356 | N242: =TEXT(relatorio[[#This Row],[Data Emissão]],"mmm") -> set | O242: =_xlfn.XLOOKUP(relatorio[[#This Row],[Número]],relatorio_Entrada_NF!A:A,relatorio_Entrada_NF!A:A,"Pendente") -> Pendente | P242: =_xlfn.XLOOKUP(relatorio[[#This Row],[Nome PJ Emitente]],Material!A:A,Material!B:B,"Medicamento") -> Material | Q242: =IF(relatorio[[#This Row],[Natureza]]="Medicamento",_xlfn.XLOOKUP(relatorio[[#This Row],[EAN]],CadastroProd!U:U,CadastroProd!A:A," "),_xlfn.XLOOKUP(relatorio[[#This Row],['[Item'] Código]],CadastroProd!X:X,CadastroProd!A:A," ")) -> 2213 | R242: =IF(O242="Pendente",_xlfn.XLOOKUP(relatorio[[#This Row],[Número]],Relatório_CTE!A:A,Relatório_CTE!B:B,"Sem CTE")," ") -> 4791 | S242: =IF(relatorio[[#This Row],[NFs Entrada - Winthor]]="Pendente",_xlfn.XLOOKUP(relatorio[[#This Row],[Número]],Relatório_CTE!A:A,Relatório_CTE!H:H,"Sem CTE")," ") -> 45918 | T242: =(IF(relatorio[[#This Row],[NFs Entrada - Winthor]]="Pendente",IF(relatorio[[#This Row],[Dt. CTE]]="Sem CTE",relatorio[[#This Row],[Data Emissão]]+_xlfn.XLOOKUP(relatorio[[#This Row],[De_Para]],'Lead Time - Histórico (Fornec.)'!B:B,'Lead Time - Histórico (Fornec.)'!C:C),relatorio[[#This Row],[Dt. CTE]]+_xlfn.XLOOKUP(relatorio[[#This Row],[Cód. Winthor]],'Lead Time - Histórico (Produto)'!A:A,'Lead Time - Histórico (Produto)'!C:C))," ")) -> 45933 | U242: =IFERROR(IF(WEEKDAY(relatorio[[#This Row],[Previsão de entrega - Bruto]],2)=6,relatorio[[#This Row],[Previsão de entrega - Bruto]]+2,IF(WEEKDAY(relatorio[[#This Row],[Previsão de entrega - Bruto]],2)=7,relatorio[[#This Row],[Previsão de entrega - Bruto]]+1,relatorio[[#This Row],[Previsão de entrega - Bruto]]))," ") -> 45933
A243: PRIVADO | B243: CE | C243: 3M DO BRASIL LTDA | D243: 509472 | E243: 45917 | F243: 18308.64 | G243: 7891040357789 | H243: HB004811426 | I243: 1683BR IV ADV 6.5CMX7CM CX 100 3M TEGADERM IV ADV FIX AVANC | J243: 46920 | K243: 32 | L243: =_xlfn.XLOOKUP(relatorio[[#This Row],[Nome PJ Emitente]],De_Para!A:A,De_Para!C:C) -> 3M | M243: {=IF(LEFT(G243&"",1)="0", IFERROR( VALUE(MID(G243&"",_xlfn.AGGREGATE(15,6,ROW(INDIRECT("1:"&LEN(G243&"")))/(MID(G243&"",ROW(INDIRECT("1:"&LEN(G243&""))),1)<>"0"),1),999)), MID(G243&"",_xlfn.AGGREGATE(15,6,ROW(INDIRECT("1:"&LEN(G243&"")))/(MID(G243&"",ROW(INDIRECT("1:"&LEN(G243&""))),1)<>"0"),1),999) ), IFERROR(VALUE(G243),G243))} -> 7891040357789 | N243: =TEXT(relatorio[[#This Row],[Data Emissão]],"mmm") -> set | O243: =_xlfn.XLOOKUP(relatorio[[#This Row],[Número]],relatorio_Entrada_NF!A:A,relatorio_Entrada_NF!A:A,"Pendente") -> Pendente | P243: =_xlfn.XLOOKUP(relatorio[[#This Row],[Nome PJ Emitente]],Material!A:A,Material!B:B,"Medicamento") -> Material | Q243: =IF(relatorio[[#This Row],[Natureza]]="Medicamento",_xlfn.XLOOKUP(relatorio[[#This Row],[EAN]],CadastroProd!U:U,CadastroProd!A:A," "),_xlfn.XLOOKUP(relatorio[[#This Row],['[Item'] Código]],CadastroProd!X:X,CadastroProd!A:A," ")) -> 3547 | R243: =IF(O243="Pendente",_xlfn.XLOOKUP(relatorio[[#This Row],[Número]],Relatório_CTE!A:A,Relatório_CTE!B:B,"Sem CTE")," ") -> 4791 | S243: =IF(relatorio[[#This Row],[NFs Entrada - Winthor]]="Pendente",_xlfn.XLOOKUP(relatorio[[#This Row],[Número]],Relatório_CTE!A:A,Relatório_CTE!H:H,"Sem CTE")," ") -> 45918 | T243: =(IF(relatorio[[#This Row],[NFs Entrada - Winthor]]="Pendente",IF(relatorio[[#This Row],[Dt. CTE]]="Sem CTE",relatorio[[#This Row],[Data Emissão]]+_xlfn.XLOOKUP(relatorio[[#This Row],[De_Para]],'Lead Time - Histórico (Fornec.)'!B:B,'Lead Time - Histórico (Fornec.)'!C:C),relatorio[[#This Row],[Dt. CTE]]+_xlfn.XLOOKUP(relatorio[[#This Row],[Cód. Winthor]],'Lead Time - Histórico (Produto)'!A:A,'Lead Time - Histórico (Produto)'!C:C))," ")) -> 45918 | U243: =IFERROR(IF(WEEKDAY(relatorio[[#This Row],[Previsão de entrega - Bruto]],2)=6,relatorio[[#This Row],[Previsão de entrega - Bruto]]+2,IF(WEEKDAY(relatorio[[#This Row],[Previsão de entrega - Bruto]],2)=7,relatorio[[#This Row],[Previsão de entrega - Bruto]]+1,relatorio[[#This Row],[Previsão de entrega - Bruto]]))," ") -> 45918
A244: PRIVADO | B244: CE | C244: 3M DO BRASIL LTDA | D244: 509473 | E244: 45917 | F244: 7108 | G244: 0707387808235 | H244: HB004805469 | I244: 1680 IV ADV 3.8X4.5CM CX C/100 3M TEGAD IV ADV CURAT FIX AVAN | J244: 46891 | K244: 4 | L244: =_xlfn.XLOOKUP(relatorio[[#This Row],[Nome PJ Emitente]],De_Para!A:A,De_Para!C:C) -> 3M | M244: {=IF(LEFT(G244&"",1)="0", IFERROR( VALUE(MID(G244&"",_xlfn.AGGREGATE(15,6,ROW(INDIRECT("1:"&LEN(G244&"")))/(MID(G244&"",ROW(INDIRECT("1:"&LEN(G244&""))),1)<>"0"),1),999)), MID(G244&"",_xlfn.AGGREGATE(15,6,ROW(INDIRECT("1:"&LEN(G244&"")))/(MID(G244&"",ROW(INDIRECT("1:"&LEN(G244&""))),1)<>"0"),1),999) ), IFERROR(VALUE(G244),G244))} -> 707387808235 | N244: =TEXT(relatorio[[#This Row],[Data Emissão]],"mmm") -> set | O244: =_xlfn.XLOOKUP(relatorio[[#This Row],[Número]],relatorio_Entrada_NF!A:A,relatorio_Entrada_NF!A:A,"Pendente") -> Pendente | P244: =_xlfn.XLOOKUP(relatorio[[#This Row],[Nome PJ Emitente]],Material!A:A,Material!B:B,"Medicamento") -> Material | Q244: =IF(relatorio[[#This Row],[Natureza]]="Medicamento",_xlfn.XLOOKUP(relatorio[[#This Row],[EAN]],CadastroProd!U:U,CadastroProd!A:A," "),_xlfn.XLOOKUP(relatorio[[#This Row],['[Item'] Código]],CadastroProd!X:X,CadastroProd!A:A," ")) -> 2199 | R244: =IF(O244="Pendente",_xlfn.XLOOKUP(relatorio[[#This Row],[Número]],Relatório_CTE!A:A,Relatório_CTE!B:B,"Sem CTE")," ") -> 4791 | S244: =IF(relatorio[[#This Row],[NFs Entrada - Winthor]]="Pendente",_xlfn.XLOOKUP(relatorio[[#This Row],[Número]],Relatório_CTE!A:A,Relatório_CTE!H:H,"Sem CTE")," ") -> 45918 | T244: =(IF(relatorio[[#This Row],[NFs Entrada - Winthor]]="Pendente",IF(relatorio[[#This Row],[Dt. CTE]]="Sem CTE",relatorio[[#This Row],[Data Emissão]]+_xlfn.XLOOKUP(relatorio[[#This Row],[De_Para]],'Lead Time - Histórico (Fornec.)'!B:B,'Lead Time - Histórico (Fornec.)'!C:C),relatorio[[#This Row],[Dt. CTE]]+_xlfn.XLOOKUP(relatorio[[#This Row],[Cód. Winthor]],'Lead Time - Histórico (Produto)'!A:A,'Lead Time - Histórico (Produto)'!C:C))," ")) -> 45933 | U244: =IFERROR(IF(WEEKDAY(relatorio[[#This Row],[Previsão de entrega - Bruto]],2)=6,relatorio[[#This Row],[Previsão de entrega - Bruto]]+2,IF(WEEKDAY(relatorio[[#This Row],[Previsão de entrega - Bruto]],2)=7,relatorio[[#This Row],[Previsão de entrega - Bruto]]+1,relatorio[[#This Row],[Previsão de entrega - Bruto]]))," ") -> 45933
A245: PRIVADO | B245: CE | C245: 3M DO BRASIL LTDA | D245: 509473 | E245: 45917 | F245: 7108 | G245: 50707387807684 | H245: HB004816565 | I245: 1610 CX C/100 5CMX5.7CM 3M TEGADERM IV CURATIVO | J245: 46853 | K245: 4 | L245: =_xlfn.XLOOKUP(relatorio[[#This Row],[Nome PJ Emitente]],De_Para!A:A,De_Para!C:C) -> 3M | M245: {=IF(LEFT(G245&"",1)="0", IFERROR( VALUE(MID(G245&"",_xlfn.AGGREGATE(15,6,ROW(INDIRECT("1:"&LEN(G245&"")))/(MID(G245&"",ROW(INDIRECT("1:"&LEN(G245&""))),1)<>"0"),1),999)), MID(G245&"",_xlfn.AGGREGATE(15,6,ROW(INDIRECT("1:"&LEN(G245&"")))/(MID(G245&"",ROW(INDIRECT("1:"&LEN(G245&""))),1)<>"0"),1),999) ), IFERROR(VALUE(G245),G245))} -> 50707387807684 | N245: =TEXT(relatorio[[#This Row],[Data Emissão]],"mmm") -> set | O245: =_xlfn.XLOOKUP(relatorio[[#This Row],[Número]],relatorio_Entrada_NF!A:A,relatorio_Entrada_NF!A:A,"Pendente") -> Pendente | P245: =_xlfn.XLOOKUP(relatorio[[#This Row],[Nome PJ Emitente]],Material!A:A,Material!B:B,"Medicamento") -> Material | Q245: =IF(relatorio[[#This Row],[Natureza]]="Medicamento",_xlfn.XLOOKUP(relatorio[[#This Row],[EAN]],CadastroProd!U:U,CadastroProd!A:A," "),_xlfn.XLOOKUP(relatorio[[#This Row],['[Item'] Código]],CadastroProd!X:X,CadastroProd!A:A," ")) -> 3479 | R245: =IF(O245="Pendente",_xlfn.XLOOKUP(relatorio[[#This Row],[Número]],Relatório_CTE!A:A,Relatório_CTE!B:B,"Sem CTE")," ") -> 4791 | S245: =IF(relatorio[[#This Row],[NFs Entrada - Winthor]]="Pendente",_xlfn.XLOOKUP(relatorio[[#This Row],[Número]],Relatório_CTE!A:A,Relatório_CTE!H:H,"Sem CTE")," ") -> 45918 | T245: =(IF(relatorio[[#This Row],[NFs Entrada - Winthor]]="Pendente",IF(relatorio[[#This Row],[Dt. CTE]]="Sem CTE",relatorio[[#This Row],[Data Emissão]]+_xlfn.XLOOKUP(relatorio[[#This Row],[De_Para]],'Lead Time - Histórico (Fornec.)'!B:B,'Lead Time - Histórico (Fornec.)'!C:C),relatorio[[#This Row],[Dt. CTE]]+_xlfn.XLOOKUP(relatorio[[#This Row],[Cód. Winthor]],'Lead Time - Histórico (Produto)'!A:A,'Lead Time - Histórico (Produto)'!C:C))," ")) -> 45918 | U245: =IFERROR(IF(WEEKDAY(relatorio[[#This Row],[Previsão de entrega - Bruto]],2)=6,relatorio[[#This Row],[Previsão de entrega - Bruto]]+2,IF(WEEKDAY(relatorio[[#This Row],[Previsão de entrega - Bruto]],2)=7,relatorio[[#This Row],[Previsão de entrega - Bruto]]+1,relatorio[[#This Row],[Previsão de entrega - Bruto]]))," ") -> 45918
A246: PRIVADO | B246: CE | C246: 3M DO BRASIL LTDA | D246: 509474 | E246: 45917 | F246: 11167.19 | G246: 7891040010653 | H246: H0001400755 | I246: 1527 100MMX4,5M CARRETEL FITA HIPOALERGENICA TRANSPORE | J246: 46563 | K246: 80 | L246: =_xlfn.XLOOKUP(relatorio[[#This Row],[Nome PJ Emitente]],De_Para!A:A,De_Para!C:C) -> 3M | M246: {=IF(LEFT(G246&"",1)="0", IFERROR( VALUE(MID(G246&"",_xlfn.AGGREGATE(15,6,ROW(INDIRECT("1:"&LEN(G246&"")))/(MID(G246&"",ROW(INDIRECT("1:"&LEN(G246&""))),1)<>"0"),1),999)), MID(G246&"",_xlfn.AGGREGATE(15,6,ROW(INDIRECT("1:"&LEN(G246&"")))/(MID(G246&"",ROW(INDIRECT("1:"&LEN(G246&""))),1)<>"0"),1),999) ), IFERROR(VALUE(G246),G246))} -> 7891040010653 | N246: =TEXT(relatorio[[#This Row],[Data Emissão]],"mmm") -> set | O246: =_xlfn.XLOOKUP(relatorio[[#This Row],[Número]],relatorio_Entrada_NF!A:A,relatorio_Entrada_NF!A:A,"Pendente") -> Pendente | P246: =_xlfn.XLOOKUP(relatorio[[#This Row],[Nome PJ Emitente]],Material!A:A,Material!B:B,"Medicamento") -> Material | Q246: =IF(relatorio[[#This Row],[Natureza]]="Medicamento",_xlfn.XLOOKUP(relatorio[[#This Row],[EAN]],CadastroProd!U:U,CadastroProd!A:A," "),_xlfn.XLOOKUP(relatorio[[#This Row],['[Item'] Código]],CadastroProd!X:X,CadastroProd!A:A," ")) -> 2180 | R246: =IF(O246="Pendente",_xlfn.XLOOKUP(relatorio[[#This Row],[Número]],Relatório_CTE!A:A,Relatório_CTE!B:B,"Sem CTE")," ") -> 4791 | S246: =IF(relatorio[[#This Row],[NFs Entrada - Winthor]]="Pendente",_xlfn.XLOOKUP(relatorio[[#This Row],[Número]],Relatório_CTE!A:A,Relatório_CTE!H:H,"Sem CTE")," ") -> 45918 | T246: =(IF(relatorio[[#This Row],[NFs Entrada - Winthor]]="Pendente",IF(relatorio[[#This Row],[Dt. CTE]]="Sem CTE",relatorio[[#This Row],[Data Emissão]]+_xlfn.XLOOKUP(relatorio[[#This Row],[De_Para]],'Lead Time - Histórico (Fornec.)'!B:B,'Lead Time - Histórico (Fornec.)'!C:C),relatorio[[#This Row],[Dt. CTE]]+_xlfn.XLOOKUP(relatorio[[#This Row],[Cód. Winthor]],'Lead Time - Histórico (Produto)'!A:A,'Lead Time - Histórico (Produto)'!C:C))," ")) -> 45934 | U246: =IFERROR(IF(WEEKDAY(relatorio[[#This Row],[Previsão de entrega - Bruto]],2)=6,relatorio[[#This Row],[Previsão de entrega - Bruto]]+2,IF(WEEKDAY(relatorio[[#This Row],[Previsão de entrega - Bruto]],2)=7,relatorio[[#This Row],[Previsão de entrega - Bruto]]+1,relatorio[[#This Row],[Previsão de entrega - Bruto]]))," ") -> 45936
A247: PRIVADO | B247: CE | C247: 3M DO BRASIL LTDA | D247: 509474 | E247: 45917 | F247: 11167.19 | G247: 7891040010745 | H247: H0001400839 | I247: 1530 50MMX10M CARRETEL FITA CIRURGICA HIPO. MICROPORE | J247: 46579 | K247: 160 | L247: =_xlfn.XLOOKUP(relatorio[[#This Row],[Nome PJ Emitente]],De_Para!A:A,De_Para!C:C) -> 3M | M247: {=IF(LEFT(G247&"",1)="0", IFERROR( VALUE(MID(G247&"",_xlfn.AGGREGATE(15,6,ROW(INDIRECT("1:"&LEN(G247&"")))/(MID(G247&"",ROW(INDIRECT("1:"&LEN(G247&""))),1)<>"0"),1),999)), MID(G247&"",_xlfn.AGGREGATE(15,6,ROW(INDIRECT("1:"&LEN(G247&"")))/(MID(G247&"",ROW(INDIRECT("1:"&LEN(G247&""))),1)<>"0"),1),999) ), IFERROR(VALUE(G247),G247))} -> 7891040010745 | N247: =TEXT(relatorio[[#This Row],[Data Emissão]],"mmm") -> set | O247: =_xlfn.XLOOKUP(relatorio[[#This Row],[Número]],relatorio_Entrada_NF!A:A,relatorio_Entrada_NF!A:A,"Pendente") -> Pendente | P247: =_xlfn.XLOOKUP(relatorio[[#This Row],[Nome PJ Emitente]],Material!A:A,Material!B:B,"Medicamento") -> Material | Q247: =IF(relatorio[[#This Row],[Natureza]]="Medicamento",_xlfn.XLOOKUP(relatorio[[#This Row],[EAN]],CadastroProd!U:U,CadastroProd!A:A," "),_xlfn.XLOOKUP(relatorio[[#This Row],['[Item'] Código]],CadastroProd!X:X,CadastroProd!A:A," ")) -> 2175 | R247: =IF(O247="Pendente",_xlfn.XLOOKUP(relatorio[[#This Row],[Número]],Relatório_CTE!A:A,Relatório_CTE!B:B,"Sem CTE")," ") -> 4791 | S247: =IF(relatorio[[#This Row],[NFs Entrada - Winthor]]="Pendente",_xlfn.XLOOKUP(relatorio[[#This Row],[Número]],Relatório_CTE!A:A,Relatório_CTE!H:H,"Sem CTE")," ") -> 45918 | T247: =(IF(relatorio[[#This Row],[NFs Entrada - Winthor]]="Pendente",IF(relatorio[[#This Row],[Dt. CTE]]="Sem CTE",relatorio[[#This Row],[Data Emissão]]+_xlfn.XLOOKUP(relatorio[[#This Row],[De_Para]],'Lead Time - Histórico (Fornec.)'!B:B,'Lead Time - Histórico (Fornec.)'!C:C),relatorio[[#This Row],[Dt. CTE]]+_xlfn.XLOOKUP(relatorio[[#This Row],[Cód. Winthor]],'Lead Time - Histórico (Produto)'!A:A,'Lead Time - Histórico (Produto)'!C:C))," ")) -> 45934 | U247: =IFERROR(IF(WEEKDAY(relatorio[[#This Row],[Previsão de entrega - Bruto]],2)=6,relatorio[[#This Row],[Previsão de entrega - Bruto]]+2,IF(WEEKDAY(relatorio[[#This Row],[Previsão de entrega - Bruto]],2)=7,relatorio[[#This Row],[Previsão de entrega - Bruto]]+1,relatorio[[#This Row],[Previsão de entrega - Bruto]]))," ") -> 45936
A248: PRIVADO | B248: CE | C248: 3M DO BRASIL LTDA | D248: 509474 | E248: 45917 | F248: 11167.19 | G248: SEM GTIN | H248: H0001556473 | I248: 2269T NEO 10 SC C/ 3 UNID CADA ELETRODO RED DOT | J248: 46549 | K248: 7 | L248: =_xlfn.XLOOKUP(relatorio[[#This Row],[Nome PJ Emitente]],De_Para!A:A,De_Para!C:C) -> 3M | M248: {=IF(LEFT(G248&"",1)="0", IFERROR( VALUE(MID(G248&"",_xlfn.AGGREGATE(15,6,ROW(INDIRECT("1:"&LEN(G248&"")))/(MID(G248&"",ROW(INDIRECT("1:"&LEN(G248&""))),1)<>"0"),1),999)), MID(G248&"",_xlfn.AGGREGATE(15,6,ROW(INDIRECT("1:"&LEN(G248&"")))/(MID(G248&"",ROW(INDIRECT("1:"&LEN(G248&""))),1)<>"0"),1),999) ), IFERROR(VALUE(G248),G248))} -> SEM GTIN | N248: =TEXT(relatorio[[#This Row],[Data Emissão]],"mmm") -> set | O248: =_xlfn.XLOOKUP(relatorio[[#This Row],[Número]],relatorio_Entrada_NF!A:A,relatorio_Entrada_NF!A:A,"Pendente") -> Pendente | P248: =_xlfn.XLOOKUP(relatorio[[#This Row],[Nome PJ Emitente]],Material!A:A,Material!B:B,"Medicamento") -> Material | Q248: =IF(relatorio[[#This Row],[Natureza]]="Medicamento",_xlfn.XLOOKUP(relatorio[[#This Row],[EAN]],CadastroProd!U:U,CadastroProd!A:A," "),_xlfn.XLOOKUP(relatorio[[#This Row],['[Item'] Código]],CadastroProd!X:X,CadastroProd!A:A," ")) -> 2367 | R248: =IF(O248="Pendente",_xlfn.XLOOKUP(relatorio[[#This Row],[Número]],Relatório_CTE!A:A,Relatório_CTE!B:B,"Sem CTE")," ") -> 4791 | S248: =IF(relatorio[[#This Row],[NFs Entrada - Winthor]]="Pendente",_xlfn.XLOOKUP(relatorio[[#This Row],[Número]],Relatório_CTE!A:A,Relatório_CTE!H:H,"Sem CTE")," ") -> 45918 | T248: =(IF(relatorio[[#This Row],[NFs Entrada - Winthor]]="Pendente",IF(relatorio[[#This Row],[Dt. CTE]]="Sem CTE",relatorio[[#This Row],[Data Emissão]]+_xlfn.XLOOKUP(relatorio[[#This Row],[De_Para]],'Lead Time - Histórico (Fornec.)'!B:B,'Lead Time - Histórico (Fornec.)'!C:C),relatorio[[#This Row],[Dt. CTE]]+_xlfn.XLOOKUP(relatorio[[#This Row],[Cód. Winthor]],'Lead Time - Histórico (Produto)'!A:A,'Lead Time - Histórico (Produto)'!C:C))," ")) -> 45933 | U248: =IFERROR(IF(WEEKDAY(relatorio[[#This Row],[Previsão de entrega - Bruto]],2)=6,relatorio[[#This Row],[Previsão de entrega - Bruto]]+2,IF(WEEKDAY(relatorio[[#This Row],[Previsão de entrega - Bruto]],2)=7,relatorio[[#This Row],[Previsão de entrega - Bruto]]+1,relatorio[[#This Row],[Previsão de entrega - Bruto]]))," ") -> 45933
A249: PRIVADO | B249: CE | C249: 3M DO BRASIL LTDA | D249: 509474 | E249: 45917 | F249: 11167.19 | G249: SEM GTIN | H249: HB004559009 | I249: 30000 MANTA AQ CORPO INT C/10 3M BAIR HUGGER MANTA 30000 | J249: 46902 | K249: 1 | L249: =_xlfn.XLOOKUP(relatorio[[#This Row],[Nome PJ Emitente]],De_Para!A:A,De_Para!C:C) -> 3M | M249: {=IF(LEFT(G249&"",1)="0", IFERROR( VALUE(MID(G249&"",_xlfn.AGGREGATE(15,6,ROW(INDIRECT("1:"&LEN(G249&"")))/(MID(G249&"",ROW(INDIRECT("1:"&LEN(G249&""))),1)<>"0"),1),999)), MID(G249&"",_xlfn.AGGREGATE(15,6,ROW(INDIRECT("1:"&LEN(G249&"")))/(MID(G249&"",ROW(INDIRECT("1:"&LEN(G249&""))),1)<>"0"),1),999) ), IFERROR(VALUE(G249),G249))} -> SEM GTIN | N249: =TEXT(relatorio[[#This Row],[Data Emissão]],"mmm") -> set | O249: =_xlfn.XLOOKUP(relatorio[[#This Row],[Número]],relatorio_Entrada_NF!A:A,relatorio_Entrada_NF!A:A,"Pendente") -> Pendente | P249: =_xlfn.XLOOKUP(relatorio[[#This Row],[Nome PJ Emitente]],Material!A:A,Material!B:B,"Medicamento") -> Material | Q249: =IF(relatorio[[#This Row],[Natureza]]="Medicamento",_xlfn.XLOOKUP(relatorio[[#This Row],[EAN]],CadastroProd!U:U,CadastroProd!A:A," "),_xlfn.XLOOKUP(relatorio[[#This Row],['[Item'] Código]],CadastroProd!X:X,CadastroProd!A:A," ")) -> 2333 | R249: =IF(O249="Pendente",_xlfn.XLOOKUP(relatorio[[#This Row],[Número]],Relatório_CTE!A:A,Relatório_CTE!B:B,"Sem CTE")," ") -> 4791 | S249: =IF(relatorio[[#This Row],[NFs Entrada - Winthor]]="Pendente",_xlfn.XLOOKUP(relatorio[[#This Row],[Número]],Relatório_CTE!A:A,Relatório_CTE!H:H,"Sem CTE")," ") -> 45918 | T249: =(IF(relatorio[[#This Row],[NFs Entrada - Winthor]]="Pendente",IF(relatorio[[#This Row],[Dt. CTE]]="Sem CTE",relatorio[[#This Row],[Data Emissão]]+_xlfn.XLOOKUP(relatorio[[#This Row],[De_Para]],'Lead Time - Histórico (Fornec.)'!B:B,'Lead Time - Histórico (Fornec.)'!C:C),relatorio[[#This Row],[Dt. CTE]]+_xlfn.XLOOKUP(relatorio[[#This Row],[Cód. Winthor]],'Lead Time - Histórico (Produto)'!A:A,'Lead Time - Histórico (Produto)'!C:C))," ")) -> 45933 | U249: =IFERROR(IF(WEEKDAY(relatorio[[#This Row],[Previsão de entrega - Bruto]],2)=6,relatorio[[#This Row],[Previsão de entrega - Bruto]]+2,IF(WEEKDAY(relatorio[[#This Row],[Previsão de entrega - Bruto]],2)=7,relatorio[[#This Row],[Previsão de entrega - Bruto]]+1,relatorio[[#This Row],[Previsão de entrega - Bruto]]))," ") -> 45933
... A266: PRIVADO | B266: CE | C266: 3M DO BRASIL LTDA | D266: 509479 | E266: 45917 | F266: 44867.08 | G266: 7891040285389 | H266: HB004558860 | I266: 55501 MANTA AQ PED UNDERB C/10 3M BAIR HUGGER MANTA 55501 | J266: 46862 | K266: 1 | L266: =_xlfn.XLOOKUP(relatorio[[#This Row],[Nome PJ Emitente]],De_Para!A:A,De_Para!C:C) -> 3M | M266: {=IF(LEFT(G266&"",1)="0", IFERROR( VALUE(MID(G266&"",_xlfn.AGGREGATE(15,6,ROW(INDIRECT("1:"&LEN(G266&"")))/(MID(G266&"",ROW(INDIRECT("1:"&LEN(G266&""))),1)<>"0"),1),999)), MID(G266&"",_xlfn.AGGREGATE(15,6,ROW(INDIRECT("1:"&LEN(G266&"")))/(MID(G266&"",ROW(INDIRECT("1:"&LEN(G266&""))),1)<>"0"),1),999) ), IFERROR(VALUE(G266),G266))} -> 7891040285389 | N266: =TEXT(relatorio[[#This Row],[Data Emissão]],"mmm") -> set | O266: =_xlfn.XLOOKUP(relatorio[[#This Row],[Número]],relatorio_Entrada_NF!A:A,relatorio_Entrada_NF!A:A,"Pendente") -> Pendente | P266: =_xlfn.XLOOKUP(relatorio[[#This Row],[Nome PJ Emitente]],Material!A:A,Material!B:B,"Medicamento") -> Material | Q266: =IF(relatorio[[#This Row],[Natureza]]="Medicamento",_xlfn.XLOOKUP(relatorio[[#This Row],[EAN]],CadastroProd!U:U,CadastroProd!A:A," "),_xlfn.XLOOKUP(relatorio[[#This Row],['[Item'] Código]],CadastroProd!X:X,CadastroProd!A:A," ")) -> 2332 | R266: =IF(O266="Pendente",_xlfn.XLOOKUP(relatorio[[#This Row],[Número]],Relatório_CTE!A:A,Relatório_CTE!B:B,"Sem CTE")," ") -> 4791 | S266: =IF(relatorio[[#This Row],[NFs Entrada - Winthor]]="Pendente",_xlfn.XLOOKUP(relatorio[[#This Row],[Número]],Relatório_CTE!A:A,Relatório_CTE!H:H,"Sem CTE")," ") -> 45918 | T266: =(IF(relatorio[[#This Row],[NFs Entrada - Winthor]]="Pendente",IF(relatorio[[#This Row],[Dt. CTE]]="Sem CTE",relatorio[[#This Row],[Data Emissão]]+_xlfn.XLOOKUP(relatorio[[#This Row],[De_Para]],'Lead Time - Histórico (Fornec.)'!B:B,'Lead Time - Histórico (Fornec.)'!C:C),relatorio[[#This Row],[Dt. CTE]]+_xlfn.XLOOKUP(relatorio[[#This Row],[Cód. Winthor]],'Lead Time - Histórico (Produto)'!A:A,'Lead Time - Histórico (Produto)'!C:C))," ")) -> 45933 | U266: =IFERROR(IF(WEEKDAY(relatorio[[#This Row],[Previsão de entrega - Bruto]],2)=6,relatorio[[#This Row],[Previsão de entrega - Bruto]]+2,IF(WEEKDAY(relatorio[[#This Row],[Previsão de entrega - Bruto]],2)=7,relatorio[[#This Row],[Previsão de entrega - Bruto]]+1,relatorio[[#This Row],[Previsão de entrega - Bruto]]))," ") -> 45933
A267: PRIVADO | B267: CE | C267: 3M DO BRASIL LTDA | D267: 509479 | E267: 45917 | F267: 44867.08 | G267: SEM GTIN | H267: HB004559009 | I267: 30000 MANTA AQ CORPO INT C/10 3M BAIR HUGGER MANTA 30000 | K267: 9 | L267: =_xlfn.XLOOKUP(relatorio[[#This Row],[Nome PJ Emitente]],De_Para!A:A,De_Para!C:C) -> 3M | M267: {=IF(LEFT(G267&"",1)="0", IFERROR( VALUE(MID(G267&"",_xlfn.AGGREGATE(15,6,ROW(INDIRECT("1:"&LEN(G267&"")))/(MID(G267&"",ROW(INDIRECT("1:"&LEN(G267&""))),1)<>"0"),1),999)), MID(G267&"",_xlfn.AGGREGATE(15,6,ROW(INDIRECT("1:"&LEN(G267&"")))/(MID(G267&"",ROW(INDIRECT("1:"&LEN(G267&""))),1)<>"0"),1),999) ), IFERROR(VALUE(G267),G267))} -> SEM GTIN | N267: =TEXT(relatorio[[#This Row],[Data Emissão]],"mmm") -> set | O267: =_xlfn.XLOOKUP(relatorio[[#This Row],[Número]],relatorio_Entrada_NF!A:A,relatorio_Entrada_NF!A:A,"Pendente") -> Pendente | P267: =_xlfn.XLOOKUP(relatorio[[#This Row],[Nome PJ Emitente]],Material!A:A,Material!B:B,"Medicamento") -> Material | Q267: =IF(relatorio[[#This Row],[Natureza]]="Medicamento",_xlfn.XLOOKUP(relatorio[[#This Row],[EAN]],CadastroProd!U:U,CadastroProd!A:A," "),_xlfn.XLOOKUP(relatorio[[#This Row],['[Item'] Código]],CadastroProd!X:X,CadastroProd!A:A," ")) -> 2333 | R267: =IF(O267="Pendente",_xlfn.XLOOKUP(relatorio[[#This Row],[Número]],Relatório_CTE!A:A,Relatório_CTE!B:B,"Sem CTE")," ") -> 4791 | S267: =IF(relatorio[[#This Row],[NFs Entrada - Winthor]]="Pendente",_xlfn.XLOOKUP(relatorio[[#This Row],[Número]],Relatório_CTE!A:A,Relatório_CTE!H:H,"Sem CTE")," ") -> 45918 | T267: =(IF(relatorio[[#This Row],[NFs Entrada - Winthor]]="Pendente",IF(relatorio[[#This Row],[Dt. CTE]]="Sem CTE",relatorio[[#This Row],[Data Emissão]]+_xlfn.XLOOKUP(relatorio[[#This Row],[De_Para]],'Lead Time - Histórico (Fornec.)'!B:B,'Lead Time - Histórico (Fornec.)'!C:C),relatorio[[#This Row],[Dt. CTE]]+_xlfn.XLOOKUP(relatorio[[#This Row],[Cód. Winthor]],'Lead Time - Histórico (Produto)'!A:A,'Lead Time - Histórico (Produto)'!C:C))," ")) -> 45933 | U267: =IFERROR(IF(WEEKDAY(relatorio[[#This Row],[Previsão de entrega - Bruto]],2)=6,relatorio[[#This Row],[Previsão de entrega - Bruto]]+2,IF(WEEKDAY(relatorio[[#This Row],[Previsão de entrega - Bruto]],2)=7,relatorio[[#This Row],[Previsão de entrega - Bruto]]+1,relatorio[[#This Row],[Previsão de entrega - Bruto]]))," ") -> 45933
A268: PRIVADO | B268: CE | C268: 3M DO BRASIL LTDA | D268: 509479 | E268: 45917 | F268: 44867.08 | G268: SEM GTIN | H268: HB004559256 | I268: 63500 MANTA AQ UNDER COMPL C/5 3M BAIR HUGGER MANTA 63500 | J268: 46945 | K268: 50 | L268: =_xlfn.XLOOKUP(relatorio[[#This Row],[Nome PJ Emitente]],De_Para!A:A,De_Para!C:C) -> 3M | M268: {=IF(LEFT(G268&"",1)="0", IFERROR( VALUE(MID(G268&"",_xlfn.AGGREGATE(15,6,ROW(INDIRECT("1:"&LEN(G268&"")))/(MID(G268&"",ROW(INDIRECT("1:"&LEN(G268&""))),1)<>"0"),1),999)), MID(G268&"",_xlfn.AGGREGATE(15,6,ROW(INDIRECT("1:"&LEN(G268&"")))/(MID(G268&"",ROW(INDIRECT("1:"&LEN(G268&""))),1)<>"0"),1),999) ), IFERROR(VALUE(G268),G268))} -> SEM GTIN | N268: =TEXT(relatorio[[#This Row],[Data Emissão]],"mmm") -> set | O268: =_xlfn.XLOOKUP(relatorio[[#This Row],[Número]],relatorio_Entrada_NF!A:A,relatorio_Entrada_NF!A:A,"Pendente") -> Pendente | P268: =_xlfn.XLOOKUP(relatorio[[#This Row],[Nome PJ Emitente]],Material!A:A,Material!B:B,"Medicamento") -> Material | Q268: =IF(relatorio[[#This Row],[Natureza]]="Medicamento",_xlfn.XLOOKUP(relatorio[[#This Row],[EAN]],CadastroProd!U:U,CadastroProd!A:A," "),_xlfn.XLOOKUP(relatorio[[#This Row],['[Item'] Código]],CadastroProd!X:X,CadastroProd!A:A," ")) -> 2337 | R268: =IF(O268="Pendente",_xlfn.XLOOKUP(relatorio[[#This Row],[Número]],Relatório_CTE!A:A,Relatório_CTE!B:B,"Sem CTE")," ") -> 4791 | S268: =IF(relatorio[[#This Row],[NFs Entrada - Winthor]]="Pendente",_xlfn.XLOOKUP(relatorio[[#This Row],[Número]],Relatório_CTE!A:A,Relatório_CTE!H:H,"Sem CTE")," ") -> 45918 | T268: =(IF(relatorio[[#This Row],[NFs Entrada - Winthor]]="Pendente",IF(relatorio[[#This Row],[Dt. CTE]]="Sem CTE",relatorio[[#This Row],[Data Emissão]]+_xlfn.XLOOKUP(relatorio[[#This Row],[De_Para]],'Lead Time - Histórico (Fornec.)'!B:B,'Lead Time - Histórico (Fornec.)'!C:C),relatorio[[#This Row],[Dt. CTE]]+_xlfn.XLOOKUP(relatorio[[#This Row],[Cód. Winthor]],'Lead Time - Histórico (Produto)'!A:A,'Lead Time - Histórico (Produto)'!C:C))," ")) -> 45933 | U268: =IFERROR(IF(WEEKDAY(relatorio[[#This Row],[Previsão de entrega - Bruto]],2)=6,relatorio[[#This Row],[Previsão de entrega - Bruto]]+2,IF(WEEKDAY(relatorio[[#This Row],[Previsão de entrega - Bruto]],2)=7,relatorio[[#This Row],[Previsão de entrega - Bruto]]+1,relatorio[[#This Row],[Previsão de entrega - Bruto]]))," ") -> 45933
A269: PRIVADO | B269: CE | C269: 3M DO BRASIL LTDA | D269: 509479 | E269: 45917 | F269: 44867.08 | G269: 7891040313204 | H269: HB004672265 | I269: COBAN NL 2082 50MMX4.5M 3M COBAN NL 2082 50MMX4.5M | J269: 46910 | K269: 36 | L269: =_xlfn.XLOOKUP(relatorio[[#This Row],[Nome PJ Emitente]],De_Para!A:A,De_Para!C:C) -> 3M | M269: {=IF(LEFT(G269&"",1)="0", IFERROR( VALUE(MID(G269&"",_xlfn.AGGREGATE(15,6,ROW(INDIRECT("1:"&LEN(G269&"")))/(MID(G269&"",ROW(INDIRECT("1:"&LEN(G269&""))),1)<>"0"),1),999)), MID(G269&"",_xlfn.AGGREGATE(15,6,ROW(INDIRECT("1:"&LEN(G269&"")))/(MID(G269&"",ROW(INDIRECT("1:"&LEN(G269&""))),1)<>"0"),1),999) ), IFERROR(VALUE(G269),G269))} -> 7891040313204 | N269: =TEXT(relatorio[[#This Row],[Data Emissão]],"mmm") -> set | O269: =_xlfn.XLOOKUP(relatorio[[#This Row],[Número]],relatorio_Entrada_NF!A:A,relatorio_Entrada_NF!A:A,"Pendente") -> Pendente | P269: =_xlfn.XLOOKUP(relatorio[[#This Row],[Nome PJ Emitente]],Material!A:A,Material!B:B,"Medicamento") -> Material | Q269: =IF(relatorio[[#This Row],[Natureza]]="Medicamento",_xlfn.XLOOKUP(relatorio[[#This Row],[EAN]],CadastroProd!U:U,CadastroProd!A:A," "),_xlfn.XLOOKUP(relatorio[[#This Row],['[Item'] Código]],CadastroProd!X:X,CadastroProd!A:A," ")) -> 2248 | R269: =IF(O269="Pendente",_xlfn.XLOOKUP(relatorio[[#This Row],[Número]],Relatório_CTE!A:A,Relatório_CTE!B:B,"Sem CTE")," ") -> 4791 | S269: =IF(relatorio[[#This Row],[NFs Entrada - Winthor]]="Pendente",_xlfn.XLOOKUP(relatorio[[#This Row],[Número]],Relatório_CTE!A:A,Relatório_CTE!H:H,"Sem CTE")," ") -> 45918 | T269: =(IF(relatorio[[#This Row],[NFs Entrada - Winthor]]="Pendente",IF(relatorio[[#This Row],[Dt. CTE]]="Sem CTE",relatorio[[#This Row],[Data Emissão]]+_xlfn.XLOOKUP(relatorio[[#This Row],[De_Para]],'Lead Time - Histórico (Fornec.)'!B:B,'Lead Time - Histórico (Fornec.)'!C:C),relatorio[[#This Row],[Dt. CTE]]+_xlfn.XLOOKUP(relatorio[[#This Row],[Cód. Winthor]],'Lead Time - Histórico (Produto)'!A:A,'Lead Time - Histórico (Produto)'!C:C))," ")) -> 45933 | U269: =IFERROR(IF(WEEKDAY(relatorio[[#This Row],[Previsão de entrega - Bruto]],2)=6,relatorio[[#This Row],[Previsão de entrega - Bruto]]+2,IF(WEEKDAY(relatorio[[#This Row],[Previsão de entrega - Bruto]],2)=7,relatorio[[#This Row],[Previsão de entrega - Bruto]]+1,relatorio[[#This Row],[Previsão de entrega - Bruto]]))," ") -> 45933
A270: PRIVADO | B270: CE | C270: 3M DO BRASIL LTDA | D270: 509480 | E270: 45917 | F270: 19713.2 | G270: 7891040159970 | H270: HB004318778 | I270: CAVILON LIMP. PELE S/ ENXAGUE CAVILON | J270: 46630 | K270: 60 | L270: =_xlfn.XLOOKUP(relatorio[[#This Row],[Nome PJ Emitente]],De_Para!A:A,De_Para!C:C) -> 3M | M270: {=IF(LEFT(G270&"",1)="0", IFERROR( VALUE(MID(G270&"",_xlfn.AGGREGATE(15,6,ROW(INDIRECT("1:"&LEN(G270&"")))/(MID(G270&"",ROW(INDIRECT("1:"&LEN(G270&""))),1)<>"0"),1),999)), MID(G270&"",_xlfn.AGGREGATE(15,6,ROW(INDIRECT("1:"&LEN(G270&"")))/(MID(G270&"",ROW(INDIRECT("1:"&LEN(G270&""))),1)<>"0"),1),999) ), IFERROR(VALUE(G270),G270))} -> 7891040159970 | N270: =TEXT(relatorio[[#This Row],[Data Emissão]],"mmm") -> set | O270: =_xlfn.XLOOKUP(relatorio[[#This Row],[Número]],relatorio_Entrada_NF!A:A,relatorio_Entrada_NF!A:A,"Pendente") -> Pendente | P270: =_xlfn.XLOOKUP(relatorio[[#This Row],[Nome PJ Emitente]],Material!A:A,Material!B:B,"Medicamento") -> Material | Q270: =IF(relatorio[[#This Row],[Natureza]]="Medicamento",_xlfn.XLOOKUP(relatorio[[#This Row],[EAN]],CadastroProd!U:U,CadastroProd!A:A," "),_xlfn.XLOOKUP(relatorio[[#This Row],['[Item'] Código]],CadastroProd!X:X,CadastroProd!A:A," ")) -> 2241 | R270: =IF(O270="Pendente",_xlfn.XLOOKUP(relatorio[[#This Row],[Número]],Relatório_CTE!A:A,Relatório_CTE!B:B,"Sem CTE")," ") -> 4791 | S270: =IF(relatorio[[#This Row],[NFs Entrada - Winthor]]="Pendente",_xlfn.XLOOKUP(relatorio[[#This Row],[Número]],Relatório_CTE!A:A,Relatório_CTE!H:H,"Sem CTE")," ") -> 45918 | T270: =(IF(relatorio[[#This Row],[NFs Entrada - Winthor]]="Pendente",IF(relatorio[[#This Row],[Dt. CTE]]="Sem CTE",relatorio[[#This Row],[Data Emissão]]+_xlfn.XLOOKUP(relatorio[[#This Row],[De_Para]],'Lead Time - Histórico (Fornec.)'!B:B,'Lead Time - Histórico (Fornec.)'!C:C),relatorio[[#This Row],[Dt. CTE]]+_xlfn.XLOOKUP(relatorio[[#This Row],[Cód. Winthor]],'Lead Time - Histórico (Produto)'!A:A,'Lead Time - Histórico (Produto)'!C:C))," ")) -> 45928 | U270: =IFERROR(IF(WEEKDAY(relatorio[[#This Row],[Previsão de entrega - Bruto]],2)=6,relatorio[[#This Row],[Previsão de entrega - Bruto]]+2,IF(WEEKDAY(relatorio[[#This Row],[Previsão de entrega - Bruto]],2)=7,relatorio[[#This Row],[Previsão de entrega - Bruto]]+1,relatorio[[#This Row],[Previsão de entrega - Bruto]]))," ") -> 45929
A271: PRIVADO | B271: CE | C271: 3M DO BRASIL LTDA | D271: 509480 | E271: 45917 | F271: 19713.2 | G271: 7891040241293 | H271: HB004512594 | I271: CAVILON CREME BARREIRA GBR 92G CAVILON CREME BARREIRA 3392GBR | J271: 46431 | K271: 96 | L271: =_xlfn.XLOOKUP(relatorio[[#This Row],[Nome PJ Emitente]],De_Para!A:A,De_Para!C:C) -> 3M | M271: {=IF(LEFT(G271&"",1)="0", IFERROR( VALUE(MID(G271&"",_xlfn.AGGREGATE(15,6,ROW(INDIRECT("1:"&LEN(G271&"")))/(MID(G271&"",ROW(INDIRECT("1:"&LEN(G271&""))),1)<>"0"),1),999)), MID(G271&"",_xlfn.AGGREGATE(15,6,ROW(INDIRECT("1:"&LEN(G271&"")))/(MID(G271&"",ROW(INDIRECT("1:"&LEN(G271&""))),1)<>"0"),1),999) ), IFERROR(VALUE(G271),G271))} -> 7891040241293 | N271: =TEXT(relatorio[[#This Row],[Data Emissão]],"mmm") -> set | O271: =_xlfn.XLOOKUP(relatorio[[#This Row],[Número]],relatorio_Entrada_NF!A:A,relatorio_Entrada_NF!A:A,"Pendente") -> Pendente | P271: =_xlfn.XLOOKUP(relatorio[[#This Row],[Nome PJ Emitente]],Material!A:A,Material!B:B,"Medicamento") -> Material | Q271: =IF(relatorio[[#This Row],[Natureza]]="Medicamento",_xlfn.XLOOKUP(relatorio[[#This Row],[EAN]],CadastroProd!U:U,CadastroProd!A:A," "),_xlfn.XLOOKUP(relatorio[[#This Row],['[Item'] Código]],CadastroProd!X:X,CadastroProd!A:A," ")) -> 2240 | R271: =IF(O271="Pendente",_xlfn.XLOOKUP(relatorio[[#This Row],[Número]],Relatório_CTE!A:A,Relatório_CTE!B:B,"Sem CTE")," ") -> 4791 | S271: =IF(relatorio[[#This Row],[NFs Entrada - Winthor]]="Pendente",_xlfn.XLOOKUP(relatorio[[#This Row],[Número]],Relatório_CTE!A:A,Relatório_CTE!H:H,"Sem CTE")," ") -> 45918 | T271: =(IF(relatorio[[#This Row],[NFs Entrada - Winthor]]="Pendente",IF(relatorio[[#This Row],[Dt. CTE]]="Sem CTE",relatorio[[#This Row],[Data Emissão]]+_xlfn.XLOOKUP(relatorio[[#This Row],[De_Para]],'Lead Time - Histórico (Fornec.)'!B:B,'Lead Time - Histórico (Fornec.)'!C:C),relatorio[[#This Row],[Dt. CTE]]+_xlfn.XLOOKUP(relatorio[[#This Row],[Cód. Winthor]],'Lead Time - Histórico (Produto)'!A:A,'Lead Time - Histórico (Produto)'!C:C))," ")) -> 45935 | U271: =IFERROR(IF(WEEKDAY(relatorio[[#This Row],[Previsão de entrega - Bruto]],2)=6,relatorio[[#This Row],[Previsão de entrega - Bruto]]+2,IF(WEEKDAY(relatorio[[#This Row],[Previsão de entrega - Bruto]],2)=7,relatorio[[#This Row],[Previsão de entrega - Bruto]]+1,relatorio[[#This Row],[Previsão de entrega - Bruto]]))," ") -> 45936
A272: PRIVADO | B272: CE | C272: 3M DO BRASIL LTDA | D272: 509480 | E272: 45917 | F272: 19713.2 | G272: SEM GTIN | H272: HB004559264 | I272: 3M FIXADOR TUBOS SONDAS NASAL 3M FIXADOR TUBOS SONDAS NASAL | J272: 46584 | K272: 4 | L272: =_xlfn.XLOOKUP(relatorio[[#This Row],[Nome PJ Emitente]],De_Para!A:A,De_Para!C:C) -> 3M | M272: {=IF(LEFT(G272&"",1)="0", IFERROR( VALUE(MID(G272&"",_xlfn.AGGREGATE(15,6,ROW(INDIRECT("1:"&LEN(G272&"")))/(MID(G272&"",ROW(INDIRECT("1:"&LEN(G272&""))),1)<>"0"),1),999)), MID(G272&"",_xlfn.AGGREGATE(15,6,ROW(INDIRECT("1:"&LEN(G272&"")))/(MID(G272&"",ROW(INDIRECT("1:"&LEN(G272&""))),1)<>"0"),1),999) ), IFERROR(VALUE(G272),G272))} -> SEM GTIN | N272: =TEXT(relatorio[[#This Row],[Data Emissão]],"mmm") -> set | O272: =_xlfn.XLOOKUP(relatorio[[#This Row],[Número]],relatorio_Entrada_NF!A:A,relatorio_Entrada_NF!A:A,"Pendente") -> Pendente | P272: =_xlfn.XLOOKUP(relatorio[[#This Row],[Nome PJ Emitente]],Material!A:A,Material!B:B,"Medicamento") -> Material | Q272: =IF(relatorio[[#This Row],[Natureza]]="Medicamento",_xlfn.XLOOKUP(relatorio[[#This Row],[EAN]],CadastroProd!U:U,CadastroProd!A:A," "),_xlfn.XLOOKUP(relatorio[[#This Row],['[Item'] Código]],CadastroProd!X:X,CadastroProd!A:A," ")) -> 2209 | R272: =IF(O272="Pendente",_xlfn.XLOOKUP(relatorio[[#This Row],[Número]],Relatório_CTE!A:A,Relatório_CTE!B:B,"Sem CTE")," ") -> 4791 | S272: =IF(relatorio[[#This Row],[NFs Entrada - Winthor]]="Pendente",_xlfn.XLOOKUP(relatorio[[#This Row],[Número]],Relatório_CTE!A:A,Relatório_CTE!H:H,"Sem CTE")," ") -> 45918 | T272: =(IF(relatorio[[#This Row],[NFs Entrada - Winthor]]="Pendente",IF(relatorio[[#This Row],[Dt. CTE]]="Sem CTE",relatorio[[#This Row],[Data Emissão]]+_xlfn.XLOOKUP(relatorio[[#This Row],[De_Para]],'Lead Time - Histórico (Fornec.)'!B:B,'Lead Time - Histórico (Fornec.)'!C:C),relatorio[[#This Row],[Dt. CTE]]+_xlfn.XLOOKUP(relatorio[[#This Row],[Cód. Winthor]],'Lead Time - Histórico (Produto)'!A:A,'Lead Time - Histórico (Produto)'!C:C))," ")) -> 45935 | U272: =IFERROR(IF(WEEKDAY(relatorio[[#This Row],[Previsão de entrega - Bruto]],2)=6,relatorio[[#This Row],[Previsão de entrega - Bruto]]+2,IF(WEEKDAY(relatorio[[#This Row],[Previsão de entrega - Bruto]],2)=7,relatorio[[#This Row],[Previsão de entrega - Bruto]]+1,relatorio[[#This Row],[Previsão de entrega - Bruto]]))," ") -> 45936
A273: PRIVADO | B273: CE | C273: 3M DO BRASIL LTDA | D273: 509480 | E273: 45917 | F273: 19713.2 | G273: 7891040350056 | H273: HB004782403 | I273: 2861BR-4 2.5CMX4M CX C/ 48 3M MEDIPORE H BR FITA MEDICA | J273: 46962 | K273: 48 | L273: =_xlfn.XLOOKUP(relatorio[[#This Row],[Nome PJ Emitente]],De_Para!A:A,De_Para!C:C) -> 3M | M273: {=IF(LEFT(G273&"",1)="0", IFERROR( VALUE(MID(G273&"",_xlfn.AGGREGATE(15,6,ROW(INDIRECT("1:"&LEN(G273&"")))/(MID(G273&"",ROW(INDIRECT("1:"&LEN(G273&""))),1)<>"0"),1),999)), MID(G273&"",_xlfn.AGGREGATE(15,6,ROW(INDIRECT("1:"&LEN(G273&"")))/(MID(G273&"",ROW(INDIRECT("1:"&LEN(G273&""))),1)<>"0"),1),999) ), IFERROR(VALUE(G273),G273))} -> 7891040350056 | N273: =TEXT(relatorio[[#This Row],[Data Emissão]],"mmm") -> set | O273: =_xlfn.XLOOKUP(relatorio[[#This Row],[Número]],relatorio_Entrada_NF!A:A,relatorio_Entrada_NF!A:A,"Pendente") -> Pendente | P273: =_xlfn.XLOOKUP(relatorio[[#This Row],[Nome PJ Emitente]],Material!A:A,Material!B:B,"Medicamento") -> Material | Q273: =IF(relatorio[[#This Row],[Natureza]]="Medicamento",_xlfn.XLOOKUP(relatorio[[#This Row],[EAN]],CadastroProd!U:U,CadastroProd!A:A," "),_xlfn.XLOOKUP(relatorio[[#This Row],['[Item'] Código]],CadastroProd!X:X,CadastroProd!A:A," ")) -> 2956 | R273: =IF(O273="Pendente",_xlfn.XLOOKUP(relatorio[[#This Row],[Número]],Relatório_CTE!A:A,Relatório_CTE!B:B,"Sem CTE")," ") -> 4791 | S273: =IF(relatorio[[#This Row],[NFs Entrada - Winthor]]="Pendente",_xlfn.XLOOKUP(relatorio[[#This Row],[Número]],Relatório_CTE!A:A,Relatório_CTE!H:H,"Sem CTE")," ") -> 45918 | T273: =(IF(relatorio[[#This Row],[NFs Entrada - Winthor]]="Pendente",IF(relatorio[[#This Row],[Dt. CTE]]="Sem CTE",relatorio[[#This Row],[Data Emissão]]+_xlfn.XLOOKUP(relatorio[[#This Row],[De_Para]],'Lead Time - Histórico (Fornec.)'!B:B,'Lead Time - Histórico (Fornec.)'!C:C),relatorio[[#This Row],[Dt. CTE]]+_xlfn.XLOOKUP(relatorio[[#This Row],[Cód. Winthor]],'Lead Time - Histórico (Produto)'!A:A,'Lead Time - Histórico (Produto)'!C:C))," ")) -> 45932 | U273: =IFERROR(IF(WEEKDAY(relatorio[[#This Row],[Previsão de entrega - Bruto]],2)=6,relatorio[[#This Row],[Previsão de entrega - Bruto]]+2,IF(WEEKDAY(relatorio[[#This Row],[Previsão de entrega - Bruto]],2)=7,relatorio[[#This Row],[Previsão de entrega - Bruto]]+1,relatorio[[#This Row],[Previsão de entrega - Bruto]]))," ") -> 45932
A274: PRIVADO | B274: CE | C274: 3M DO BRASIL LTDA | D274: 509480 | E274: 45917 | F274: 19713.2 | G274: 7891040350032 | H274: HB004782429 | I274: 2864BR-4 10CMX4M CX C/ 24 3M MEDIPORE H BR FITA MEDICA | J274: 46914 | K274: 96 | L274: =_xlfn.XLOOKUP(relatorio[[#This Row],[Nome PJ Emitente]],De_Para!A:A,De_Para!C:C) -> 3M | M274: {=IF(LEFT(G274&"",1)="0", IFERROR( VALUE(MID(G274&"",_xlfn.AGGREGATE(15,6,ROW(INDIRECT("1:"&LEN(G274&"")))/(MID(G274&"",ROW(INDIRECT("1:"&LEN(G274&""))),1)<>"0"),1),999)), MID(G274&"",_xlfn.AGGREGATE(15,6,ROW(INDIRECT("1:"&LEN(G274&"")))/(MID(G274&"",ROW(INDIRECT("1:"&LEN(G274&""))),1)<>"0"),1),999) ), IFERROR(VALUE(G274),G274))} -> 7891040350032 | N274: =TEXT(relatorio[[#This Row],[Data Emissão]],"mmm") -> set | O274: =_xlfn.XLOOKUP(relatorio[[#This Row],[Número]],relatorio_Entrada_NF!A:A,relatorio_Entrada_NF!A:A,"Pendente") -> Pendente | P274: =_xlfn.XLOOKUP(relatorio[[#This Row],[Nome PJ Emitente]],Material!A:A,Material!B:B,"Medicamento") -> Material | Q274: =IF(relatorio[[#This Row],[Natureza]]="Medicamento",_xlfn.XLOOKUP(relatorio[[#This Row],[EAN]],CadastroProd!U:U,CadastroProd!A:A," "),_xlfn.XLOOKUP(relatorio[[#This Row],['[Item'] Código]],CadastroProd!X:X,CadastroProd!A:A," ")) -> 2958 | R274: =IF(O274="Pendente",_xlfn.XLOOKUP(relatorio[[#This Row],[Número]],Relatório_CTE!A:A,Relatório_CTE!B:B,"Sem CTE")," ") -> 4791 | S274: =IF(relatorio[[#This Row],[NFs Entrada - Winthor]]="Pendente",_xlfn.XLOOKUP(relatorio[[#This Row],[Número]],Relatório_CTE!A:A,Relatório_CTE!H:H,"Sem CTE")," ") -> 45918 | T274: =(IF(relatorio[[#This Row],[NFs Entrada - Winthor]]="Pendente",IF(relatorio[[#This Row],[Dt. CTE]]="Sem CTE",relatorio[[#This Row],[Data Emissão]]+_xlfn.XLOOKUP(relatorio[[#This Row],[De_Para]],'Lead Time - Histórico (Fornec.)'!B:B,'Lead Time - Histórico (Fornec.)'!C:C),relatorio[[#This Row],[Dt. CTE]]+_xlfn.XLOOKUP(relatorio[[#This Row],[Cód. Winthor]],'Lead Time - Histórico (Produto)'!A:A,'Lead Time - Histórico (Produto)'!C:C))," ")) -> 45933 | U274: =IFERROR(IF(WEEKDAY(relatorio[[#This Row],[Previsão de entrega - Bruto]],2)=6,relatorio[[#This Row],[Previsão de entrega - Bruto]]+2,IF(WEEKDAY(relatorio[[#This Row],[Previsão de entrega - Bruto]],2)=7,relatorio[[#This Row],[Previsão de entrega - Bruto]]+1,relatorio[[#This Row],[Previsão de entrega - Bruto]]))," ") -> 45933
A275: PRIVADO | B275: CE | C275: 3M DO BRASIL LTDA | D275: 509480 | E275: 45917 | F275: 19713.2 | G275: 30707387802241 | H275: HB004800312 | I275: 1660R TEGADERM CHG CX C/25 3M TEGADERM CHG | J275: 46450 | K275: 4 | L275: =_xlfn.XLOOKUP(relatorio[[#This Row],[Nome PJ Emitente]],De_Para!A:A,De_Para!C:C) -> 3M | M275: {=IF(LEFT(G275&"",1)="0", IFERROR( VALUE(MID(G275&"",_xlfn.AGGREGATE(15,6,ROW(INDIRECT("1:"&LEN(G275&"")))/(MID(G275&"",ROW(INDIRECT("1:"&LEN(G275&""))),1)<>"0"),1),999)), MID(G275&"",_xlfn.AGGREGATE(15,6,ROW(INDIRECT("1:"&LEN(G275&"")))/(MID(G275&"",ROW(INDIRECT("1:"&LEN(G275&""))),1)<>"0"),1),999) ), IFERROR(VALUE(G275),G275))} -> 30707387802241 | N275: =TEXT(relatorio[[#This Row],[Data Emissão]],"mmm") -> set | O275: =_xlfn.XLOOKUP(relatorio[[#This Row],[Número]],relatorio_Entrada_NF!A:A,relatorio_Entrada_NF!A:A,"Pendente") -> Pendente | P275: =_xlfn.XLOOKUP(relatorio[[#This Row],[Nome PJ Emitente]],Material!A:A,Material!B:B,"Medicamento") -> Material | Q275: =IF(relatorio[[#This Row],[Natureza]]="Medicamento",_xlfn.XLOOKUP(relatorio[[#This Row],[EAN]],CadastroProd!U:U,CadastroProd!A:A," "),_xlfn.XLOOKUP(relatorio[[#This Row],['[Item'] Código]],CadastroProd!X:X,CadastroProd!A:A," ")) -> 3551 | R275: =IF(O275="Pendente",_xlfn.XLOOKUP(relatorio[[#This Row],[Número]],Relatório_CTE!A:A,Relatório_CTE!B:B,"Sem CTE")," ") -> 4791 | S275: =IF(relatorio[[#This Row],[NFs Entrada - Winthor]]="Pendente",_xlfn.XLOOKUP(relatorio[[#This Row],[Número]],Relatório_CTE!A:A,Relatório_CTE!H:H,"Sem CTE")," ") -> 45918 | T275: =(IF(relatorio[[#This Row],[NFs Entrada - Winthor]]="Pendente",IF(relatorio[[#This Row],[Dt. CTE]]="Sem CTE",relatorio[[#This Row],[Data Emissão]]+_xlfn.XLOOKUP(relatorio[[#This Row],[De_Para]],'Lead Time - Histórico (Fornec.)'!B:B,'Lead Time - Histórico (Fornec.)'!C:C),relatorio[[#This Row],[Dt. CTE]]+_xlfn.XLOOKUP(relatorio[[#This Row],[Cód. Winthor]],'Lead Time - Histórico (Produto)'!A:A,'Lead Time - Histórico (Produto)'!C:C))," ")) -> 45918 | U275: =IFERROR(IF(WEEKDAY(relatorio[[#This Row],[Previsão de entrega - Bruto]],2)=6,relatorio[[#This Row],[Previsão de entrega - Bruto]]+2,IF(WEEKDAY(relatorio[[#This Row],[Previsão de entrega - Bruto]],2)=7,relatorio[[#This Row],[Previsão de entrega - Bruto]]+1,relatorio[[#This Row],[Previsão de entrega - Bruto]]))," ") -> 45918
